Workbook

Sheet 企业分析总览
A1: 岗位信息 v4 · 企业维度分析 | P1: 产业链层级 | Q1: 岗位数 | S1: 公司所属地区 | T1: 岗位数 | V1: 融资轮次 | W1: 岗位数 | Y1: 总部城市 | Z1: 岗位数 | AB1: 重点企业简称 | AC1: 岗位数 | AD1: 企业库标准名称 | AE1: 企业属性字段 | AF1: 完整率
A2: 企业属性以《具身智能企业数据_整合去重_完整.xlsx》为主数据；未匹配项留空，不以模型猜测补齐。统计口径：4,655条v4岗位事实。 | P2: 中游 | Q2: =COUNTIF(岗位信息v4_企业增强!$P$2:$P$4656,P2) -> 2925 | S2: 华东 | T2: =COUNTIF(岗位信息v4_企业增强!$S$2:$S$4656,S2) -> 1808 | V2: 已上市 | W2: =COUNTIF(岗位信息v4_企业增强!$R$2:$R$4656,V2) -> 2499 | Y2: 广东省深圳市南山区 | Z2: =COUNTIF(岗位信息v4_企业增强!$T$2:$T$4656,Y2) -> 791 | AB2: 蓝思科技 | AC2: =COUNTIF(岗位信息v4_企业增强!$AK$2:$AK$4656,AD2) -> 762 | AD2: 蓝思科技股份有限公司 | AE2: 产业链层级 | AF2: =COUNTIF(岗位信息v4_企业增强!$P$2:$P$4656,"<>")/COUNTA(岗位信息v4_企业增强!$B$2:$B$4656) -> 1
P3: 上游 | Q3: =COUNTIF(岗位信息v4_企业增强!$P$2:$P$4656,P3) -> 1156 | S3: 华南 | T3: =COUNTIF(岗位信息v4_企业增强!$S$2:$S$4656,S3) -> 955 | V3: C轮 | W3: =COUNTIF(岗位信息v4_企业增强!$R$2:$R$4656,V3) -> 645 | Y3: 湖南省长沙市浏阳永安园区 | Z3: =COUNTIF(岗位信息v4_企业增强!$T$2:$T$4656,Y3) -> 762 | AB3: 智元创新科技 | AC3: =COUNTIF(岗位信息v4_企业增强!$AK$2:$AK$4656,AD3) -> 567 | AD3: 智元创新（上海）科技股份有限公司 | AE3: 公司细分领域 | AF3: =COUNTIF(岗位信息v4_企业增强!$Q$2:$Q$4656,"<>")/COUNTA(岗位信息v4_企业增强!$B$2:$B$4656) -> 1
A4: 岗位事实 | D4: 企业库已匹配岗位 | G4: 岗位匹配覆盖率 | J4: 已关联企业实体 | M4: 待核验/待补全岗位 | P4: 横向支撑 | Q4: =COUNTIF(岗位信息v4_企业增强!$P$2:$P$4656,P4) -> 287 | S4: 华中 | T4: =COUNTIF(岗位信息v4_企业增强!$S$2:$S$4656,S4) -> 768 | V4: A轮 | W4: =COUNTIF(岗位信息v4_企业增强!$R$2:$R$4656,V4) -> 496 | Y4: 上海市临港新片区 | Z4: =COUNTIF(岗位信息v4_企业增强!$T$2:$T$4656,Y4) -> 567 | AB4: 优必选科技 | AC4: =COUNTIF(岗位信息v4_企业增强!$AK$2:$AK$4656,AD4) -> 457 | AD4: 深圳市优必选科技股份有限公司 | AE4: 融资轮次 | AF4: =COUNTIF(岗位信息v4_企业增强!$R$2:$R$4656,"<>")/COUNTA(岗位信息v4_企业增强!$B$2:$B$4656) -> 1
A5: =COUNTA(岗位信息v4_企业增强!$B$2:$B$4656) -> 4655 | D5: =COUNTIF(岗位信息v4_企业增强!$AN$2:$AN$4656,"已匹配") -> 4472 | G5: =D5/A5 -> 0.96068743 | J5: =COUNTIF(企业岗位汇总!$B$2:$B$634,">0") -> 103 | M5: =A5-D5 -> 183 | P5: 下游 | Q5: =COUNTIF(岗位信息v4_企业增强!$P$2:$P$4656,P5) -> 104 | S5: 华北 | T5: =COUNTIF(岗位信息v4_企业增强!$S$2:$S$4656,S5) -> 368 | V5: B轮 | W5: =COUNTIF(岗位信息v4_企业增强!$R$2:$R$4656,V5) -> 400 | Y5: 江苏省苏州市吴中区 | Z5: =COUNTIF(岗位信息v4_企业增强!$T$2:$T$4656,Y5) -> 388 | AB5: 追觅 | AC5: =COUNTIF(岗位信息v4_企业增强!$AK$2:$AK$4656,AD5) -> 386 | AD5: 追觅科技（苏州）有限公司 | AE5: 公司所属地区 | AF5: =COUNTIF(岗位信息v4_企业增强!$S$2:$S$4656,"<>")/COUNTA(岗位信息v4_企业增强!$B$2:$B$4656) -> 1
S6: 西南 | T6: =COUNTIF(岗位信息v4_企业增强!$S$2:$S$4656,S6) -> 265 | V6: 天使轮/种子轮 | W6: =COUNTIF(岗位信息v4_企业增强!$R$2:$R$4656,V6) -> 189 | Y6: 北京市海淀区 | Z6: =COUNTIF(岗位信息v4_企业增强!$T$2:$T$4656,Y6) -> 347 | AB6: 惠科 | AC6: =COUNTIF(岗位信息v4_企业增强!$AK$2:$AK$4656,AD6) -> 265 | AD6: 惠科股份有限公司 | AE6: 公司总部城市 | AF6: =COUNTIF(岗位信息v4_企业增强!$T$2:$T$4656,"<>")/COUNTA(岗位信息v4_企业增强!$B$2:$B$4656) -> 1
S7: 海外 | T7: =COUNTIF(岗位信息v4_企业增强!$S$2:$S$4656,S7) -> 156 | V7: 央企/国企/事业单位 | W7: =COUNTIF(岗位信息v4_企业增强!$R$2:$R$4656,V7) -> 162 | Y7: 重庆市巴南区 | Z7: =COUNTIF(岗位信息v4_企业增强!$T$2:$T$4656,Y7) -> 265 | AB7: 上海禾赛 | AC7: =COUNTIF(岗位信息v4_企业增强!$AK$2:$AK$4656,AD7) -> 255 | AD7: 上海禾赛科技有限公司
A8: 一眼读懂：v4岗位事实 → 企业名称治理 → 企业库唯一实体 → 产业链/细分领域/融资/地区/总部城市 → 岗位簇与人岗匹配。精确或人工确认别名直接使用；唯一包含匹配标记为中置信；多候选与未匹配项进入待办表。 | S8: 东北 | T8: =COUNTIF(岗位信息v4_企业增强!$S$2:$S$4656,S8) -> 149 | V8: 拟上市/Pre-IPO | W8: =COUNTIF(岗位信息v4_企业增强!$R$2:$R$4656,V8) -> 44 | Y8: 上海市嘉定区 | Z8: =COUNTIF(岗位信息v4_企业增强!$T$2:$T$4656,Y8) -> 255 | AB8: 宇树科技 | AC8: =COUNTIF(岗位信息v4_企业增强!$AK$2:$AK$4656,AD8) -> 172 | AD8: 宇树科技股份有限公司
S9: 港澳台 | T9: =COUNTIF(岗位信息v4_企业增强!$S$2:$S$4656,S9) -> 3 | V9: D轮及以上 | W9: =COUNTIF(岗位信息v4_企业增强!$R$2:$R$4656,V9) -> 26 | Y9: 浙江省杭州市滨江区 | Z9: =COUNTIF(岗位信息v4_企业增强!$T$2:$T$4656,Y9) -> 216 | AB9: 北京清微智能科技 | AC9: =COUNTIF(岗位信息v4_企业增强!$AK$2:$AK$4656,AD9) -> 158 | AD9: 北京清微智能科技股份有限公司
V10: 未融资/未公开 | W10: =COUNTIF(岗位信息v4_企业增强!$R$2:$R$4656,V10) -> 7 | Y10: 吉林省长春市北湖科技开发区 | Z10: =COUNTIF(岗位信息v4_企业增强!$T$2:$T$4656,Y10) -> 149 | AB10: 吉翼具身智能机器人 | AC10: =COUNTIF(岗位信息v4_企业增强!$AK$2:$AK$4656,AD10) -> 149 | AD10: 吉林省吉翼具身智能机器人有限公司
V11: 未披露 | W11: =COUNTIF(岗位信息v4_企业增强!$R$2:$R$4656,V11) -> 2 | Y11: 浙江省杭州市西湖区 | Z11: =COUNTIF(岗位信息v4_企业增强!$T$2:$T$4656,Y11) -> 109 | AB11: 自变量科技 | AC11: =COUNTIF(岗位信息v4_企业增强!$AK$2:$AK$4656,AD11) -> 112 | AD11: 自变量科技（深圳）股份有限公司
V12: 不适用(美的集团控制 | W12: =COUNTIF(岗位信息v4_企业增强!$R$2:$R$4656,V12) -> 1 | Y12: 广东省深圳市前海深港合作区 | Z12: =COUNTIF(岗位信息v4_企业增强!$T$2:$T$4656,Y12) -> 100
V13: D轮 | W13: =COUNTIF(岗位信息v4_企业增强!$R$2:$R$4656,V13) -> 1 | Y13: 浙江省杭州市余杭区 | Z13: =COUNTIF(岗位信息v4_企业增强!$T$2:$T$4656,Y13) -> 99
A49: 职业方向 × 产业链层级：岗位需求落点
A51: 职业方向 | B51: 中游 | C51: 上游 | D51: 横向支撑 | E51: 下游 | H51: 企业库关联结论：当前4,655条岗位中，4,472条已关联企业库，覆盖率96.1%；共关联102个企业实体。未匹配与多候选数据未强行赋值，均进入“企业待补全”。
A52: 基础理论与前沿研究 | B52: =COUNTIFS(岗位信息v4_企业增强!$N$2:$N$4656,$A52,岗位信息v4_企业增强!$P$2:$P$4656,B$51) -> 83 | C52: =COUNTIFS(岗位信息v4_企业增强!$N$2:$N$4656,$A52,岗位信息v4_企业增强!$P$2:$P$4656,C$51) -> 31 | D52: =COUNTIFS(岗位信息v4_企业增强!$N$2:$N$4656,$A52,岗位信息v4_企业增强!$P$2:$P$4656,D$51) -> 6 | E52: =COUNTIFS(岗位信息v4_企业增强!$N$2:$N$4656,$A52,岗位信息v4_企业增强!$P$2:$P$4656,E$51) -> 1
A53: 仿真测试与数据工程 | B53: =COUNTIFS(岗位信息v4_企业增强!$N$2:$N$4656,$A53,岗位信息v4_企业增强!$P$2:$P$4656,B$51) -> 160 | C53: =COUNTIFS(岗位信息v4_企业增强!$N$2:$N$4656,$A53,岗位信息v4_企业增强!$P$2:$P$4656,C$51) -> 38 | D53: =COUNTIFS(岗位信息v4_企业增强!$N$2:$N$4656,$A53,岗位信息v4_企业增强!$P$2:$P$4656,D$51) -> 67 | E53: =COUNTIFS(岗位信息v4_企业增强!$N$2:$N$4656,$A53,岗位信息v4_企业增强!$P$2:$P$4656,E$51) -> 7
A54: 软件硬件与系统架构 | B54: =COUNTIFS(岗位信息v4_企业增强!$N$2:$N$4656,$A54,岗位信息v4_企业增强!$P$2:$P$4656,B$51) -> 1171 | C54: =COUNTIFS(岗位信息v4_企业增强!$N$2:$N$4656,$A54,岗位信息v4_企业增强!$P$2:$P$4656,C$51) -> 885 | D54: =COUNTIFS(岗位信息v4_企业增强!$N$2:$N$4656,$A54,岗位信息v4_企业增强!$P$2:$P$4656,D$51) -> 69 | E54: =COUNTIFS(岗位信息v4_企业增强!$N$2:$N$4656,$A54,岗位信息v4_企业增强!$P$2:$P$4656,E$51) -> 19
A55: 感知决策与控制算法 | B55: =COUNTIFS(岗位信息v4_企业增强!$N$2:$N$4656,$A55,岗位信息v4_企业增强!$P$2:$P$4656,B$51) -> 1117 | C55: =COUNTIFS(岗位信息v4_企业增强!$N$2:$N$4656,$A55,岗位信息v4_企业增强!$P$2:$P$4656,C$51) -> 142 | D55: =COUNTIFS(岗位信息v4_企业增强!$N$2:$N$4656,$A55,岗位信息v4_企业增强!$P$2:$P$4656,D$51) -> 28 | E55: =COUNTIFS(岗位信息v4_企业增强!$N$2:$N$4656,$A55,岗位信息v4_企业增强!$P$2:$P$4656,E$51) -> 53
A56: 部署运维与技术支持 | B56: =COUNTIFS(岗位信息v4_企业增强!$N$2:$N$4656,$A56,岗位信息v4_企业增强!$P$2:$P$4656,B$51) -> 214 | C56: =COUNTIFS(岗位信息v4_企业增强!$N$2:$N$4656,$A56,岗位信息v4_企业增强!$P$2:$P$4656,C$51) -> 34 | D56: =COUNTIFS(岗位信息v4_企业增强!$N$2:$N$4656,$A56,岗位信息v4_企业增强!$P$2:$P$4656,D$51) -> 81 | E56: =COUNTIFS(岗位信息v4_企业增强!$N$2:$N$4656,$A56,岗位信息v4_企业增强!$P$2:$P$4656,E$51) -> 15
A57: 产业支撑与运营 | B57: =COUNTIFS(岗位信息v4_企业增强!$N$2:$N$4656,$A57,岗位信息v4_企业增强!$P$2:$P$4656,B$51) -> 180 | C57: =COUNTIFS(岗位信息v4_企业增强!$N$2:$N$4656,$A57,岗位信息v4_企业增强!$P$2:$P$4656,C$51) -> 26 | D57: =COUNTIFS(岗位信息v4_企业增强!$N$2:$N$4656,$A57,岗位信息v4_企业增强!$P$2:$P$4656,D$51) -> 36 | E57: =COUNTIFS(岗位信息v4_企业增强!$N$2:$N$4656,$A57,岗位信息v4_企业增强!$P$2:$P$4656,E$51) -> 9

Sheet 岗位信息v4_企业增强
A1: 序号 | B1: occ_id | C1: group_id | D1: 公司 | E1: 关联公司 | F1: 岗位 | G1: 城市 | H1: 薪资 | I1: 学历(原始) | J1: 学历(标准化) | K1: 经验(原始) | L1: 经验(标准化) | M1: 能力等级 | N1: 职业方向 | O1: 职业种类 | P1: 产业链层级 | Q1: 公司细分领域 | R1: 融资轮次 | S1: 公司所属地区 | T1: 公司总部城市 | U1: 技能标签 | V1: 清洗JD描述 | W1: 链接 | X1: 发布时间 | Y1: 收录时间 | Z1: 来源列表 | AA1: 是否有有效JD | AB1: 数据来源批次 | AC1: 原始occ_id | AD1: 原始职业方向 | AE1: 原始职业种类 | AF1: 分类方式 | AG1: 分类置信度 | AH1: 发布状态 | AI1: 去重指纹 | AJ1: 处理说明 | AK1: 企业库标准名称 | AL1: 企业匹配方式 | AM1: 企业匹配置信度 | AN1: 企业属性补全状态 | AO1: 产业链12类 | AP1: 融资阶段(企业库原文) | AQ1: 企业库官网 | AR1: 企业库数据来源 | AS1: v4原产业链层级 | AT1: v4原公司细分领域 | AU1: v4原融资轮次 | AV1: v4原公司所属地区 | AW1: v4原公司总部城市
A2: 1 | B2: O00015 | C2: 6027 | D2: Google DeepMind | E2: Google DeepMind | F2: Staff AI Product Designer, Gemini Assistant, GeminiApp | J2: 未说明 | L2: 未说明 | M2: 高级 | N2: 基础理论与前沿研究 | O2: 基础与前沿研究 | P2: 中游 | Q2: 具身智能基础模型/VLA模型/机器人AI大脑 | R2: 央企/国企/事业单位 | S2: 海外 | T2: 美国 加利福尼亚州 山景城 | U2: 机器学习; 多模态; 嵌入式开发; CAN | V2: The Gemini App Design team is instrumental in building the Gemini Universal Assistant, the conversational AI that people around the world use to collaborate with generative AI to fuel their imagination, expand their curiosity, and enhance their productivity. We're building innovative ways for people to get things done & enrich their lives. Our Design team is dedicated to developing the world's useful generative AI experiences. At Google DeepMind, we aim to unlock state-of-the-art artificial intelligence capabilities across Alphabet, creating positive impact and magical product experiences for billions of users. We're a world-leading AI research company, pushing the boundaries of what's possible with artificial intelligence. Our groundbreaking research spans areas like machine learning, neuroscience, and systems engineering, with applications ranging from scientific discovery to creating more helpful and intuitive products. We're committed to developing AI responsibly and ethically, and we foster a collaborative and inclusive environment where brilliant minds come together to tackle some of the world's most challenging problems. Join us and be part of a team that's shaping the future of AI. The Integrated Assistance team contributes towards this mission by making Gemini a personalized universal assistant that is natively present across devices and apps. We unlock useful generative AI experiences through deep OS and app integrations, including the quick access Android overlay, embedded app entry points, and novel screen context capabilities. As shepherds of the largest volume surfaces in Gemini, we aim to guide users to understand the value of generative AI, including unique capabilities outside of the full screen Gemini app. We are a global team with designers based in Europe and US, and engineering and product partners in those locations as well as India. We partner closely with other UX designers in the Gemini App team, including research and modelling. Role We are seeking a highly experienced, self-starting, and innovative Staff AI Product Designer to join our Gemini Integrated Assistance Team. As a key member of our team, you will work hand-in-hand with engineers, research scientists, and product managers to design and build intuitive solutions to help people around the world use Google’s best AI models to enrich their lives and realize their potential. You will play a crucial role in shaping the future of how people interact with AI. You will be involved in all aspects of the design process, from conceptualization and ideation to prototyping and implementation in a fast-moving and highly collaborative environment. Responsibilities: Architect intuitive AI experiences: Lead the design of user interfaces and consumer experiences for Gemini across diverse platforms and modalities, ensuring natural and efficient interaction. Contribute to product strategy and manage stakeholders: Use strong communication skills to collaborate with Product, Engineering and influence relevant stakeholders (e.g. in Gemini App, Android, other Google Apps) to define product strategy and influence key cross-functional decisions that drive positive user outcomes. Innovate through user-centered design: Translate user needs, technical understanding and business requirements into groundbreaking design solutions that amplify people’s capabilities and enrich their lives. Design with systems-thinking approach: Apply a systems-thinking approach to design user interfaces, understanding the impact of individual components and features on the overall AI-powered experience, optimized for AI's probabilistic nature and multimodal capabilities. Craft visually compelling interfaces: Create high-fidelity visual designs, encompassing layouts, typography, color palettes, and iconography, that are aesthetically pleasing and highly usable. Motion and interaction design: Design engaging interactions and fluid interfaces, utilizing tools like Origami Studio, Principle, and Protopie, and create motion designs that enhance user experience and effectively communicate complex information. Bridge design and technology: Leverage technical understanding to use system instructions and diverse prototyping methods, simulating model responses to inform design requirements and approaches. Champion design innovation: Stay current on the latest design trends and technologies, in consumer technology, generative AI and natural language processing, and leverage this knowledge to innovate. Design for ethical and societal impact: Consider the intricate interplay of AI models, user interface, ethical considerations, and societal impacts to develop responsible solutions. Minimum Qualifications Bachelor's degree in Design, Human-Computer Interaction, or a related field. 7+ years of experience designing user interfaces for complex software applications, with specific experience designing for conversational AI / LLMs A robust portfolio showcasing fluency in visual, motion, and interaction design skills, with specific examples of work specific to AI-powered interfaces and interactions and for leading consumer applications. Proficiency in designing user-centric experiences across diverse platforms (web, desktop, mobile), with a strong understanding of how to adapt AI interactions to different device contexts. Demonstrated expertise in designing intuitive and engaging interactions for AI-driven products Demonstrated expertise in guiding cross-functional teams through ideation, validation, and iteration processes, transforming abstract ideas into shippable product Familiarity with behavioral data and strong capability to create data-driven designs, while being equally capable of moving forward in the absence of data. Proficiency in design tools such as Figma, Sketch, Adobe Creative Suite, and Principle. Excellent communication and collaboration skills with the ability to listen, articulate positions, and challenge partners with new product design thinking Mastery in presentation and storytelling capabilities with the ability to communicate effectively to leadership and cross company teams A strong systems thinker with a passion for creating innovative and user-centered AI design solutions. Ability to understand the broader implications of AI technologies and design experiences that are ethical, accessible, and impactful. Demonstrated experience thriving in a startup environment, comfortable with the ambiguity, rapid iteration, and resourcefulness required to deliver impactful designs in a fast-paced, evolving landscape. Preferred Qualifications Demonstrated ability to foster divergent design thinking and translate complex AI concepts into user-centered product visions. Proven experience in shepherding radical ideas that leverage AI to create truly transformative product experiences. Experience prototyping interactive experiences using tools like Figma, ProtoPie, or Framer. Experience vibe-coding with tools like Loveable, ReplitFigmaMake, AI Studio, Cursor or AntiGravity. Experience with front-end development technologies (HTML, CSS, JavaScript, React, Swift, Jetpack Compose) and coding tools (CLIs, IDEs). Demonstrable experience designing polished, highly performant mobile apps and experiences requiring OS integrations (Android, iOS). Experience driving product impact through close collaboration with user research, including expertise in user research methodologies for AI product evaluation. The US base salary range for this full-time position is between $178,000 USD - $265,000 + bonus + equity + benefits. Your recruiter can share more about the specific salary range for your targeted location during the hiring process. Application deadline: Note: In the event your application is successful and an offer of employment is made to you, any offer of employment will be conditional on the results of a background check, performed by a third party acting on our behalf. For more information on how we handle your data, please see our Applicant and Candidate Privacy Policy At Google DeepMind, we value diversity of experience, knowledge, backgrounds and perspectives and harness these qualities to create extraordinary impact. We are committed to equal employment opportunity regardless of sex, race, religion or belief, ethnic or national origin, disability, age, citizenship, marital, domestic or civil partnership status, sexual orientation, gender identity, pregnancy, or related condition (including breastfeeding) or any other basis as protected by applicable law. If you have a disability or additional need that requires accommodation, please do not hesitate to let us know. Create a Job AlertInterested in building your career at DeepMind? Get future opportunities sent straight to your email.Create alert | W2: https://job-boards.greenhouse.io/deepmind/jobs/7762107 | Z2: all_jobs_jd | AA2: 是 | AB2: 核心基线3718 | AC2: O00015 | AD2: 基础理论与前沿研究 | AE2: 基础与前沿研究 | AF2: 原始6方向/17种类标签 | AG2: 高 | AH2: 正式基线 | AI2: 0514c40b8f556477dd38 | AJ2: 核心基线标签直接沿用 | AK2: Google DeepMind Technologies Limited | AL2: 企业别名精确匹配 | AM2: 高 | AN2: 已匹配 | AO2: AI大模型 | AP2: 央企/国企；Alphabet内部（未独立融资） | AQ2: https://deepmind.google | AR2: Google DeepMind官网/TechSpot/The Robot Report | AS2: 中游-AI基础模型（具身大脑） | AT2: 具身智能基础模型/VLA模型/机器人AI大脑 | AU2: 央企/国企/事业单位 | AV2: 海外 | AW2: 美国加利福尼亚州山景城(Mountain View, CA); 英国伦敦
A3: 2 | B3: O00014 | C3: 6022 | D3: Google DeepMind | E3: Google DeepMind | F3: Staff AI Product Designer, Gemini Assistant | J3: 未说明 | L3: 未说明 | M3: 中级 | N3: 基础理论与前沿研究 | O3: 基础与前沿研究 | P3: 中游 | Q3: 具身智能基础模型/VLA模型/机器人AI大脑 | R3: 央企/国企/事业单位 | S3: 海外 | T3: 美国 加利福尼亚州 山景城 | U3: 机器学习; 多模态; CAN | V3: The Gemini App Design team is instrumental in building the Gemini Universal Assistant, the conversational AI that people around the world use to collaborate with generative AI to fuel their imagination, expand their curiosity, and enhance their productivity. We're building innovative ways for people to get things done & enrich their lives. Our Design team is dedicated to developing the world's useful generative AI experiences. At Google DeepMind, we aim to unlock state-of-the-art artificial intelligence capabilities across Alphabet, creating positive impact and magical product experiences for billions of users. We're a world-leading AI research company, pushing the boundaries of what's possible with artificial intelligence. Our groundbreaking research spans areas like machine learning, neuroscience, and systems engineering, with applications ranging from scientific discovery to creating more helpful and intuitive products. We're committed to developing AI responsibly and ethically, and we foster a collaborative and inclusive environment where brilliant minds come together to tackle some of the world's most challenging problems. Join us and be part of a team that's shaping the future of AI.Role We are seeking a highly experienced, self-starting, and innovative Senior AI Product Designer to join the Gemini App Team. As a key member of our team, you will work hand-in-hand with engineers, research scientists, and product managers to design and build intuitive solutions to help people around the world use Google’s best AI models to enrich their lives and realize their potential. You will play a crucial role in shaping the future of how people interact with AI. You will be involved in all aspects of the design process, from conceptualization and ideation to prototyping and implementation in a fast-moving and highly collaborative environment. Responsibilities: Architect intuitive AI experiences: Lead the design of user interfaces and consumer experiences for Gemini across diverse platforms and modalities, ensuring natural and efficient interaction. Key contributor to product strategy: Collaborate with Product and Engineering to define product strategy and influence key cross-functional decisions that drive positive user outcomes. Innovate through user-centered design: Translate user needs, technical understanding and business requirements into groundbreaking design solutions that amplify people’s capabilities and enrich their lives. Design with systems-thinking approach: Apply a systems-thinking approach to design user interfaces, understanding the impact of individual components and features on the overall AI-powered experience, optimized for AI's probabilistic nature and multimodal capabilities. Craft visually compelling interfaces: Create high-fidelity visual designs, encompassing layouts, typography, color palettes, and iconography, that are aesthetically pleasing and highly usable. Motion and interaction design: Design engaging interactions and fluid interfaces, utilizing tools like Origami Studio, Principle, and Protopie, and create motion designs that enhance user experience and effectively communicate complex information. Bridge design and technology: Leverage technical understanding to use system instructions and diverse prototyping methods, simulating model responses to inform design requirements and approaches. Champion design innovation: Stay current on the latest design trends and technologies, in consumer technology, generative AI and natural language processing, and leverage this knowledge to innovate. Design for ethical and societal impact: Consider the intricate interplay of AI models, user interface, ethical considerations, and societal impacts to develop responsible solutions. Minimum Qualifications Bachelor's degree in Design, Human-Computer Interaction, or a related field. 7+ years of experience designing user interfaces for complex software applications, with specific experience designing for conversational AI / LLMs A robust portfolio showcasing fluency in visual, motion, and interaction design skills, with specific examples of work specific to AI-powered interfaces and interactions and for leading consumer applications. Proficiency in designing user-centric experiences across diverse platforms (web, desktop, mobile), with a strong understanding of how to adapt AI interactions to different device contexts. Demonstrated expertise in designing intuitive and engaging interactions for AI-driven products Demonstrated expertise in guiding cross-functional teams through ideation, validation, and iteration processes, transforming abstract ideas into shippable product Familiarity with behavioral data and strong capability to create data-driven designs, while being equally capable of moving forward in the absence of data. Proficiency in design tools such as Figma, Sketch, Adobe Creative Suite, and Principle. Excellent communication and collaboration skills with the ability to listen, articulate positions, and challenge partners with new product design thinking Mastery in presentation and storytelling capabilities with the ability to communicate effectively to leadership and cross company teams A strong systems thinker with a passion for creating innovative and user-centered AI design solutions. Ability to understand the broader implications of AI technologies and design experiences that are ethical, accessible, and impactful. Demonstrated experience thriving in a startup environment, comfortable with the ambiguity, rapid iteration, and resourcefulness required to deliver impactful designs in a fast-paced, evolving landscape. Preferred Qualifications Demonstrated ability to foster divergent design thinking and translate complex AI concepts into user-centered product visions. Proven experience in shepherding radical ideas that leverage AI to create truly transformative product experiences. Experience prototyping interactive experiences using tools like Figma, ProtoPie, or Framer. Experience with front-end development technologies (HTML, CSS, JavaScript). Experience driving product impact through close collaboration with user research, including expertise in user research methodologies for AI product evaluation. Experience mentoring more junior teammates, but note this is not a manager role The US base salary range for this full-time position is between $178,000 USD - $265,000 + bonus + equity + benefits. Your recruiter can share more about the specific salary range for your targeted location during the hiring process. Application deadline: Note: In the event your application is successful and an offer of employment is made to you, any offer of employment will be conditional on the results of a background check, performed by a third party acting on our behalf. For more information on how we handle your data, please see our Applicant and Candidate Privacy Policy At Google DeepMind, we value diversity of experience, knowledge, backgrounds and perspectives and harness these qualities to create extraordinary impact. We are committed to equal employment opportunity regardless of sex, race, religion or belief, ethnic or national origin, disability, age, citizenship, marital, domestic or civil partnership status, sexual orientation, gender identity, pregnancy, or related condition (including breastfeeding) or any other basis as protected by applicable law. If you have a disability or additional need that requires accommodation, please do not hesitate to let us know.Create a Job AlertInterested in building your career at DeepMind? Get future opportunities sent straight to your email.Create alert | W3: https://job-boards.greenhouse.io/deepmind/jobs/7561947 | Z3: all_jobs_jd | AA3: 是 | AB3: 核心基线3718 | AC3: O00014 | AD3: 基础理论与前沿研究 | AE3: 基础与前沿研究 | AF3: 原始6方向/17种类标签 | AG3: 高 | AH3: 正式基线 | AI3: 444d925042f718d5fb79 | AJ3: 核心基线标签直接沿用 | AK3: Google DeepMind Technologies Limited | AL3: 企业别名精确匹配 | AM3: 高 | AN3: 已匹配 | AO3: AI大模型 | AP3: 央企/国企；Alphabet内部（未独立融资） | AQ3: https://deepmind.google | AR3: Google DeepMind官网/TechSpot/The Robot Report | AS3: 中游-AI基础模型（具身大脑） | AT3: 具身智能基础模型/VLA模型/机器人AI大脑 | AU3: 央企/国企/事业单位 | AV3: 海外 | AW3: 美国加利福尼亚州山景城(Mountain View, CA); 英国伦敦
A4: 3 | B4: O00016 | C4: 6026 | D4: Google DeepMind | E4: Google DeepMind | F4: Staff AI Product Designer, Growth & Discovery, GeminiApp | J4: 未说明 | L4: 未说明 | M4: 高级 | N4: 基础理论与前沿研究 | O4: 基础与前沿研究 | P4: 中游 | Q4: 具身智能基础模型/VLA模型/机器人AI大脑 | R4: 央企/国企/事业单位 | S4: 海外 | T4: 美国 加利福尼亚州 山景城 | U4: 机器学习; 多模态; CAN | V4: At Google DeepMind, we aim to unlock state-of-the-art artificial intelligence capabilities across Alphabet, creating positive impact and magical product experiences for billions of users. We're a world-leading AI research company, pushing the boundaries of what's possible with artificial intelligence. Our groundbreaking research spans areas like machine learning, neuroscience, and systems engineering, with applications ranging from scientific discovery to creating more helpful and intuitive products. We're committed to developing AI responsibly and ethically, and we foster a collaborative and inclusive environment where brilliant minds come together to tackle some of the world's most challenging problems. Join us and be part of a team that's shaping the future of AI.Role We are seeking a highly experienced, self-starting, and innovative Staff AI Product Designer focusing on our Growth and Discovery initiatives. As a key member of our team, you will work hand-in-hand with engineers, research scientists, and product managers to design and build intuitive solutions to help people around the world use Google’s best AI models to enrich their lives and realize their potential. You will play a crucial role in shaping the future of how people interact with AI. You will be involved in all aspects of the design process, from conceptualization and ideation to prototyping and implementation in a fast-moving and highly collaborative environment. Responsibilities: Architect intuitive AI experiences: Lead the design of user interfaces and consumer experiences for Gemini across diverse platforms and modalities, ensuring natural and efficient interaction. Key contributor to product strategy: Collaborate with Product and Engineering to define product strategy and influence key cross-functional decisions that drive positive user outcomes. Innovate through user-centered design: Translate user needs, technical understanding and business requirements into groundbreaking design solutions that amplify people’s capabilities and enrich their lives. Design with systems-thinking approach: Apply a systems-thinking approach to design user interfaces, understanding the impact of individual components and features on the overall AI-powered experience, optimized for AI's probabilistic nature and multimodal capabilities. Craft visually compelling interfaces: Create high-fidelity visual designs, encompassing layouts, typography, color palettes, and iconography, that are aesthetically pleasing and highly usable. Motion and interaction design: Design engaging interactions and fluid interfaces, utilizing tools like Origami Studio, Principle, and Protopie, and create motion designs that enhance user experience and effectively communicate complex information. Bridge design and technology: Leverage technical understanding to use system instructions and diverse prototyping methods, simulating model responses to inform design requirements and approaches. Champion design innovation: Stay current on the latest design trends and technologies, in consumer technology, generative AI and natural language processing, and leverage this knowledge to innovate. Design for ethical and societal impact: Consider the intricate interplay of AI models, user interface, ethical considerations, and societal impacts to develop responsible solutions. Minimum Qualifications Bachelor's degree in Design, Human-Computer Interaction, or a related field. 7+ years of experience designing user interfaces for complex software applications, with specific experience designing for conversational AI / LLMs A robust portfolio showcasing fluency in visual, motion, and interaction design skills, with specific examples of work specific to AI-powered interfaces and interactions and for leading consumer applications. Proficiency in designing user-centric experiences across diverse platforms (web, desktop, mobile), with a strong understanding of how to adapt AI interactions to different device contexts. Demonstrated expertise in designing intuitive and engaging interactions for AI-driven products Demonstrated expertise in guiding cross-functional teams through ideation, validation, and iteration processes, transforming abstract ideas into shippable product Familiarity with behavioral data and strong capability to create data-driven designs, while being equally capable of moving forward in the absence of data. Proficiency in design tools such as Figma, Sketch, Adobe Creative Suite, and Principle. Excellent communication and collaboration skills with the ability to listen, articulate positions, and challenge partners with new product design thinking Mastery in presentation and storytelling capabilities with the ability to communicate effectively to leadership and cross company teams A strong systems thinker with a passion for creating innovative and user-centered AI design solutions. Ability to understand the broader implications of AI technologies and design experiences that are ethical, accessible, and impactful. Demonstrated experience thriving in a startup environment, comfortable with the ambiguity, rapid iteration, and resourcefulness required to deliver impactful designs in a fast-paced, evolving landscape. Preferred Qualifications Demonstrated ability to foster divergent design thinking and translate complex AI concepts into user-centered product visions. Proven experience in shepherding radical ideas that leverage AI to create truly transformative product experiences. Experience prototyping interactive experiences using tools like Figma, ProtoPie, or Framer. Experience with front-end development technologies (HTML, CSS, JavaScript). Experience driving product impact through close collaboration with user research, including expertise in user research methodologies for AI product evaluation. The US base salary range for this full-time position is between $178,000 USD - $265,000 + bonus + equity + benefits. Your recruiter can share more about the specific salary range for your targeted location during the hiring process. Application deadline: Note: In the event your application is successful and an offer of employment is made to you, any offer of employment will be conditional on the results of a background check, performed by a third party acting on our behalf. For more information on how we handle your data, please see our Applicant and Candidate Privacy Policy At Google DeepMind, we value diversity of experience, knowledge, backgrounds and perspectives and harness these qualities to create extraordinary impact. We are committed to equal employment opportunity regardless of sex, race, religion or belief, ethnic or national origin, disability, age, citizenship, marital, domestic or civil partnership status, sexual orientation, gender identity, pregnancy, or related condition (including breastfeeding) or any other basis as protected by applicable law. If you have a disability or additional need that requires accommodation, please do not hesitate to let us know.Create a Job AlertInterested in building your career at DeepMind? Get future opportunities sent straight to your email.Create alert | W4: https://job-boards.greenhouse.io/deepmind/jobs/7728122 | Z4: all_jobs_jd | AA4: 是 | AB4: 核心基线3718 | AC4: O00016 | AD4: 基础理论与前沿研究 | AE4: 基础与前沿研究 | AF4: 原始6方向/17种类标签 | AG4: 高 | AH4: 正式基线 | AI4: 22c635254556cae53728 | AJ4: 核心基线标签直接沿用 | AK4: Google DeepMind Technologies Limited | AL4: 企业别名精确匹配 | AM4: 高 | AN4: 已匹配 | AO4: AI大模型 | AP4: 央企/国企；Alphabet内部（未独立融资） | AQ4: https://deepmind.google | AR4: Google DeepMind官网/TechSpot/The Robot Report | AS4: 中游-AI基础模型（具身大脑） | AT4: 具身智能基础模型/VLA模型/机器人AI大脑 | AU4: 央企/国企/事业单位 | AV4: 海外 | AW4: 美国加利福尼亚州山景城(Mountain View, CA); 英国伦敦
A5: 4 | B5: O00012 | C5: 6025 | D5: Google DeepMind | E5: Google DeepMind | F5: Research Scientist, Multimodal Alignment, Safety, and Fairness | J5: 未说明 | L5: 未说明 | M5: 中级 | N5: 基础理论与前沿研究 | O5: 基础与前沿研究 | P5: 中游 | Q5: 具身智能基础模型/VLA模型/机器人AI大脑 | R5: 央企/国企/事业单位 | S5: 海外 | T5: 美国 加利福尼亚州 山景城 | U5: Python; JAX; 强化学习; 深度学习; 机器学习; 计算机视觉; 多模态; CAN; Prompt Engineering | V5: We are seeking strong Research Scientists with expertise in AI research and experience in interdisciplinary sociotechnical modeling to join a multimodal safety research effort within Google DeepMind's Frontier AI unit. This role requires a passion for understanding and modeling the interactions between AI and society, a strong awareness of the AI alignment and safety landscape, and a penchant for developing novel ideas, methods, interfaces, and tools. This is a unique opportunity to contribute to impactful research and advance Google DeepMind's mission towards Artificial General Intelligence (AGI). About us Artificial Intelligence could be one of humanity’s most useful inventions. At Google DeepMind, we’re a team of scientists, engineers, machine learning experts and more, working together to advance the state of the art in artificial intelligence and ultimately achieve Artificial General Intelligence. We use our technologies for widespread public benefit and scientific discovery, and collaborate with others on critical challenges, ensuring safety and ethics are the highest priority. We’re a dedicated scientific community, committed to “solving intelligence” and ensuring our technology is used for widespread public benefit. We’ve built a supportive and inclusive environment where collaboration is encouraged and learning is shared freely. We don’t set limits based on what others think is possible or impossible. We drive ourselves and inspire each other to push boundaries and achieve ambitious goals. Our team is a part of Google DeepMind's Frontier AI unit. We have a mission to advance the frontiers of safety and inclusion in multimodal AI, build new capabilities into Google's flagship models and products, and break new ground on AI alignment. We approach alignment research with an ecosystem view, partnering across the development and deployment cycle and grounding our work in real-world impact on global users and communities. We are a research team with a mandate to invest in longer term bets and explore innovative approaches that deliver breakthrough improvements to models (Gemini) and products. Our work is at the frontier of augmented oversight for multimodal AI, and our research advances have directly impacted multiple versions of Gemini and Nano Banana models. The role We are seeking strong Research Scientists with expertise in AI research and experience in interdisciplinary sociotechnical modeling, to lead new breakthrough research directions. You will join a team working to supercharge exploration, assessment, and steering of evolving AI behaviors, with a focus on subjective and creative tasks. You will tackle the underlying research questions to improve collaborative specification of alignment objectives and assessment of adherence to desired behaviors. You will research new methods to enable AI agents to monitor real-world social context and dynamically evaluate and evolve system behaviors over long time-horizons. You’ll develop new paradigms for human+AI rating that considers systemic behaviors, adapts to human feedback, and proactively seeks context. Research Scientists at Google DeepMind lead the development of novel tools and algorithms to solve Artificial General Intelligence. Joining from top academic or industrial labs, they collaborate across fields to tackle fundamental AI questions using expertise in deep learning, computer vision, and generative architectures. This role requires independent judgment to navigate complex, ambiguous problems and explore diverse technical avenues. Your work will drive breakthroughs within GDM, Google products, and the AI alignment community. Key responsibilities Research: Generate new ideas, keep up with the state of the art in the field, discuss research directions with other researchers. Execute: Design, rapidly implement, and rigorously evaluate cutting-edge ideas, methods, interfaces, and tools to explore new sociotechnical AI systems. Communicate: Report and present research findings and developments clearly and efficiently both internally and externally, verbally and in writing. Collaborate: Suggest and engage in inter- and intra- team collaborations to meet ambitious research goals, while also driving significant individual contributions. Drive technical projects: Take ownership of substantial technical projects, from ideation and design to implementation and evaluation, often involving cross-functional collaboration. About you In order to set you up for success as a Research Scientist at Google DeepMind, we look for the following skills and experience: Requirements: PhD degree in Computer Science, Machine Learning, or a related technical field. Strong publication record in top machine learning conferences (e.g., NeurIPS, CVPR, ICML, ICLR, ICCV, ECCV). Demonstrated hands-on experience in developing multimodal AI models and systems, Strong programming skills in Python and experience with at least one major deep learning framework (e.g., JAX/Flax/Gemax) Experience conducting independent research and development, including experimental design, implementation, and analysis. In addition, the following would be an advantage: Proven expertise in working with and tuning large-scale vision language models. Experience prototyping with VLMs with modern prompting strategies Experience finetuning and post-training LLMs using RL Experience with developing agentic AI solutions to complex problems Excited to collaborate across orgs and disciplines to leverage diverse perspectives and expertise and find creative solutions. Interest and a strong awareness of the AI alignment / safety / responsibility / fairness landscape Experience with Generative AI techniques and architectures. Familiarity with Reinforcement Learning or alignment methods. Experience with multimodal learning, integrating information from different data types (e.g., vision, audio, text). The US base salary range for this full-time position is between 147,000 USD - 211,000 USD + bonus + equity + benefits. Your recruiter can share more about the specific salary range for your targeted location during the hiring process. Note: In the event your application is successful and an offer of employment is made to you, any offer of employment will be conditional on the results of a background check, performed by a third party acting on our behalf. For more information on how we handle your data, please see our Applicant and Candidate Privacy Policy. At Google DeepMind, we value diversity of experience, knowledge, backgrounds and perspectives and harness these qualities to create extraordinary impact. We are committed to equal employment opportunities regardless of sex, race, religion or belief, ethnic or national origin, disability, age, citizenship, marital, domestic or civil partnership status, sexual orientation, gender identity, pregnancy, or related condition (including breastfeeding) or any other basis as protected by applicable law. If you have a disability or additional need that requires accommodation, please do not hesitate to let us know.Create a Job AlertInterested in building your career at DeepMind? Get future opportunities sent straight to your email.Create alert | W5: https://job-boards.greenhouse.io/deepmind/jobs/7680885 | Z5: all_jobs_jd | AA5: 是 | AB5: 核心基线3718 | AC5: O00012 | AD5: 基础理论与前沿研究 | AE5: 基础与前沿研究 | AF5: 原始6方向/17种类标签 | AG5: 高 | AH5: 正式基线 | AI5: 74b2bdafc78c6e83202a | AJ5: 核心基线标签直接沿用 | AK5: Google DeepMind Technologies Limited | AL5: 企业别名精确匹配 | AM5: 高 | AN5: 已匹配 | AO5: AI大模型 | AP5: 央企/国企；Alphabet内部（未独立融资） | AQ5: https://deepmind.google | AR5: Google DeepMind官网/TechSpot/The Robot Report | AS5: 中游-AI基础模型（具身大脑） | AT5: 具身智能基础模型/VLA模型/机器人AI大脑 | AU5: 央企/国企/事业单位 | AV5: 海外 | AW5: 美国加利福尼亚州山景城(Mountain View, CA); 英国伦敦
A6: 5 | B6: O00018 | C6: 6021 | D6: Google DeepMind | E6: Google DeepMind | F6: Tech Strategy Director, Compute, Google DeepMind | J6: 未说明 | L6: 未说明 | M6: 高级 | N6: 基础理论与前沿研究 | O6: 基础与前沿研究 | P6: 中游 | Q6: 具身智能基础模型/VLA模型/机器人AI大脑 | R6: 央企/国企/事业单位 | S6: 海外 | T6: 美国 加利福尼亚州 山景城 | U6: 机器学习; 动力学; CAN | V6: This is a critical and high impact strategic role that will drive AI strategy, infrastructure investments and AI product portfolio optimization across Google. The role sits within Google DeepMind’s Technology Strategy (TechStrat) function and is a leadership role within Techstrat’s Compute team. Since compute has become the key ingredient for AI model leadership, AI serving success and next generation AI research, this leader will drive high impact decisions that will define the success of Google, with implications on the future of AI for the world. About us Artificial Intelligence could be one of humanity’s most useful inventions. At Google DeepMind, we’re a team of scientists, engineers, machine learning experts and more, working together to advance the state of the art in artificial intelligence. We use our technologies for widespread public benefit and scientific discovery, and collaborate with others on critical challenges, ensuring safety and ethics are the highest priority. The role As one of the key senior leaders of the compute Tech Strategy team, this role will own the success of our AI strategy by driving the maximal product impact for Google and AI impact for humanity. This leader will have the responsibility of framing key strategic decisions for our SVP+ leadership group based on deep analysis of the situation including value at stake from AI investments, investment optimization options, Industry understanding, financial modeling, product strategy analysis and understanding. They will be constantly looking for opportunities to push the envelope of impact from our investments in AI and inspire the team to do the same. This leader will also drive the synthesis of the situation into SVP+ consumable frameworks and crisp grounded and data backed options. They will then ensure the strategy is executed flawlessly partnering with a multitude of cross functional teams and stakeholders. Key responsibilities Personally drive and amplify impact through leading a team to Investigate and drive clarity on some of Google’s hardest long range strategic questions in AI Create new and partner with existing virtual teams across Google to create comprehensive product and policy plans that stand the test of time Model scenarios and various tradeoffs to create opinionated strategies for maximizing AI value and optimizing AI investments across Google Create SVP+ forum content (presentations, communications, mandates) Help develop a per-mandate monitoring view to keep programs accountable Collaborate with operational teams and forums in AI to ensure that company-wide SVP+mandates are set up for success -- well organized, staffed and delivering on desired goals. Stay connected across Google to maintain a living catalog of ongoing experiments & proposed innovations that may become worthy of discussion at NRC Identify gaps in our processes and information and propose/implement solutions. About you Are you a PM who thrives as both a central hub orchestrating complex and long running investigations AND a rapid iteration IC who can quickly create something out of nothing and move on to the next thing? This is the job for you. In both cases, you must be able to concisely communicate the merits & risks of multiple scenarios in documents that will get circulated broadly and to some of the most senior folks at the company. If you have high energy, a positive attitude, strong tech judgment, excellent interpersonal skills, and are excited to handle complex pan-Google topics and SVP audiences, this job will offer an opportunity to have a massive company-wide impact. In order to set you up for success as a Product Manager at DeepMind, we look for the following skills and experience: BA/BS degree in Computer Science/ EE or equivalent practical experience in a technical and/or business area 15+ years of product management experience for a technology-driven company, at scale, including a proven track record in driving 0->1 product capabilities and founding or incubating new, high-impact technical initiatives. Exceptional organizational talent running high velocity, high impact, strategic programs Stellar verbal and written communication; past experience with SVP/VP+ level audiences Extensive experience in product operations and business strategy Strong analytics, strategy, and data fluency experience Experience in a role that deals with machine learning and/or compute Innovative problem solver that can turn ambiguous problem spaces into clear solutions Ability to influence without direct authority, you adeptly work on and with technical and cross-functional or highly matrixed teams in a way that leads to aligned decision making In addition, the following would be an advantage: Familiarity with the role of compute and data in building LLMs and the capabilities of these models Strong product vision and sensibility, ideally with prior and proven experience embedding applied AI capabilities into products and a track record of leveraging AI productivity tools 5+ years of product strategy work experience in managing highly-complex, technically-challenging projects spanning a wide set of stakeholders A quantitative and analytical mentality to understand Google PA and external user needs Experience navigating sensitive organizational dynamics Collaborating within data-driven or quantitative-focused teams A consistent record of creative problem solving and a bias towards action Outstanding business judgment Outstanding organizational, prioritization, and multitasking skills. Excellent communication skills A proven track record of building positive relationships with senior stakeholders and influencing strong personalities within a complex business environment Experience in corporate planning Ability to manage multiple concurrent complex interactions with geographically disparate teams Past people management experience; Experience in hiring and leading teams, including distributed teams At Google DeepMind, we value diversity of experience, knowledge, backgrounds and perspectives and harness these qualities to create extraordinary impact. We are committed to equal employment opportunities regardless of sex, race, religion or belief, ethnic or national origin, disability, age, citizenship, marital, domestic or civil partnership status, sexual orientation, gender identity, pregnancy, or related condition (including breastfeeding) or any other basis as protected by applicable law. If you have a disability or additional need that requires accommodation, please do not hesitate to let us know. Application deadline: 13th Feb 2026 Note: In the event your application is successful and an offer of employment is made to you, any offer of employment will be conditional on the results of a background check, performed by a third party acting on our behalf. For more information on how we handle your data, please see our Applicant and Candidate Privacy Policy.Create a Job AlertInterested in building your career at DeepMind? Get future opportunities sent straight to your email.Create alert | W6: https://job-boards.greenhouse.io/deepmind/jobs/7535866 | Z6: all_jobs_jd | AA6: 是 | AB6: 核心基线3718 | AC6: O00018 | AD6: 基础理论与前沿研究 | AE6: 基础与前沿研究 | AF6: 原始6方向/17种类标签 | AG6: 高 | AH6: 正式基线 | AI6: 4f25750961905128011c | AJ6: 核心基线标签直接沿用 | AK6: Google DeepMind Technologies Limited | AL6: 企业别名精确匹配 | AM6: 高 | AN6: 已匹配 | AO6: AI大模型 | AP6: 央企/国企；Alphabet内部（未独立融资） | AQ6: https://deepmind.google | AR6: Google DeepMind官网/TechSpot/The Robot Report | AS6: 中游-AI基础模型（具身大脑） | AT6: 具身智能基础模型/VLA模型/机器人AI大脑 | AU6: 央企/国企/事业单位 | AV6: 海外 | AW6: 美国加利福尼亚州山景城(Mountain View, CA); 英国伦敦
A7: 6 | B7: O00019 | C7: 6019 | D7: Google DeepMind | E7: Google DeepMind | F7: Research Engineer, Materials Science | J7: 未说明 | L7: 未说明 | M7: 初级 | N7: 基础理论与前沿研究 | O7: 基础与前沿研究 | P7: 中游 | Q7: 具身智能基础模型/VLA模型/机器人AI大脑 | R7: 央企/国企/事业单位 | S7: 海外 | T7: 美国 加利福尼亚州 山景城 | U7: PyTorch; TensorFlow; JAX; LLM; 深度学习; 机器学习; Diffusion; 动力学; 仿真; 嵌入式开发; CAN | V7: At Google DeepMind, we value diversity of experience, knowledge, backgrounds and perspectives and harness these qualities to create extraordinary impact. We are committed to equal employment opportunities regardless of sex, race, religion or belief, ethnic or national origin, disability, age, citizenship, marital, domestic or civil partnership status, sexual orientation, gender identity, pregnancy or related condition (including breastfeeding) or any other basis as protected by applicable law. If you have a disability or additional need that requires accommodation, please do not hesitate to let us know. Science is at the heart of everything we do at Google DeepMind. From the beginning, we took inspiration from science to build better algorithms, and now, we want to use our toolkit to accelerate scientific discovery. By bringing together specialists with backgrounds in machine learning, computer science, physics, chemistry, biology and more, we’re optimistic that we can build new methods that will push the boundaries of what is possible and help solve the biggest problems facing humanity. Project Overview Google DeepMind (GDM) is pursuing a ground-breaking research program in materials, aiming to accelerate the discovery of new functional materials by combining the predictive power of artificial intelligence (AI) and computational simulation with automated experimentation. You'll join an interdisciplinary team of domain experts, ML researchers, and engineers exploring a diverse set of important scientific problems in materials science, physics, quantum chemistry and other areas. Our work is organised into several longer-term focus areas, which aim to achieve step changes to the state-of-the-art (as exemplified in e.g. DM21 and GNoME). The role To succeed in this role you will need to be passionate about advancing material science using machine learning and other computational techniques. As an embedded Research Engineer you will collaborate with other researchers and engineers to develop infrastructure for running experiments and help researchers explore new applications of AI and LLMs to materials science. The team is pioneering in many different domains so you will take part in exploratory work that enables validating early ideas, and work in a maturing area to deepen and build infrastructure to exploit a promising line of research. You will also contribute to the scientific knowledge and experience of the team with your own scientific domain knowledge. Key responsibilities: Plan and perform rapid prototyping of machine learning techniques applied to problems in science. Undertake exploratory analysis to inform experimentation and research directions. Make improvements to model architectures and training procedures of machine learning models. Implement tools, libraries and frameworks to speed up and enable new research. Report and present software developments, experimental results and data analysis clearly and efficiently. Collaborate with internal and external scientific domain experts. About you Research Engineers come from a diverse set of backgrounds, sometimes with degrees in Computer Science and sometimes with extensive experience with real problems, or both. In order to set you up for success as a Research Engineer at Google DeepMind, we look for the following skills and experience: Degree in computer science, electrical engineering, science, mathematics or equivalent experience. Experience applying software engineering principles in a scientific research environment. Knowledge of linear algebra, calculus and statistics equivalent to at least first-year university coursework. Experience exploring, analysing, and visualising large and noisy datasets. Experience using Jax, PyTorch, TensorFlow, NumPy, Pandas or similar ML/scientific libraries. In addition, we also look for at least one of the following: Specific domain expertise in areas like inorganic chemistry, solid-state physics, or materials synthesis. Experience applying modern deep learning architectures (e.g., transformers, diffusion models) to chemistry or material science challenges (e.g. ML force fields). Experience running large-scale scientific simulations (e.g. molecular dynamics, computational chemistry simulations, etc.) on Cloud or HPC clusters. Experience developing custom LLM agents or tool-using systems. Experience with concurrent and distributed software algorithms and architectures. Masters or PhD in computer science, electrical engineering, science, mathematics or equivalent experience. The US base salary range for this full-time position is between $141,000 - $202,000 + bonus + equity + benefits. Your recruiter can share more about the specific salary range for your targeted location during the hiring process. Note: In the event your application is successful and an offer of employment is made to you, any offer of employment will be conditional on the results of a background check, performed by a third party acting on our behalf. For more information on how we handle your data, please see our Applicant and Candidate Privacy Policy At Google DeepMind, we value diversity of experience, knowledge, backgrounds and perspectives and harness these qualities to create extraordinary impact. We are committed to equal employment opportunity regardless of sex, race, religion or belief, ethnic or national origin, disability, age, citizenship, marital, domestic or civil partnership status, sexual orientation, gender identity, pregnancy, or related condition (including breastfeeding) or any other basis as protected by applicable law. If you have a disability or additional need that requires accommodation, please do not hesitate to let us know. Create a Job AlertInterested in building your career at DeepMind? Get future opportunities sent straight to your email.Create alert | W7: https://job-boards.greenhouse.io/deepmind/jobs/7339890 | Z7: all_jobs_jd | AA7: 是 | AB7: 核心基线3718 | AC7: O00019 | AD7: 基础理论与前沿研究 | AE7: 基础与前沿研究 | AF7: 原始6方向/17种类标签 | AG7: 高 | AH7: 正式基线 | AI7: c03d8b693d28b1b93518 | AJ7: 核心基线标签直接沿用 | AK7: Google DeepMind Technologies Limited | AL7: 企业别名精确匹配 | AM7: 高 | AN7: 已匹配 | AO7: AI大模型 | AP7: 央企/国企；Alphabet内部（未独立融资） | AQ7: https://deepmind.google | AR7: Google DeepMind官网/TechSpot/The Robot Report | AS7: 中游-AI基础模型（具身大脑） | AT7: 具身智能基础模型/VLA模型/机器人AI大脑 | AU7: 央企/国企/事业单位 | AV7: 海外 | AW7: 美国加利福尼亚州山景城(Mountain View, CA); 英国伦敦
A8: 7 | B8: O00010 | C8: 6024 | D8: Google DeepMind | E8: Google DeepMind | F8: Research Engineer, Human Understanding | J8: 未说明 | L8: 未说明 | M8: 高级 | N8: 基础理论与前沿研究 | O8: 基础与前沿研究 | P8: 中游 | Q8: 具身智能基础模型/VLA模型/机器人AI大脑 | R8: 央企/国企/事业单位 | S8: 海外 | T8: 美国 加利福尼亚州 山景城 | U8: Python; JAX; 强化学习; 深度学习; 机器学习; 计算机视觉; 多模态; 动力学; CAN | V8: We are seeking a highly motivated Research Engineer (L5) with a strong background in multi-modal modelling for humans and a focus on speech & audio/visual to join the effort within Google DeepMind's Frontier AI unit. This role is pivotal in developing foundational multimodal AI capabilities to understand, generate, and protect human likeness. As a key contributor, you will design and implement cutting-edge models and frameworks, pushing the boundaries of AI to enable foundational capabilities for human-centric understanding and generation. This is a unique opportunity to contribute to impactful research and advance Google DeepMind's mission towards Artificial General Intelligence (AGI). About us Artificial Intelligence could be one of humanity’s most useful inventions. At Google DeepMind, we’re a team of scientists, engineers, machine learning experts and more, working together to advance the state of the art in artificial intelligence and ultimately achieve Artificial General Intelligence. We use our technologies for widespread public benefit and scientific discovery, and collaborate with others on critical challenges, ensuring safety and ethics are the highest priority. The effort is a part of Google DeepMind's Frontier AI unit. The team aims to build holistic representation encompassing a full spectrum of human understanding. We develop systems to provide perception skills critical for person-centric applications, which is crucial for enabling AI to interact naturally & seamlessly, depict humans accurately & responsibly in generative AI, and build trustworthy & resilient systems that can detect and prevent misuse like deepfakes and impersonation. The role You will drive outcomes for critical technical components aimed at advancing our capabilities in multimodal human understanding. You will play a critical role in developing and deploying models that can provide accurate human understanding across multiple modalities (e.g., visual appearance, voice, dynamics, etc), while also building robust defenses against sophisticated AI-driven manipulation and impersonation. This role involves tackling complex, ambiguous problems with no obvious "best" solution, requiring independent judgment and a proactive approach to exploring multiple technical avenues. You will be instrumental in shaping the technical direction for core components of the effort. Your contribution will lead to key breakthrough and impactful landings within GDM and across Google products, ensuring our technologies are both groundbreaking and responsibly deployed. Key responsibilities Advance multimodal human representations & understanding : Research and implement novel models and other multimodal techniques for a more holistic understanding of humans across visual, audio, and textual data. Conduct applied research: Conduct experimental research cycles from hypothesis to deployment. Drive technical projects: Take ownership of substantial technical projects within the effort, from ideation and design to implementation and evaluation, often involving cross-functional collaboration. Contribute to Infrastructure: Inform and contribute to the development of scalable and efficient research infrastructure for multimodal human understanding models and datasets. Design and execute strategies for tuning and adapting VLMs and other foundation models for specific tasks About you In order to set you up for success as a Research Engineer at Google DeepMind, we look for the following skills and experience: Requirements: PhD degree in Computer Science, Machine Learning, or a related technical field with 3+ years of relevant experience. Experience in developing machine learning models, such as audio & speech-visual models. Experience in working with and tuning large-scale vision language models. Strong programming skills in Python and experience with at least one major deep learning framework (e.g., JAX) Experience conducting independent research and development, including experimental design, implementation, and analysis. In addition, the following would be an advantage: Experience with Generative AI techniques and architectures. Familiarity with Reinforcement Learning or alignment methods. A track record of publications in top-tier AI/ML conferences (e.g., NeurIPS, ICML, ICLR, CVPR, ICCV, ECCV). Experience with multimodal learning, integrating information from different data types (e.g., vision, audio, text). Understanding of privacy-preserving machine learning or responsible AI practices. The US base salary range for this full-time position is between 174,000 USD - 252,000 USD + bonus + equity + benefits. Your recruiter can share more about the specific salary range for your targeted location during the hiring process. Note: In the event your application is successful and an offer of employment is made to you, any offer of employment will be conditional on the results of a background check, performed by a third party acting on our behalf. For more information on how we handle your data, please see our Applicant and Candidate Privacy Policy. At Google DeepMind, we value diversity of experience, knowledge, backgrounds and perspectives and harness these qualities to create extraordinary impact. We are committed to equal employment opportunities regardless of sex, race, religion or belief, ethnic or national origin, disability, age, citizenship, marital, domestic or civil partnership status, sexual orientation, gender identity, pregnancy, or related condition (including breastfeeding) or any other basis as protected by applicable law. If you have a disability or additional need that requires accommodation, please do not hesitate to let us know. Create a Job AlertInterested in building your career at DeepMind? Get future opportunities sent straight to your email.Create alert | W8: https://job-boards.greenhouse.io/deepmind/jobs/7669433 | Z8: all_jobs_jd | AA8: 是 | AB8: 核心基线3718 | AC8: O00010 | AD8: 基础理论与前沿研究 | AE8: 基础与前沿研究 | AF8: 原始6方向/17种类标签 | AG8: 高 | AH8: 正式基线 | AI8: 38b1c5570e2e962c1ab1 | AJ8: 核心基线标签直接沿用 | AK8: Google DeepMind Technologies Limited | AL8: 企业别名精确匹配 | AM8: 高 | AN8: 已匹配 | AO8: AI大模型 | AP8: 央企/国企；Alphabet内部（未独立融资） | AQ8: https://deepmind.google | AR8: Google DeepMind官网/TechSpot/The Robot Report | AS8: 中游-AI基础模型（具身大脑） | AT8: 具身智能基础模型/VLA模型/机器人AI大脑 | AU8: 央企/国企/事业单位 | AV8: 海外 | AW8: 美国加利福尼亚州山景城(Mountain View, CA); 英国伦敦
A9: 8 | B9: O07975 | C9: 3699 | D9: Neura Robotics | E9: Neura Robotics | F9: Head of AI AI | G9: 杭州-萧山区 | H9: 薪资面议 | I9: 硕士 | J9: 硕士 | L9: 未说明 | M9: 中级 | N9: 基础理论与前沿研究 | O9: 基础与前沿研究 | P9: 中游 | Q9: 认知协作机器人/人形机器人 | R9: B轮 | S9: 海外 | T9: 德国 巴登-符腾堡州 梅青根 | U9: Python; C++; PyTorch; TensorFlow; LLM; 强化学习; 模仿学习; 深度学习; 机器学习; 计算机视觉; Diffusion; 多模态; 仿真; Linux; DevOps; 数据采集 | V9: 岗位要求： 1. Technology Strategy and System Development: Formulate and execute a long-term roadmap for the company's embodied AI robotics technology; Lead the construction of core technical architectures for real-world task training grounds, including data closed-loop systems, large-scale distributed training platforms, and high-efficiency Sim-to-Real deployment pipelines. 2. Data Closed-Loop System Development: Plan and establish an efficient, scalable, multimodal robotics data collection, cleaning, annotation, and management system; Lead the design of a data-driven model iteration closed-loop to ensure data asset quality and vitality, providing ample fuel for model evolution. 3. Core Model R&D and Training: Lead the team in developing embodied intelligence large models, including but not limited to vision-language-action models, Diffusion Policy, and RT-X series models; oversee large-scale distributed model training, continuously enhancing performance in generalization, safety, and execution efficiency. 4. Sim-to-Real Deployment and Optimization: Establish an efficient simulation-to-physical technology pipeline to address model transfer and deployment from virtual environments to real robots. Lead performance validation, debugging, and iterative optimization of models on physical robots to ensure stable AI capability deployment and application. 5. Platform and Toolchain Development: Lead or collaborate on building internal robotics AI development, training, and evaluation platforms to enhance algorithm R&D and testing efficiency; advance MLOps practices in robotics to automate model training, evaluation, and deployment. 6. Technology Forecasting and Innovation: Closely track global advancements in embodied intelligence and robotics (e.g., LLM+Robotics, World Models), explore and integrate novel technologies and methodologies to maintain the company's technological leadership; oversee the strategic planning and filing of relevant technology patents. 7. Team Building and Cross-Departmental Collaboration: Assemble and manage a high-caliber AI R&D team, overseeing talent recruitment, development, and performance management; collaborate closely with hardware, software, and product departments to collectively advance the technical implementation and performance enhancement of robotic products. 任职资格： 1. Education Background: Master's degree or higher in Computer Science, Artificial Intelligence, Robotics, or related fields; PhD preferred. 2. Work Experience: -At least 8 years of R&D experience in AI or machine learning, with a minimum of 3 years specializing in robotics AI domains (e.g., perception, decision-making, control, Sim-to-Real). -At least 3 years of technical team management experience, having successfully led algorithm teams of 10+ members, with proven experience in planning and executing large-scale projects from inception to completion. -Candidates with experience building large-scale data acquisition systems or robot training simulation platforms is preferred; Candidates with research publications in top-tier conferences or journals such as ICRA, IROS, CoRL, NeurIPS is preferred. 3. Professional Competencies: -Technical Depth: Proficient in theoretical foundations of deep learning, reinforcement learning, computer vision, and robotics; Demonstrated deep understanding and practical experience in embodied intelligence, multimodal large models, imitation learning, and Sim-to-Real. -Engineering Practice: Expertise in mainstream deep learning frameworks (PyTorch/TensorFlow); Extensive Linux-based C++/Python development experience; Capable of managing large-scale GPU clusters for model training and optimization. Capable of managing large-scale GPU clusters for model training and optimization. | W9: https://www.liepin.com/job/1981551025.shtml | Y9: 2026-07-17 | Z9: 猎聘10家中游 | AA9: 是 | AB9: 核心基线3718 | AC9: O07975 | AD9: 基础理论与前沿研究 | AE9: 基础与前沿研究 | AF9: 原始6方向/17种类标签 | AG9: 高 | AH9: 正式基线 | AI9: c0b67627b11c14bb5943 | AJ9: 核心基线标签直接沿用 | AK9: 纽鼐机器人（杭州）有限公司 | AL9: 企业别名精确匹配 | AM9: 高 | AN9: 已匹配 | AO9: 具身智能本体 | AP9: B轮后多轮融资; B轮(2025年1月, 1.2亿欧元, Lingotto/沃尔沃汽车科技基金); 新一轮(2026年3月, 约10亿欧元, 卡塔尔王室/亚马逊/高通创投/博世/Tether); 估值约40亿欧元(约320亿人民币) | AQ9: https://www.neura-robotics.com | AR9: NEURA Robotics官网(neura-robotics.com), 百度百科, 智东西, 浙江在线, 兆丰股份公告, 创业邦, 证券时报 | AS9: 中游-整机 | AT9: 认知机器人/人形机器人/协作机器人/具身智能 | AU9: C轮 | AV9: 华东 | AW9: 德国巴登-符腾堡州梅青根(Metzingen); 浙江省杭州市萧山区(中国总部)
A10: 9 | B10: O00011 | C10: 6018 | D10: Google DeepMind | E10: Google DeepMind | F10: Research Engineer, Multimodal Reasoning For Information Literacy | J10: 未说明 | L10: 未说明 | M10: 中级 | N10: 基础理论与前沿研究 | O10: 基础与前沿研究 | P10: 中游 | Q10: 具身智能基础模型/VLA模型/机器人AI大脑 | R10: 央企/国企/事业单位 | S10: 海外 | T10: 美国 加利福尼亚州 山景城 | U10: Python; PyTorch; TensorFlow; JAX; 深度学习; 机器学习; 计算机视觉; 多模态; CAN; Prompt Engineering | V10: At Google DeepMind, our research team is dedicated to tackling the most complex challenges in online information quality. We strive to advance the state of the art by developing innovative solutions to detect manipulated media and misleading narratives, ensuring the integrity of digital discourse. A prominent example of our scientific discovery is Backstory. Our interdisciplinary work spans provenance analysis and the creation of tools for AI-assisted information literacy, leveraging our technologies for the widespread public benefit of a safer online environment. We thrive in a supportive environment that encourages rapid prototyping and iteration, driving our research achievements directly into Google’s flagship models, including Gemini. About us Artificial Intelligence could be one of humanity’s most useful inventions. At Google DeepMind, we’re a team of scientists, engineers, machine learning experts and more, working together to advance the state of the art in artificial intelligence. We use our technologies for widespread public benefit and scientific discovery, and collaborate with others on critical challenges, ensuring safety and ethics are the highest priority. We’re a dedicated scientific community, committed to “solving intelligence” and ensuring our technology is used for widespread public benefit. We’ve built a supportive and inclusive environment where collaboration is encouraged and learning is shared freely. We don’t set limits based on what others think is possible or impossible. We drive ourselves and inspire each other to push boundaries and achieve ambitious goals. The role To succeed in this role, you will need to be passionate about advancing information literacy using machine learning and other computational techniques. You'll join an interdisciplinary team of domain experts, ML researchers, and engineers to research and build multimodal reasoning systems and Vision-Language Models (VLMs) to assess the trustworthiness of media (images, audio, and videos) on the internet. Key responsibilities: Plan and perform rapid prototyping of computer vision and multimodal machine learning techniques applied to determining authenticity of media information. Design and train multimodal models capable of complex visual reasoning. Undertake exploratory analysis to inform experimentation and research directions. Engage with product teams to drive the development of our research. Implement tools, libraries, and frameworks to speed up and enable new research. Report and present research findings, software developments, experimental results, and data analysis clearly and efficiently. Collaborate with internal and external scientific domain experts. About you In order to set you up for success as a Research Engineer at Google DeepMind, we look for the following skills and experience: PhD/Master’s degree in Computer Science, AI, ML, or equivalent practical experience. At least 2 years of relevant experience developing computer vision techniques or multimodal machine learning models. Experience in software development using Python and deep learning frameworks (e.g., Jax, TensorFlow, PyTorch), with a proven track record of building high-quality research prototypes and systems. Quantitative skills in math and statistics. Experience exploring, analysing and visualising data. In addition, the following would be an advantage: Experience in training and deployment of large-scale models. Experience with Video Understanding Experience with Large Language Models, prompt engineering, few-shot learning, post-training techniques, and evaluations. A proven track record of research or engineering achievements, such as publications in peer-reviewed conferences or journals. When assessing technical background we will take a holistic view of the mix of scientific, ML and computational experience. We do not expect you to be an expert in all fields simultaneously. At Google DeepMind, we value diversity of experience, knowledge, backgrounds and perspectives and harness these qualities to create extraordinary impact. We are committed to equal employment opportunity regardless of sex, race, religion or belief, ethnic or national origin, disability, age, citizenship, marital, domestic or civil partnership status, sexual orientation, gender identity, pregnancy, or related condition (including breastfeeding) or any other basis as protected by applicable law. If you have a disability or additional need that requires accommodation, please do not hesitate to let us know. The US base salary range for this full-time position is between 174,000 USD - 252,000 USD + bonus + equity + benefits. Your recruiter can share more about the specific salary range for your targeted location during the hiring process. Create a Job AlertInterested in building your career at DeepMind? Get future opportunities sent straight to your email.Create alert | W10: https://job-boards.greenhouse.io/deepmind/jobs/7171371 | Z10: all_jobs_jd | AA10: 是 | AB10: 核心基线3718 | AC10: O00011 | AD10: 基础理论与前沿研究 | AE10: 基础与前沿研究 | AF10: 原始6方向/17种类标签 | AG10: 高 | AH10: 正式基线 | AI10: 61a025203e5a21e53a23 | AJ10: 核心基线标签直接沿用 | AK10: Google DeepMind Technologies Limited | AL10: 企业别名精确匹配 | AM10: 高 | AN10: 已匹配 | AO10: AI大模型 | AP10: 央企/国企；Alphabet内部（未独立融资） | AQ10: https://deepmind.google | AR10: Google DeepMind官网/TechSpot/The Robot Report | AS10: 中游-AI基础模型（具身大脑） | AT10: 具身智能基础模型/VLA模型/机器人AI大脑 | AU10: 央企/国企/事业单位 | AV10: 海外 | AW10: 美国加利福尼亚州山景城(Mountain View, CA); 英国伦敦
A11: 10 | B11: O00013 | C11: 6023 | D11: Google DeepMind | E11: Google DeepMind | F11: Distinguished Designer, Gemini App Systems | J11: 未说明 | L11: 未说明 | M11: 中级 | N11: 基础理论与前沿研究 | O11: 基础与前沿研究 | P11: 中游 | Q11: 具身智能基础模型/VLA模型/机器人AI大脑 | R11: 央企/国企/事业单位 | S11: 海外 | T11: 美国 加利福尼亚州 山景城 | U11: 机器学习; 多模态; CAN | V11: At Google DeepMind, we’re a team of scientists, engineers, machine learning experts and more, working together to advance the state of the art in artificial intelligence. We use our technologies for widespread public benefit and scientific discovery, and collaborate with others on critical challenges, ensuring safety and ethics are the highest priority. We don’t set limits based on what others think is possible or impossible. We drive ourselves and inspire each other to push boundaries and achieve ambitious goals. The Area: Gemini App The Gemini App is at the forefront of the AI revolution, bringing helpful, generative AI experiences to users across the globe. We are seeking a visionary Design Leader to lead the strategy that will define the future of our product. The Role In this critical role, you will be responsible for defining and visioning the user experience, driving design excellence, and fostering a culture of innovation across Gemini. You will work closely with product management, engineering, and research teams to deliver an intuitive, powerful, and aesthetically pleasing experience for the needs of users globally. The Distinguished Designer is the technical soul of the Gemini interface. You are responsible for the bridge between cutting-edge machine learning and pixel-perfect mobile implementation. You will architect the systems that allow Gemini to feel "as fast as thought" while maintaining world-class stability and performance. Key responsibilities: Architecting the AI-UI Bridge: Design the technical frameworks for iOS and Android that handle non-deterministic AI outputs (streaming audio/visuals) with zero jitter and maximum fluidity. Performance Engineering: Own the "Gold Standard" for mobile UI latency. You will optimize rendering and state management to handle complex multimodal requests without compromising battery life or device thermals. AI-Augmented Tooling: Build and deploy internal "Design-to-Code" pipelines that allow the design team to use Gemini to automate UI generation and live-model prototyping. Technical North Star: Establish UX best practices for emerging technologies or ambiguous problem spaces. Mentor senior individual contributors and engineers at the intersection of UI development and AI inference. About You In order to set you up for success, we look for the following skills and experience: Minimum: 15+ years of experience in User Experience / Design, with experience establishing UX best practices for emerging technologies or ambiguous problem spaces. Technical Mastery: Expert-level mastery of mobile frameworks (Flutter, Swift, Kotlin, or React Native) and front-end performance for real-time applications. Leadership: Demonstrated track record of shipping and scaling flagship consumer applications across platforms. Preferred background includes one or any combination of the following: Master's degree or Ph.D. in a design-related field. Experience with AI/ML and agentic technologies; Depth and breadth of knowledge that enables ideation and development of creative solutions. Note: In the event your application is successful and an offer of employment is made to you, any offer of employment will be conditional on the results of a background check, performed by a third party acting on our behalf. For more information on how we handle your data, please see our Applicant and Candidate Privacy Policy The US base salary range for this full-time position is between $323,000 USD - $449,000 USD + bonus + equity + benefits. Your recruiter can share more about the specific salary range for your targeted location during the hiring process. At DeepMind, we value diversity of experience, knowledge, backgrounds and perspectives and harness these qualities to create extraordinary impact. We are committed to equal employment opportunity regardless of sex, race, religion or belief, ethnic or national origin, disability, age, citizenship, marital, domestic or civil partnership status, sexual orientation, gender identity, pregnancy, maternity or related condition (including breastfeeding) or any other basis as protected by applicable law. If you have a disability or additional need that requires accommodation, please do not hesitate to let us know. Create a Job AlertInterested in building your career at DeepMind? Get future opportunities sent straight to your email.Create alert | W11: https://job-boards.greenhouse.io/deepmind/jobs/7662676 | Z11: all_jobs_jd | AA11: 是 | AB11: 核心基线3718 | AC11: O00013 | AD11: 基础理论与前沿研究 | AE11: 基础与前沿研究 | AF11: 原始6方向/17种类标签 | AG11: 高 | AH11: 正式基线 | AI11: e56eed9f878ef66ef8bc | AJ11: 核心基线标签直接沿用 | AK11: Google DeepMind Technologies Limited | AL11: 企业别名精确匹配 | AM11: 高 | AN11: 已匹配 | AO11: AI大模型 | AP11: 央企/国企；Alphabet内部（未独立融资） | AQ11: https://deepmind.google | AR11: Google DeepMind官网/TechSpot/The Robot Report | AS11: 中游-AI基础模型（具身大脑） | AT11: 具身智能基础模型/VLA模型/机器人AI大脑 | AU11: 央企/国企/事业单位 | AV11: 海外 | AW11: 美国加利福尼亚州山景城(Mountain View, CA); 英国伦敦
A12: 11 | B12: O03712 | C12: 6174 | D12: 优世界 | E12: 优世界 | F12: 实习生招聘共0个职位 | J12: 未说明 | L12: 未说明 | M12: 初级 | N12: 仿真测试与数据工程 | O12: 数据工程 | P12: 中游 | Q12: 消费级超仿生人形机器人/情感陪伴 | R12: 已上市 | S12: 华南 | T12: 广东省深圳市南山区 | U12: 数据采集 | V12: 工作职责 负责协助遥操作数据采集（需要穿IMU动捕服装）、遥操作功能调试、算法优化 任职资格 1、大学本科及以上。 2、有动捕数据采集经验优先（光学、惯性等）。 3、有机器人算法开发基础/机器人调试经验优先考虑。 4、实习期3个月及以上 | W12: 北森 | Z12: all_jobs_jd | AA12: 是 | AB12: 核心基线3718 | AC12: O03712 | AD12: 仿真测试与数据工程 | AE12: 数据工程 | AF12: 原始6方向/17种类标签 | AG12: 高 | AH12: 正式基线 | AI12: 44d5704d751d3d3b89e1 | AJ12: 核心基线标签直接沿用 | AK12: 深圳市优世界机器人有限公司 | AL12: 企业别名精确匹配 | AM12: 高 | AN12: 已匹配 | AO12: 具身智能本体 | AP12: 已上市；优必选子品牌(优必选港股上市:09880.HK);U1系列独立定价(11.98-99万) | AQ12: https://www.ubtrobot.com(优必选主站) | AR12: IT之家/东方财富/凤凰网/百度百科/澎湃新闻/南方+/PCOnline | AS12: 下游-应用场景(C端消费) | AT12: 消费级超仿生人形机器人/情感陪伴 | AU12: 已上市 | AV12: 华南 | AW12: 广东省深圳市南山区(优必选总部)
A13: 12 | B13: O00017 | C13: 6020 | D13: Google DeepMind | E13: Google DeepMind | F13: Research Scientist, Gemini Safety | J13: 未说明 | L13: 未说明 | M13: 高级 | N13: 基础理论与前沿研究 | O13: 基础与前沿研究 | P13: 中游 | Q13: 具身智能基础模型/VLA模型/机器人AI大脑 | R13: 央企/国企/事业单位 | S13: 海外 | T13: 美国 加利福尼亚州 山景城 | U13: JAX; LLM; 强化学习; 机器学习; 自然语言处理 | V13: Artificial Intelligence could be one of humanity’s most useful inventions. At Google DeepMind, we’re a team of scientists, engineers, machine learning experts and more, working together to advance the state of the art in artificial intelligence. We use our technologies for widespread public benefit and scientific discovery, and collaborate with others on critical challenges, ensuring safety and ethics are the highest priority. The Gemini Safety team is accountable for the safety and fairness behavior of GDM’s latest Gemini models. The role of the Research Scientist / Research Engineer will be to apply and develop data and algorithmic cutting edge solutions to advance GDM’s latest user-facing models. The workstyle is fast paced, and highly collaborative. The team has a strong culture of support, dedication and collaboration. Artificial Intelligence could be one of humanity’s most useful inventions. At Google DeepMind, we’re a team of scientists, engineers, machine learning experts and more, working together to advance the state of the art in artificial intelligence. We use our technologies for widespread public benefit and scientific discovery, and collaborate with others on critical challenges, ensuring safety and ethics are the highest priority. The Role We’re looking for a versatile Research Scientist at ease both with figuring out how to approach new research questions, and the technical implementation of research ideas. Our team focuses on advancing the safety and fairness behavior of state of the art AI models. We drive the development of the foundational technology adopted by numerous product areas including Gemini App, Cloud API, and Search. Key responsibilities: Post-training / instruction tuning state of the art LLMs, focusing on text-to-text, image/video/audio-to-text modalities and agentic capabilities Exploring data, reasoning and algorithmic solutions to make sure Gemini Models are safe, maximally helpful, and work for everyone. Improve Gemini’s adversarial robustness, with a focus on high-stakes abuse risks. Design and maintain high quality evaluation protocols to assess model behavior gaps and headroom related to safety and fairness. Develop and execute experimental plans to address known gaps, or construct entirely new capabilities Drive innovation and enhance understanding of Supervised Fine Tuning and Reinforcement Learning fine-tuning at scale About You In order to set you up for success as a Research Scientist on the Gemini Safety team we look for the following skills and experience: PhD in Computer Science, a related field, or equivalent practical experience. Significant LLM post-training experience In addition, the following would be an advantage: Experience in Reward modeling and Reinforcement Learning for LLMs Instruction tuning Experience with Long-range Reinforcement learning Experience in areas such as Safety, Fairness and Alignment Track record of publications at NeurIPS, ICLR, ICML, RL/DL, EMNLP, AAAI, UAI Experience taking research from concept to product Experience with collaborating or leading an applied research project Experience with JAX At Google DeepMind, we value diversity of experience, knowledge, backgrounds and perspectives and harness these qualities to create extraordinary impact. We are committed to equal employment opportunity regardless of sex, race, religion or belief, ethnic or national origin, disability, age, citizenship, marital, domestic or civil partnership status, sexual orientation, gender identity, pregnancy, or related condition (including breastfeeding) or any other basis as protected by applicable law. If you have a disability or additional need that requires accommodation, please do not hesitate to let us know. Create a Job AlertInterested in building your career at DeepMind? Get future opportunities sent straight to your email.Create alert | W13: https://job-boards.greenhouse.io/deepmind/jobs/7421111 | Z13: all_jobs_jd | AA13: 是 | AB13: 核心基线3718 | AC13: O00017 | AD13: 基础理论与前沿研究 | AE13: 基础与前沿研究 | AF13: 原始6方向/17种类标签 | AG13: 高 | AH13: 正式基线 | AI13: 069ac1055ef70c0cffb3 | AJ13: 核心基线标签直接沿用 | AK13: Google DeepMind Technologies Limited | AL13: 企业别名精确匹配 | AM13: 高 | AN13: 已匹配 | AO13: AI大模型 | AP13: 央企/国企；Alphabet内部（未独立融资） | AQ13: https://deepmind.google | AR13: Google DeepMind官网/TechSpot/The Robot Report | AS13: 中游-AI基础模型（具身大脑） | AT13: 具身智能基础模型/VLA模型/机器人AI大脑 | AU13: 央企/国企/事业单位 | AV13: 海外 | AW13: 美国加利福尼亚州山景城(Mountain View, CA); 英国伦敦
A14: 13 | B14: O01729 | C14: 5401 | D14: 智元机器人 | E14: 智元机器人 | F14: 上海 SRE高级工程师（公有云） | H14: 30-50k·15薪 | I14: 统招本科 | J14: 本科 | L14: 未说明 | M14: 高级 | N14: 软件硬件与系统架构 | O14: 软件与系统 | P14: 中游 | Q14: 通用人形机器人; 具身智能全栈 | R14: C轮 | S14: 华东 | T14: 上海市临港新片区 | U14: Python; Linux; Docker; Kubernetes; CI; CD | V14: 我们是一家以机器人为核心的科技公司，业务横跨国内与海外多个市场，核心系统大规模运行于国内（阿里云、腾讯云、火山引擎等）与海外（AWS、Azure、GCP 等）多家公有云之上。随着多云规模快速扩张，我们正在搭建统一的云平台工程能力，把「账号、网络、权限、资源、成本」沉淀为可治理、可自助、可观测、可审计的平台化服务。 我们正在寻找一位具备体系化思维的 SRE 工程师（公有云方向）。你将以平台化、规范化、自动化的方式，统筹国内外多云环境的规范制定、资源交付、成本管理、账号管理四大职责：从 0 到 1 设计并落地多云治理框架与 Landing Zone（落地区），建设以 IaC 为核心的自助化资源交付平台，主导多云组织/账号体系与统一身份权限管控，并以 FinOps 为抓手建立从账单归集到降本运营的完整闭环。 这不是一个「开通账号、处理工单」的执行型岗位。你需要把分散在多个云厂商、多条业务线的云资源，治理成一套标准、安全、可复制、可量化的体系，在保障合规与稳定性基线的同时，持续提升交付效率并控制成本——让规范不止停留在文档，让降本落到每一分预算。 主要职责 1. 多云治理规范与 Landing Zone 落地 主导制定面向阿里云、腾讯云、华为云、火山引擎及 AWS、Azure、GCP 的多云治理框架，沉淀账号、网络、标签/命名、权限、安全等核心规范与基线标准；设计并实施多云 Landing Zone，规划组织结构、账号分层（管理/安全/日志/共享服务/生产/测试等）、网络拓扑与集中日志审计，通过组织策略（SCP/控制策略）、防护栏（Guardrails）与 Account Factory 把规范固化为不可绕过的平台约束，保证每个新落地的账号天然合规。 2. IaC 与自助化资源交付平台建设 以 Terraform / OpenTofu / Pulumi 为核心，沉淀覆盖国内外多云的可复用模块（VPC、子网、安全组、K8s 集群、数据库、对象存储、负载均衡等），建设自助化资源交付平台与服务目录，让研发团队通过标准化模板自助申请、按需交付云资源；制定交付 SLA 与质量标准，持续降低人工介入比例与交付时长，提升交付的速度与一致性。 3. 交付流水线与策略即代码（Policy as Code） 设计并维护资源交付的 CI/CD 流水线，落地 IaC 代码评审、plan 预检、策略即代码（OPA / Sentinel / Config Rules）、自动化合规校验与灰度发布；以 GitOps 方式管理基础设施变更，在交付管道中前置拦截不合规资源，实现「先合规、后交付」，确保所有云资源变更可追溯、可审计、可回滚，降低人为误操作与配置漂移风险。 4. 容量、配额与稳定性保障 建立跨云的容量规划与配额（Quota）管理机制，统一监控并申报各云厂商的资源配额（实例、IP、API 调用、专有网络等），对高风险资源设置限流与告警，提前预测增长趋势，避免因配额耗尽或容量瓶颈导致业务故障；为关键平台服务定义 SLI/SLO 与错误预算，主导故障应急与事故复盘（Postmortem），持续降低 MTTR。 5. 多云组织与账号体系管理 建设并维护多云组织（阿里云资源目录、AWS Organizations、腾讯云组织、Azure Management Groups 等）与账号体系，设计账号分级、分组与 OU/资源夹结构；统一账号生命周期管理（申请、审批、创建、回收），建立账号台账与归属、责任人、计费归集映射，杜绝「野生账号」与计费黑洞，确保账号结构与成本归属、分摊模型保持一致。 6. 统一身份权限与安全合规 建设跨云统一身份认证与单点登录（对接企业 IdP，SSO/SAML/OIDC），设计基于最小权限原则的 IAM/RAM 权限模型、权限边界（Permission Boundary）、SCP/控制策略与角色体系，推动权限按需申请、定期复核与自动回收；制定并下发多云安全基线（默认加密、日志留存、公网暴露管控、关键操作审计等），建设跨云合规扫描与配置审计能力，支撑等保、内部安全及客户合规审计要求。 7. 多云 FinOps 与成本可见性 打通各云厂商账单与用量数据，搭建统一的成本采集与归集管道（账单 API、CUR/成本导出、用量明细等），统一计费口径、汇率换算与维度模型，建立可信的「单一成本事实源」；基于标签、账号与资源归属设计 showback/chargeback 分摊模型，搭建成本看板与定期成本评审机制，向业务方与管理层输出清晰的成本归因与优化建议，推动「谁使用、谁负责、谁优化」的降本文化落地。 8. 成本优化与降本运营闭环 按业务线、团队、环境等维度拆解成本结构，定位高消耗与异常增长项；结合资源利用率（CPU/内存/磁盘/带宽/GPU）识别闲置、超配与低效资源，推动 Rightsizing（规格优化）、弹性伸缩、按需启停与闲置回收；负责 RI（预留实例）、Savings Plans（节省计划）、包年包月与竞价/抢占式实例的组合策略与日常运营，建立预算管控、成本预测与异常波动告警机制，在保障稳定性与交付效率的前提下持续降本，并跟踪每项优化的实际节省效果。 任职要求 1. 教育背景 计算机科学、软件工程、通信工程或相关专业本科及以上学历；具备扎实的计算机网络、操作系统、分布式系统基础，以及良好的工程素养与数据敏感度。 2. 经验要求 5 年以上 SRE / 云平台 / 基础设施 / 运维相关经验，其中 2 年以上公有云治理、平台建设、多云管理或 FinOps 实践经验；具备至少一家主流公有云的中大规模生产环境实战经验，有从 0 到 1 设计并落地 Landing Zone、多云治理体系、大规模账号体系或降本运营闭环者优先；有多云（国内 + 海外）、跨国或出海业务环境管理经验者优先。 3. 核心能力 深入掌握至少一家主流公有云（AWS / Azure / GCP / 阿里云 / 腾讯云 / 华为云 / 火山引擎）的产品体系与治理能力，熟悉组织与账号管理（Organizations / 资源目录 / Management Groups）、OU/资源夹、跨账号访问与计费归集，能在多云异构环境下抽象出统一的治理模型；具备良好的文档撰写、跨团队沟通与推动落地能力，能在多业务线诉求中平衡安全、效率与成本，做事严谨、注重规范与可审计性。 4. 专项技能 - IaC 与自动化：精通 Terraform / OpenTofu 或 Pulumi，具备模块化设计、状态管理（remote state / state 拆分）、多环境多云编排实战经验；熟悉 GitOps、CI/CD（GitLab CI、GitHub Actions、Jenkins、Argo CD 等）与策略即代码（OPA / Sentinel）；熟练使用至少一门脚本/编程语言（Python / Go / Shell）开发自动化工具或平台。 - 身份权限与安全合规：精通 IAM/RAM 权限模型、SSO/SAML/OIDC 单点登录、最小权限设计、SCP/控制策略与权限边界；熟悉云安全基线、配置审计、合规扫描与等保等合规要求，具备权限治理与安全风险识别、收敛的实战能力。 - 网络与基础设施：熟悉云上网络架构（VPC、子网与地址段规划、路由、专线/VPN、对等连接、Transit Gateway/云联网、DNS），理解多账号多 VPC 互联与隔离方案；具备 Linux、容器与编排（Docker、Kubernetes）及可观测性（Prometheus、Grafana、Loki、OpenTelemetry 等）基础。 - FinOps 与数据分析：深入理解云计费模型与各类计价方式（按量、包年包月、RI、Savings Plans、竞价实例等），具备账单归集、成本拆解、利用率分析、覆盖率优化、预算与成本预测、showback/chargeback 分摊的实战经验；熟练使用 SQL 与脚本语言处理海量账单数据，熟悉各云厂商成本工具（AWS Cost Explorer/CUR、阿里云费用中心、Azure Cost Management 等）及 Cloud Custodian、BI 看板等 FinOps/可视化工具。 5. 语言能力 具备良好的英文读写能力，能阅读海外云厂商（AWS / Azure / GCP）官方文档、API 与控制台，并支撑跨国业务场景下的协作与沟通。 加分项 - 持有主流云厂商专业级/专家级认证（AWS / Azure / 阿里云等），或 FinOps Certified Practitioner 认证； - 有自助化资源交付平台、云治理平台等产品从 0 到 1 的建设经验，或开源社区贡献经历； - 有大规模（如月云支出千万级以上）多云成本治理、GPU/AI 算力成本优化经验，或主导过显著降本项目（如整体云成本下降双位数百分比）； - 具备 SLI/SLO/错误预算落地、混沌工程与故障演练等成熟 SRE 实践经验。 承担主要目标/关键任务 1、对全公司年支出5000万以上的公有云进行精细管理，优化成本。 2、对内输出公有云技术使用支持，输出规范。 | W14: https://www.liepin.com/job/1983876329.shtml | Z14: all_jobs_jd | AA14: 是 | AB14: 核心基线3718 | AC14: O01729 | AD14: 软件硬件与系统架构 | AE14: 软件与系统 | AF14: 原始6方向/17种类标签 | AG14: 高 | AH14: 正式基线 | AI14: 92bb1e7355b2613d0104 | AJ14: 核心基线标签直接沿用 | AK14: 智元创新（上海）科技股份有限公司 | AL14: 企业别名精确匹配 | AM14: 高 | AN14: 已匹配 | AO14: 具身智能本体 | AP14: C轮；成立3年融资12轮; 最新估值约150亿元人民币; 投资方含红杉中国、高瓴创投、蓝驰创投、中金资本等顶级机构; 2025年营收突破10亿元 | AQ14: https://zhiyuan-robot.com | AR14: zhiyuan-robot.com官方网站; 36氪; 经济观察报; 长江日报; 南方日报; 投资界; 猎云网; 腾讯新闻; store.agibot.com; 界面新闻; 新华网 | AS14: 中游-整机+算法（软硬全栈） | AT14: 全尺寸人形机器人/四足机器人/具身智能操作系统 | AU14: 已上市 | AV14: 华东 | AW14: 上海市浦东新区临港新片区
A15: 14 | B15: O06217 | C15: 6057 | D15: 波士顿动力 | E15: 波士顿动力 | F15: 未说明岗位名称 | G15: Manager, R&D Build page is loaded | J15: 未说明 | K15: 页面未说明或按原文保留，未根据职级推断。 | L15: 未说明 | M15: 高级 | N15: 感知决策与控制算法 | O15: SLAM与控制 | P15: 中游 | Q15: 足式机器人/人形机器人/机器人运动控制 | R15: 已上市 | S15: 海外 | T15: 美国 马萨诸塞州 沃尔瑟姆 | U15: Go; C | V15: 页面职责段落显示：Responsibilities Leadership & Supervision Manage and coach supervisors leading teams of R&D Technical Specialists and Prototype Assembly Technicians. Ensure role clarity and smooth transitions as products evolve from early prototype units into repeat build phases. Foster a culture of accountability, technical rigor, and continuous improvement. Prototype Build Execution Oversee planning, coordination, and execution of prototype robot builds, ensuring alignment to program priorities and timelines. Enable Technical Specialists to resolve complex integration challenges where designs are incomplete or rapidly changing. Guide Assembly Technicians toward repeatable, efficient processes once builds stabilize. Process & Quality Partner with Engineering and Operations to ensure build processes meet safety, quality, and reliability standards. Ensure lessons learned from early builds are captured and transferred into work instructions, documentation, and training. Drive continuous improvement in tooling, fixturing, layout, and process design. Cross-Functional Alignment Act as the key interface between Prototype Operations, Hardware Engineering, Systems Engineering, and Program Management. Balance R&D iteration speed with program-level commitments and downstream manufacturability. Ensure effective communication across build phases, minimizing disruption as designs evolve. People Development Identify, mentor, and develop high-potential supervisors and team members. Ensure needed capabilities and bench depth are met for the Atlas program needs through cross-training and supplier-led training. Provide clear career pathways for both Technical Specialists and Assembly Technicians. Reinforce safety, technical excellence, and operational discipline. Core Competencies Execution: En 【任职要求】 页面任职要求段落显示：requirements are constantly evolving. This role requires balancing the ambiguity and hands-on problem solving of early prototype builds with the discipline and structure required to enable repeatability, scalability, and throughput. Key Responsibilities Leadership & Supervision Manage and coach supervisors leading teams of R&D Technical Specialists and Prototype Assembly Technicians. Ensure role clarity and smooth transitions as products evolve from early prototype units into repeat build phases. Foster a culture of accountability, technical rigor, and continuous improvement. Prototype Build Execution Oversee planning, coordination, and execution of prototype robot builds, ensuring alignment to program priorities and timelines. Enable Technical Specialists to resolve complex integration challenges where designs are incomplete or rapidly changing. Guide Assembly Technicians toward repeatable, efficient processes once builds stabilize. Process & Quality Partner with Engineering and Operations to ensure build processes meet safety, quality, and reliability standards. Ensure lessons learned from early builds are captured and transferred into work instructions, documentation, and training. Drive continuous improvement in tooling, fixturing, layout, and process design. Cross-Functional Alignment Act as the key interface between Prototype Operations, Hardware Engineering, Systems Engineering, and Program Management. Balance R&D iteration speed with program-level commitments and downstream manufacturability. Ensure effective communication across build phases, minimizing disruption as designs evolve. People Development Identify, mentor, and develop high-potential supervisors and team members. Ensure needed capabilities and bench depth are met for the Atlas program nee | W15: https://bostondynamics.wd1.myworkdayjobs.com/Boston_Dynamics/job/Waltham-Office-POST/Sr-Supervisor--R-D-Build_R2697-1 | Z15: embodied_final | AA15: 是 | AB15: 核心基线3718 | AC15: O06217 | AD15: 感知决策与控制算法 | AE15: SLAM与控制 | AF15: 原始6方向/17种类标签 | AG15: 高 | AH15: 正式基线 | AI15: 71376cb5274618b61fc5 | AJ15: 核心基线标签直接沿用；技能标签由技能词典从岗位名称/JD补全 | AK15: Boston Dynamics, Inc. | AL15: 企业别名精确匹配 | AM15: 高 | AN15: 已匹配 | AO15: 具身智能本体 | AP15: 已上市；已被现代汽车集团全资收购（2026年6月完成剩余股份收购），估值约210亿美元，计划2027年纳斯达克IPO | AQ15: https://www.bostondynamics.com | AR15: 公司官网、IT之家、新浪财经、路透社、抖音百科 | AS15: 中游-整机制造+上游-核心技术 | AT15: 足式机器人/人形机器人/机器人运动控制 | AU15: 已上市 | AV15: 海外 | AW15: 美国马萨诸塞州沃尔瑟姆(Waltham, MA)
A16: 15 | B16: O06208 | C16: 6049 | D16: 波士顿动力 | E16: 波士顿动力 | F16: 未说明岗位名称 | G16: 未说明 | J16: 未说明 | K16: 页面未说明或按原文保留，未根据职级推断。 | L16: 未说明 | M16: 中级 | N16: 感知决策与控制算法 | O16: SLAM与控制 | P16: 中游 | Q16: 足式机器人/人形机器人/机器人运动控制 | R16: 已上市 | S16: 海外 | T16: 美国 马萨诸塞州 沃尔瑟姆 | U16: 动力学 | V16: 页面职责段落显示：Responsibilities Conduct preventive and corrective maintenance inspections to proactively identify, troubleshoot, and resolve advanced facility and equipment issues. Diagnose and repair complex problems with mechanical systems independently. Perform skilled trades work including carpentry, drywall repair, and minor construction projects to maintain and improve facilities. Install, calibrate, and maintain building systems and equipment to comply with codes, standards, and manufacturer specifications. Respond to service requests and work orders with minimal supervision, prioritizing activities to reduce operational disruptions. Maintain accurate records of maintenance activities, repairs, materials used, and compliance documentation. Monitor inventory of parts, tools, and supplies; coordinate procurement and manage usage. Collaborate with contractors, vendors, and internal teams to plan and execute complex repairs and upgrades. Provide training, technical guidance, and mentoring to less experienced maintenance technicians. Part of onsite safety Team Assist in Logistics documentation and receiving Core Competencies Adaptability Adapts and pivots in real time to match the shifting demands of different situations, and moves forward productively and optimistically under conditions of change and ambiguity. Collaboration Builds partnerships and works collaboratively with others to meet shared objectives through effective communication that understands the unique needs of different audiences. Execution Analyzes and prioritizes the varying aspects of the role, knows and follows the most effective and efficient processes to get things done, and consistently achieves results, even under tough circumstances. Innovation Creates new and better ways for the organization to be 【任职要求】 页面任职要求段落显示：requirements. Highly developed troubleshooting and diagnostic skills to resolve complex technical issues independently. Proficiency in using a broad range of hand and power tools and specialized maintenance equipment. Excellent organizational skills and attention to detail to document activities and manage resources. Effective communication and leadership skills to train and support others. Typical Qualifications High school diploma or equivalent; vocational or trade school training in a relevant field strongly preferred. 7+ years of experience in facilities maintenance, building systems repair, or skilled trades. Relevant certifications preferred (OSHA safety training). The pay range for this position is between $34 to $43 per hour. Base pay will depend on multiple individualized factors including, but not limited to internal equity, job related knowledge, skills and experience. This range represents a good faith estimate of compensation at the time of posting. Boston Dynamics offers a generous Benefits package including medical, dental vision, 401(k), paid time off and a annual bonus structure. Additional details regarding these benefit plans will be provided if an employee receives an offer for employment. | W16: https://bostondynamics.wd1.myworkdayjobs.com/Boston_Dynamics/job/Savannah/Facilities-Maintenance-Senior-Technician_R2891 | Z16: embodied_final | AA16: 是 | AB16: 核心基线3718 | AC16: O06208 | AD16: 感知决策与控制算法 | AE16: SLAM与控制 | AF16: 原始6方向/17种类标签 | AG16: 高 | AH16: 正式基线 | AI16: f05904f4945917e093e1 | AJ16: 核心基线标签直接沿用 | AK16: Boston Dynamics, Inc. | AL16: 企业别名精确匹配 | AM16: 高 | AN16: 已匹配 | AO16: 具身智能本体 | AP16: 已上市；已被现代汽车集团全资收购（2026年6月完成剩余股份收购），估值约210亿美元，计划2027年纳斯达克IPO | AQ16: https://www.bostondynamics.com | AR16: 公司官网、IT之家、新浪财经、路透社、抖音百科 | AS16: 中游-整机制造+上游-核心技术 | AT16: 足式机器人/人形机器人/机器人运动控制 | AU16: 已上市 | AV16: 海外 | AW16: 美国马萨诸塞州沃尔瑟姆(Waltham, MA)
A17: 16 | B17: O06004 | C17: 5946 | D17: Figure AI | E17: Figure AI | F17: Helix AI Engineer, Agentic Systems | G17: Helix AI Engineer, Agentic Systems | J17: 未说明 | K17: 页面未说明或按原文保留，未根据职级推断。 | L17: 未说明 | M17: 中级 | N17: 基础理论与前沿研究 | O17: 基础与前沿研究 | P17: 中游 | Q17: 全尺寸通用人形机器人 | R17: C轮 | S17: 海外 | T17: 美国 加利福尼亚州 圣何塞 | U17: Python; PyTorch; 强化学习; 深度学习; 机器学习; 多模态; 端到端学习; 传感器; Agent | V17: 页面职责段落显示：Responsibilities Design, train, and deploy multimodal agents that operate autonomously for hours to days Build agents that reason from raw sensory inputs (pixels, environment state, proprioception) to structured actions Implement episodic memory systems for persistent state, retrieval, and long-horizon reasoning Develop planning, reasoning, and tool-use mechanisms for multi-step task execution Build reliable perception → reasoning → action loops with strong stability and failure recovery Design evaluation harnesses, benchmarks, and metrics to measure agent reasoning, planning, and reliability Design and run data studies across the training lifecycle, including pretraining, mid-training, and post-training Apply reinforcement learning, reward modeling, and post-training techniques to improve agent reasoning and reliability in real-world environments Develop evaluation frameworks and benchmarks to measure robot reasoning, planning, and task success across diverse scenarios Build infrastructure for scalable model training, distributed experimentation, and agent evaluation Work closely with other teams to integrate agent models into the full humanoid autonomy stack 【任职要求】 页面任职要求段落显示：Requirements Experience building autonomous agents that run continuously and complete multi-step tasks Experience developing agents that reason from pixel inputs or raw environment observations Experience implementing agent memory, planning, reasoning, or tool-use systems Experience training or fine-tuning multimodal or foundation models Strong proficiency in Python and modern deep learning frameworks (e.g., PyTorch) Strong experimental rigor and ability to design, analyze, and iterate on ML systems Strong software engineering skills and ability to build reliable, maintainable systems Ability to work independently and own complex technical problems end-to-end Bonus Qualifications Experience with embodied AI, robotics learning, or robot policy training Experience building multimodal foundation models (vision-language or vision-language-action) Background in agentic AI systems or long-horizon planning architectures Experience working with large-scale distributed training systems Publication record in machine learning, robotics, or embodied AI Passion for building autonomous humanoid robots that operate in the real world The US base salary range for this full-time position is between $150,000 - $350,000 annually. The pay offered for this position may vary based on several individual factors, including job-related knowledge, skills, and experience. The total compensation package may also include additional components/benefits depending on the specific role. This information will be shared if an employment offer is extended. Create a Job Alert Interested in building your career at Figure? Get future opportunities sent straight to your email. Create alert Apply for this job * indicates a required field Quick Apply with MyGreenhouse First Name* Last Name* Preferred | W17: https://job-boards.greenhouse.io/figureai/jobs/4659175006 | Z17: embodied_final | AA17: 是 | AB17: 核心基线3718 | AC17: O06004 | AD17: 基础理论与前沿研究 | AE17: 基础与前沿研究 | AF17: 原始6方向/17种类标签 | AG17: 高 | AH17: 正式基线 | AI17: faf676b7dfdd14fca2f7 | AJ17: 核心基线标签直接沿用 | AK17: Figure AI, Inc. | AL17: 企业别名精确匹配 | AM17: 高 | AN17: 已匹配 | AO17: 具身智能本体 | AP17: C轮>$1B（2025.9/估值$39B）；累计~$3.68B；微软/NVIDIA/OpenAI/英特尔/高通/LG等投资 | AQ17: https://www.figure.ai | AR17: 公司官网/Axios/Intel Capital/PitchBook | AS17: 中游-整机（人形机器人） | AT17: 全尺寸通用人形机器人 | AU17: C轮 | AV17: 海外 | AW17: 美国加利福尼亚州圣何塞(San Jose, CA)
A18: 17 | B18: O06013 | C18: 5939 | D18: Figure AI | E18: Figure AI | F18: Helix AI Engineer, Robot Learning | G18: Helix AI Engineer, Robot Learning | J18: 未说明 | K18: 页面未说明或按原文保留，未根据职级推断。 | L18: 未说明 | M18: 高级 | N18: 感知决策与控制算法 | O18: 算法工程 | P18: 中游 | Q18: 全尺寸通用人形机器人 | R18: C轮 | S18: 海外 | T18: 美国 加利福尼亚州 圣何塞 | U18: Python; C++; PyTorch; VLA; 强化学习; 模仿学习; 深度学习; 计算机视觉; 动力学; 仿真; 数字孪生; 电机驱动; 传感器; 数据采集 | V18: 页面职责段落显示：Responsibilities Design, train, evaluate, and deploy learning-based visuomotor policies for humanoid robot manipulation Develop manipulation behaviors such as grasping, pick-and-place, object reorientation, door opening, bimanual manipulation, and basic assembly Apply and extend techniques including behavior cloning, reinforcement learning, and VLA reasoning Train models that are robust to real-world challenges such as sensor noise, partial observability, contact dynamics, and environment variability Own the full pipeline from data collection on real robots to model training, evaluation, and deployment Work closely with simulation and digital twin tooling where useful, while prioritizing real-world performance and transfer Collaborate with perception, controls, systems, and hardware teams to integrate policies into a full autonomy stack Evaluate tradeoffs between learning-based and classical approaches and make principled design decisions Write high-quality, well-tested software that ships to and runs reliably on physical humanoid robots Partner with integration and testing teams to continuously improve robustness, performance, and deployment velocity 【任职要求】 页面任职要求段落显示：Requirements Hands-on experience developing and deploying robot learning systems on real robots Strong background in robot manipulation and visuomotor control Experience with behavior cloning, reinforcement learning, or related learning-based manipulation methods Proficiency in Python and/or C++ for robotics and ML systems Experience with modern deep learning frameworks (e.g., PyTorch) Ability to design experiments, analyze failures, and iterate quickly in real-world robotic systems Solid understanding of the tradeoffs between classical robotics approaches and learning-based methods Thrive in fast-paced, ambiguous environments where solutions require exploration and ownership Bonus Qualifications Experience deploying learning-based manipulation systems in commercial or production robotic systems Prior work on humanoids or highly dexterous robotic platforms Publication record in robot learning, manipulation, or embodied AI Experience leading projects or mentoring other engineers Passion for building autonomous humanoid robots that operate in the real world The pay offered for this position may vary based on several individual factors, including job-related knowledge, skills, and experience. The total compensation package may also include additional components/benefits depending on the specific role. This information will be shared if an employment offer is extended. Create a Job Alert Interested in building your career at Figure? Get future opportunities sent straight to your email. Create alert Apply for this job * indicates a required field Quick Apply with MyGreenhouse First Name* Last Name* Preferred First Name Email* Phone Country Phone Resume/CV Attach Attach Dropbox Google Drive Enter manually Enter manually Accepted file types: pdf, doc, docx, txt, rtf | W18: https://job-boards.greenhouse.io/figureai/jobs/4649851006 | Z18: embodied_final | AA18: 是 | AB18: 核心基线3718 | AC18: O06013 | AD18: 感知决策与控制算法 | AE18: 算法工程 | AF18: 原始6方向/17种类标签 | AG18: 高 | AH18: 正式基线 | AI18: 2df6e676f48903eef862 | AJ18: 核心基线标签直接沿用 | AK18: Figure AI, Inc. | AL18: 企业别名精确匹配 | AM18: 高 | AN18: 已匹配 | AO18: 具身智能本体 | AP18: C轮>$1B（2025.9/估值$39B）；累计~$3.68B；微软/NVIDIA/OpenAI/英特尔/高通/LG等投资 | AQ18: https://www.figure.ai | AR18: 公司官网/Axios/Intel Capital/PitchBook | AS18: 中游-整机（人形机器人） | AT18: 全尺寸通用人形机器人 | AU18: C轮 | AV18: 海外 | AW18: 美国加利福尼亚州圣何塞(San Jose, CA)
A19: 18 | B19: O06041 | C19: 5951 | D19: Figure AI | E19: Figure AI | F19: AI Data Operations Lead | G19: San Jose | J19: 未说明 | K19: 页面未说明或按原文保留，未根据职级推断。 | L19: 未说明 | M19: 中级 | N19: 感知决策与控制算法 | O19: 视觉与多模态 | P19: 中游 | Q19: 全尺寸通用人形机器人 | R19: C轮 | S19: 海外 | T19: 美国 加利福尼亚州 圣何塞 | U19: 机器学习; 计算机视觉; 数据采集 | V19: 页面职责段落显示：Responsibilities: Day one, you will own a meaningful piece of Figure's data collection operation. You'll be hitting volume, quality, and velocity targets, building the systems that get us there, and partnering across engineering, product, and ops to make it happen. Specific responsibilities include: Owning contributor acquisition, activation, and retention strategy and execution Identifying and launching in new geographies, managing localization, partnerships, and community building to establish presence in target regions Coordinating with engineering, product, and ops to develop the new hardware, software, and operational systems Owning your category’s data dashboard — tracking volume, quality, and throughput metrics daily, identifying bottlenecks, and shipping operational fixes fast Sourcing, negotiating, and managing relationships with local partners, agencies, and vendors to accelerate growth Serving as the connective tissue between your contributors and internal teams — surfacing hardware/software friction, translating field feedback into actionable product improvements, and advocating for your workstreams' needs 【任职要求】 页面任职要求段落显示：Requirements: 4+ years in investment banking, management consulting, corporate development, growth, or startup operations roles, ideally with exposure to a frontier technology business Comfortable rapidly building and deploying apps/agents using AI coding tools (zero technical academic background necessary) Demonstrated ability to own outcomes Exceptional written and verbal communication skills Experience working across cultures or in international markets Highly organized with strong project management instincts — comfortable managing multiple contributors, sessions, or sites simultaneously and keeping all plates spinning A commitment to 5 days/week in-office collaboration Bonus Qualifications: Experience scaling consumer mobile applications or marketplace platforms Background in AI/ML companies or understanding of data collection for machine learning Prior experience in emerging markets or with distributed workforces Fluency in additional languages Experience managing physical-world operations (events, field crews, hardware logistics) in addition to digital platforms The US base salary range for this full-time position is between $175,000 - $200,000 annually. The pay offered for this position may vary based on several individual factors, including job-related knowledge, skills, and experience. The total compensation package may also include additional components/benefits depending on the specific role. This information will be shared if an employment offer is extended. Create a Job Alert Interested in building your career at Figure? Get future opportunities sent straight to your email. Create alert Apply for this job * indicates a required field Quick Apply with MyGreenhouse First Name* Last Name* Email* Phone Country Phone Resume/CV Attach Attach Dropbox G | W19: https://job-boards.greenhouse.io/figureai/jobs/4665206006 | Z19: embodied_final | AA19: 是 | AB19: 核心基线3718 | AC19: O06041 | AD19: 感知决策与控制算法 | AE19: 视觉与多模态 | AF19: 原始6方向/17种类标签 | AG19: 高 | AH19: 正式基线 | AI19: 57024b565bfb601d33b2 | AJ19: 核心基线标签直接沿用 | AK19: Figure AI, Inc. | AL19: 企业别名精确匹配 | AM19: 高 | AN19: 已匹配 | AO19: 具身智能本体 | AP19: C轮>$1B（2025.9/估值$39B）；累计~$3.68B；微软/NVIDIA/OpenAI/英特尔/高通/LG等投资 | AQ19: https://www.figure.ai | AR19: 公司官网/Axios/Intel Capital/PitchBook | AS19: 中游-整机（人形机器人） | AT19: 全尺寸通用人形机器人 | AU19: C轮 | AV19: 海外 | AW19: 美国加利福尼亚州圣何塞(San Jose, CA)
A20: 19 | B20: O06018 | C20: 5907 | D20: Figure AI | E20: Figure AI | F20: Manufacturing Equipment Technician | G20: San Jose, CA | J20: 未说明 | K20: 页面未说明或按原文保留，未根据职级推断。 | L20: 未说明 | M20: 初级 | N20: 感知决策与控制算法 | O20: SLAM与控制 | P20: 中游 | Q20: 全尺寸通用人形机器人 | R20: C轮 | S20: 海外 | T20: 美国 加利福尼亚州 圣何塞 | U20: 计算机视觉 | V20: 页面职责段落显示：Responsibilities: Provide technician-level support for all manufacturing equipment, including but not limited to adhesive dispense systems, 3-axis robot gantries, laser cleaners, laser welders, wirebonders, vision systems, torque tools, custom fixtures, and tooling Serve as the first point of contact to troubleshoot issues that arise during production Develop and own a full maintenance program, including setting preventative maintenance schedules, ensuring a proper supply of spare parts, and writing standard operating procedures for maintenance Write standard operating procedures/work instructions for operation of equipment Operate equipment during initial process validation builds Train operators and associates on operation of equipment in steady state production Support engineering teams with line setup and process validation (e.g., gauge R&R testing, process window qualification, NPI validation builds) Support engineering teams on failure root cause investigations Support cycle time studies Take ownership of implementing equipment/process improvements to improve safety, quality, and throughput 【任职要求】 页面任职要求段落显示：Requirements: Experience with high tech manufacturing tools and automation Occasional travel to equipment vendor locations Familiarity with basic tools and facilities equipment such as drills, soldering irons, wire crimping, and compressed air fittings Ability to take full ownership of projects with minimal direction from managers Respectful work attitude with a championship mindset Excellent time management skills and a commitment to punctuality Previous experience working in a manufacturing environment with complex equipment Strong attention to detail with a methodical approach to documentation and organization Ability to lift and transport materials safely (up to 50lbs as required) Excellent communication skills and ability to work effectively in a team setting Bonus Qualifications: Experience working with battery cells Experience working with adhesive dispense systems Experience working with laser weld equipment Background in machining and fabrication Forklift or other powered equipment certification (preferred but not required) The US hourly range for this full-time position is between $40/hr to $65/hr. The pay offered for this position may vary based on several individual factors, including job-related knowledge, skills, and experience. The total compensation package may also include additional components/benefits depending on the specific role. This information will be shared if an employment offer is extended. Create a Job Alert Interested in building your career at Figure? Get future opportunities sent straight to your email. Create alert Apply for this job * indicates a required field Quick Apply with MyGreenhouse First Name* Last Name* Email* Phone Country Phone Resume/CV Attach Attach Dropbox Google Drive Enter manually Enter manually Accepted fil | W20: https://job-boards.greenhouse.io/figureai/jobs/4553552006 | Z20: embodied_final | AA20: 是 | AB20: 核心基线3718 | AC20: O06018 | AD20: 感知决策与控制算法 | AE20: SLAM与控制 | AF20: 原始6方向/17种类标签 | AG20: 高 | AH20: 正式基线 | AI20: 2d3abd0e401767aab929 | AJ20: 核心基线标签直接沿用 | AK20: Figure AI, Inc. | AL20: 企业别名精确匹配 | AM20: 高 | AN20: 已匹配 | AO20: 具身智能本体 | AP20: C轮>$1B（2025.9/估值$39B）；累计~$3.68B；微软/NVIDIA/OpenAI/英特尔/高通/LG等投资 | AQ20: https://www.figure.ai | AR20: 公司官网/Axios/Intel Capital/PitchBook | AS20: 中游-整机（人形机器人） | AT20: 全尺寸通用人形机器人 | AU20: C轮 | AV20: 海外 | AW20: 美国加利福尼亚州圣何塞(San Jose, CA)
A21: 20 | B21: O06219 | C21: 6055 | D21: 波士顿动力 | E21: 波士顿动力 | F21: 未说明岗位名称 | G21: Waltham Office (360) | J21: 未说明 | K21: 页面未说明或按原文保留，未根据职级推断。 | L21: 未说明 | M21: 高级 | N21: 感知决策与控制算法 | O21: SLAM与控制 | P21: 中游 | Q21: 足式机器人/人形机器人/机器人运动控制 | R21: 已上市 | S21: 海外 | T21: 美国 马萨诸塞州 沃尔瑟姆 | U21: 动力学; CAN; Prompt Engineering | V21: 页面职责段落显示：responsibilities. Boston Dynamics is a world leader in mobile robots, tackling some of the toughest robotics challenges. For years, our awe-inspiring viral videos on YouTube have shown the world what remarkably capable robots can do. Now we are quickly becoming a recognized leader in automation solutions for industrial applications and warehouse logistics. Responsibilities: Implement quality assurance activities including inspection planning, control plans, and test procedures to ensure conformance to specifications and standards Analyze manufacturing and quality data (e.g., defect rates, yield performance) to identify trends, support investigations, and recommend improvements Collaborate with Design Engineers, Supplier Quality Engineers, Test Engineers and the Operations Team to ensure that quality standards are met Lead root cause, corrective action and preventive action investigations cross functionally Implement resolution of product quality issues in sustaining and across multiple disciplines of the business (including design, supply chain, production and service) Plan and lead process 【任职要求】 页面任职要求段落显示：requirements are clear. We will also look for you to solve complex quality challenges, acting as a key technical resource for cross-functional teams throughout the entire product lifecycle. To be successful in this role, you must be inquisitive and thrive on solving problems, have excellent communication skills and be willing to take on an ever-changing list of tasks and responsibilities. Boston Dynamics is a world leader in mobile robots, tackling some of the toughest robotics challenges. For years, our awe-inspiring viral videos on YouTube have shown the world what remarkably capable robots can do. Now we are quickly becoming a recognized leader in automation solutions for industrial applications and warehouse logistics. Responsibilities: Implement quality assurance activities including inspection planning, control plans, and test procedures to ensure conformance to specifications and standards Analyze manufacturing and quality data (e.g., defect rates, yield performance) to identify trends, support investigations, and recommend improvements Collaborate with Design Engineers, Supplier Quality Engineers, Test Engineers and the Operations Team to ensure that quality standards are met Lead root cause, corrective action and preventive action investigations cross functionally Implement resolution of product quality issues in sustaining and across multiple disciplines of the business (including design, supply chain, production and service) Plan and lead process qualifications generating clear and concise plans and reports as a result of new product releases and sustaining change. Provide support to the MRB process to ensure effective root cause/corrective action and prompt and accurate disposition for nonconforming material Implement methods to inspect and evalua | W21: https://bostondynamics.wd1.myworkdayjobs.com/Boston_Dynamics/job/Waltham-Office-360/Senior-Product-Quality-Engineer_R2579 | Z21: embodied_final | AA21: 是 | AB21: 核心基线3718 | AC21: O06219 | AD21: 感知决策与控制算法 | AE21: SLAM与控制 | AF21: 原始6方向/17种类标签 | AG21: 高 | AH21: 正式基线 | AI21: 6b1da9bbfadec83fe22b | AJ21: 核心基线标签直接沿用 | AK21: Boston Dynamics, Inc. | AL21: 企业别名精确匹配 | AM21: 高 | AN21: 已匹配 | AO21: 具身智能本体 | AP21: 已上市；已被现代汽车集团全资收购（2026年6月完成剩余股份收购），估值约210亿美元，计划2027年纳斯达克IPO | AQ21: https://www.bostondynamics.com | AR21: 公司官网、IT之家、新浪财经、路透社、抖音百科 | AS21: 中游-整机制造+上游-核心技术 | AT21: 足式机器人/人形机器人/机器人运动控制 | AU21: 已上市 | AV21: 海外 | AW21: 美国马萨诸塞州沃尔瑟姆(Waltham, MA)
A22: 21 | B22: O06213 | C22: 6048 | D22: 波士顿动力 | E22: 波士顿动力 | F22: 未说明岗位名称 | G22: 未说明 | J22: 未说明 | K22: 页面未说明或按原文保留，未根据职级推断。 | L22: 未说明 | M22: 高级 | N22: 感知决策与控制算法 | O22: SLAM与控制 | P22: 中游 | Q22: 足式机器人/人形机器人/机器人运动控制 | R22: 已上市 | S22: 海外 | T22: 美国 马萨诸塞州 沃尔瑟姆 | U22: Python; CAN; 电机驱动; 传感器; PCB设计 | V22: 页面职责段落显示：responsibilities and timelines. Foster clear communication among team members, other technical leads, and management. Actively ensure that everyone is on the same page regarding project objectives and expectations, which contributes to maintaining high standards for project completion. Required Skills Experience with Maintenance and Repair Workflows. Proficiency in repair ticketing or issue management tools such as JIRA. Hands-on experience building and debugging electro-mechanical test setups. Experience with lab equipment including oscilloscopes, power supplies, programmable loads, thermal probes. Experience with communication interfaces, e.g., CAN, Ethernet, SPI, and I2C. Strong ability to multitask and change priorities quickly as needed. Clear and effective communication of test results and data. A deep passion for mentoring and fostering a culture of excellence and best practices. Experience working in a collaborative setting. Excellent verbal and written communication skills to clearly articulate 【任职要求】 页面任职要求段落显示：requirements. Develop comprehensive work schedules that ensure team members are aligned and aware of their responsibilities and timelines. Foster clear communication among team members, other technical leads, and management. Actively ensure that everyone is on the same page regarding project objectives and expectations, which contributes to maintaining high standards for project completion. Required Skills Experience with Maintenance and Repair Workflows. Proficiency in repair ticketing or issue management tools such as JIRA. Hands-on experience building and debugging electro-mechanical test setups. Experience with lab equipment including oscilloscopes, power supplies, programmable loads, thermal probes. Experience with communication interfaces, e.g., CAN, Ethernet, SPI, and I2C. Strong ability to multitask and change priorities quickly as needed. Clear and effective communication of test results and data. A deep passion for mentoring and fostering a culture of excellence and best practices. Experience working in a collaborative setting. Excellent verbal and written communication skills to clearly articulate requirements, expectations, and updates. Exceptional organizational and time management skills to effectively juggle multiple tasks, prioritize workload, and ensure deadlines are met without compromising quality. Nice to Have Experience with Python, and command-line operations in a UNIX-like OS. Familiarity with position encoder and force sensor technology. Experience working with robots and/or robotic systems. Experience with electric actuators and motors Experience with PCB schematic and layout software such as Altium Experience with PCB rework and cable assembly, especially technically difficult rework. We are interested in every qualified candidate wh | W22: https://bostondynamics.wd1.myworkdayjobs.com/Boston_Dynamics/job/Mountain-View/Senior-Field-Service-Engineer---1st-Shift_R2812 | Z22: embodied_final | AA22: 是 | AB22: 核心基线3718 | AC22: O06213 | AD22: 感知决策与控制算法 | AE22: SLAM与控制 | AF22: 原始6方向/17种类标签 | AG22: 高 | AH22: 正式基线 | AI22: ddd94c797449403ebcba | AJ22: 核心基线标签直接沿用 | AK22: Boston Dynamics, Inc. | AL22: 企业别名精确匹配 | AM22: 高 | AN22: 已匹配 | AO22: 具身智能本体 | AP22: 已上市；已被现代汽车集团全资收购（2026年6月完成剩余股份收购），估值约210亿美元，计划2027年纳斯达克IPO | AQ22: https://www.bostondynamics.com | AR22: 公司官网、IT之家、新浪财经、路透社、抖音百科 | AS22: 中游-整机制造+上游-核心技术 | AT22: 足式机器人/人形机器人/机器人运动控制 | AU22: 已上市 | AV22: 海外 | AW22: 美国马萨诸塞州沃尔瑟姆(Waltham, MA)
A23: 22 | B23: O06015 | C23: 5958 | D23: Figure AI | E23: Figure AI | F23: Helix AI Engineer, Video Pretraining | G23: Helix AI Engineer, Video Pretraining | J23: 未说明 | K23: 页面未说明或按原文保留，未根据职级推断。 | L23: 未说明 | M23: 中级 | N23: 感知决策与控制算法 | O23: 视觉与多模态 | P23: 中游 | Q23: 全尺寸通用人形机器人 | R23: C轮 | S23: 海外 | T23: 美国 加利福尼亚州 圣何塞 | U23: Python; PyTorch; 深度学习; 机器学习; 计算机视觉; Transformer; Diffusion; 多模态; 动力学; Agent | V23: 页面职责段落显示：Responsibilities Design and train large-scale video foundation models on diverse datasets spanning internet-scale video and robot-collected data Develop pretraining strategies that capture temporal dynamics, motion, and object interaction from raw video sequences Build models that learn transferable representations for downstream tasks such as perception, tracking, prediction, and control Explore architectures for video understanding and generation, including transformer-based and diffusion-based approaches Implement efficient data pipelines and training strategies for high-throughput video ingestion and large-scale distributed training Optimize model performance across compute, memory, and training efficiency constraints Collaborate closely with generative modeling, agent, and robot learning teams to integrate pretrained models into the autonomy stack Design evaluation frameworks and benchmarks to measure temporal understanding, prediction quality, and generalization 【任职要求】 页面任职要求段落显示：Requirements Experience training large-scale models on video data or other high-dimensional sequential modalities Strong understanding of modern deep learning architectures for video, vision, or multimodal systems Experience with large-scale pretraining, including dataset curation, training dynamics, and scaling laws Proficiency in Python and deep learning frameworks such as PyTorch Experience working with distributed training systems and large GPU clusters Strong experimental rigor and ability to iterate quickly on model design and training strategies Solid software engineering skills and ability to build scalable, reliable systems Ability to operate independently and drive ambiguous, high-impact research directions Bonus Qualifications Experience working on frontier video models or multimodal foundation models Background in video diffusion, autoregressive video modeling, or world models Experience at leading AI labs such as OpenAI, Google DeepMind, Google, ByteDance, Midjourney, or Adobe Experience with large-scale dataset construction and filtering for video pretraining Familiarity with robotics, embodied AI, or learning from egocentric / first-person video Publication record in machine learning, computer vision, or multimodal AI The pay offered for this position may vary based on several individual factors, including job-related knowledge, skills, and experience. The total compensation package may also include additional components/benefits depending on the specific role. This information will be shared if an employment offer is extended. Create a Job Alert Interested in building your career at Figure? Get future opportunities sent straight to your email. Create alert Apply for this job * indicates a required field Quick Apply with MyGreenhouse First Name | W23: https://job-boards.greenhouse.io/figureai/jobs/4671703006 | Z23: embodied_final | AA23: 是 | AB23: 核心基线3718 | AC23: O06015 | AD23: 感知决策与控制算法 | AE23: 视觉与多模态 | AF23: 原始6方向/17种类标签 | AG23: 高 | AH23: 正式基线 | AI23: 78e322411bb8d178bf41 | AJ23: 核心基线标签直接沿用 | AK23: Figure AI, Inc. | AL23: 企业别名精确匹配 | AM23: 高 | AN23: 已匹配 | AO23: 具身智能本体 | AP23: C轮>$1B（2025.9/估值$39B）；累计~$3.68B；微软/NVIDIA/OpenAI/英特尔/高通/LG等投资 | AQ23: https://www.figure.ai | AR23: 公司官网/Axios/Intel Capital/PitchBook | AS23: 中游-整机（人形机器人） | AT23: 全尺寸通用人形机器人 | AU23: C轮 | AV23: 海外 | AW23: 美国加利福尼亚州圣何塞(San Jose, CA)
A24: 23 | B24: O00293 | C24: 4497 | D24: 禾赛科技 | E24: 禾赛科技 | F24: 上海 Customer Project Manager | H24: 20-40k | I24: 硕士 | J24: 硕士 | L24: 未说明 | M24: 中级 | N24: 软件硬件与系统架构 | O24: 软件与系统 | P24: 上游 | Q24: 激光雷达（LiDAR） | R24: 已上市 | S24: 华东 | T24: 上海市嘉定区 | U24: C | V24: 职位描述： To support our rapidly growing customer globally, we are looking for an experienced, enthusiastic, and driven Customer Program Manager to support our Automotive business. Responsibilities Articulate key program information internally and externally to stakeholders and key program sponsors. Develop and deliver the defined program scope to ensure customer requirements are successfully achieved. Represent company interests at customer meetings, build events, and communicate via other means of communication. Perform planning activities such as WBS, project charters, and project plans. Follow defined methods and procedures for implementing new program development through the launch of the product Coordinate program activities. Perform program-level Risk/Impact Analysis reviews and define and record recovery strategies, including response plans and role ownership. Construct and maintain detailed Gantt charts to the performance baseline representative of the SOW detailed in the defined project plans. Perform critical path analysis and work with the internal team to generate recovery plans to safeguard program milestones. Support Change Management activities to achieve program objectives. Provide leadership during program assessments with appropriate corporate/plant personnel. Prepare various program reports to confirm Scope/Quality/Cost of the program are on track. Owns accounts and identifies and realizes opportunities within the Automotive market. Builds multi-level customer relationships to support account strategy and coordinate the use of internal resources, including local application engineers and business unit staff, and overseas design teams to drive design wins Provides value-added feedback on customer needs to management, business units and customer service teams 职位要求： Qualification What we look for Fluent in English, other languages as plus. A result-oriented, driven, and enthusiastic Program Manager with extensive launch experience with global Automotive customers Demonstrated background in driving success in the Automotive Market at a Tier 1 supplier. Bachelor's degree in Electronics/Electrical Engineering/Computer Engineering or equivalent. 5+ years' experience in new product development or program/project management. Demonstrated ability to manage various engineering disciplines, including Software, Hardware, Mechanical, Functional Safety, and Cybersecurity. Product Development experience from quote to production on camera/radar/ECUs/ADAS/displays or similar electrical products Experience managing within a matrixed environment, including Quality, Purchasing, Engineering, Sales, and Finance. Strong interpersonal skills and a team player with the ability to work effectively on cross-functional teams. | W24: https://www.liepin.com/job/1982959231.shtml | Z24: all_jobs_jd | AA24: 是 | AB24: 核心基线3718 | AC24: O00293 | AD24: 软件硬件与系统架构 | AE24: 软件与系统 | AF24: 原始6方向/17种类标签 | AG24: 高 | AH24: 正式基线 | AI24: ff860b39352e76393b3d | AJ24: 核心基线标签直接沿用；技能标签由技能词典从岗位名称/JD补全 | AK24: 上海禾赛科技有限公司 | AL24: 企业别名精确匹配 | AM24: 高 | AN24: 已匹配 | AO24: 感知系统 | AP24: 已上市（纳斯达克HSAI/港交所2525）；2025.9港股IPO募资41.6亿港元；全球激光雷达收入第一 | AQ24: https://www.hesaitech.com | AR24: 公司财报/国信证券研报 | AS24: 上游-核心零部件（激光雷达） | AT24: 激光雷达（LiDAR） | AU24: 已上市 | AV24: 华东 | AW24: 上海市嘉定区/长宁区
A25: 24 | B25: O00292 | C25: 4509 | D25: 禾赛科技 | E25: 禾赛科技 | F25: 上海 Customer Project Manager | H25: 20-30k | I25: 统招本科 | J25: 本科 | L25: 未说明 | M25: 中级 | N25: 软件硬件与系统架构 | O25: 软件与系统 | P25: 上游 | Q25: 激光雷达（LiDAR） | R25: 已上市 | S25: 华东 | T25: 上海市嘉定区 | U25: C | V25: To support our rapidly growing customer globally, we are looking for an experienced, enthusiastic, and driven Customer Program Manager to support our Automotive business. Responsibilities Articulate key program information internally and externally to stakeholders and key program sponsors. Develop and deliver the defined program scope to ensure customer requirements are successfully achieved. Represent company interests at customer meetings, build events, and communicate via other means of communication. Perform planning activities such as WBS, project charters, and project plans. Follow defined methods and procedures for implementing new program development through the launch of the product Coordinate program activities. Perform program-level Risk/Impact Analysis reviews and define and record recovery strategies, including response plans and role ownership. Construct and maintain detailed Gantt charts to the performance baseline representative of the SOW detailed in the defined project plans. Perform critical path analysis and work with the internal team to generate recovery plans to safeguard program milestones. Support Change Management activities to achieve program objectives. Provide leadership during program assessments with appropriate corporate/plant personnel. Prepare various program reports to confirm Scope/Quality/Cost of the program are on track. Owns accounts and identifies and realizes opportunities within the Automotive market. Builds multi-level customer relationships to support account strategy and coordinate the use of internal resources, including local application engineers and business unit staff, and overseas design teams to drive design wins Provides value-added feedback on customer needs to management, business units and customer service teams 职位要求 Qualification What we look for Fluent in English, other languages as plus. A result-oriented, driven, and enthusiastic Program Manager with extensive launch experience with global Automotive customers Demonstrated background in driving success in the Automotive Market at a Tier 1 supplier. Bachelor's degree in Electronics/Electrical Engineering/Computer Engineering or equivalent. 5+ years' experience in new product development or program/project management. Demonstrated ability to manage various engineering disciplines, including Software, Hardware, Mechanical, Functional Safety, and Cybersecurity. Product Development experience from quote to production on camera/radar/ECUs/ADAS/displays or similar electrical products Experience managing within a matrixed environment, including Quality, Purchasing, Engineering, Sales, and Finance. Strong interpersonal skills and a team player with the ability to work effectively on cross-functional teams. | W25: https://www.liepin.com/job/1982978543.shtml | Z25: all_jobs_jd | AA25: 是 | AB25: 核心基线3718 | AC25: O00292 | AD25: 软件硬件与系统架构 | AE25: 软件与系统 | AF25: 原始6方向/17种类标签 | AG25: 高 | AH25: 正式基线 | AI25: 2bffd5ccb26a693f1296 | AJ25: 核心基线标签直接沿用；技能标签由技能词典从岗位名称/JD补全 | AK25: 上海禾赛科技有限公司 | AL25: 企业别名精确匹配 | AM25: 高 | AN25: 已匹配 | AO25: 感知系统 | AP25: 已上市（纳斯达克HSAI/港交所2525）；2025.9港股IPO募资41.6亿港元；全球激光雷达收入第一 | AQ25: https://www.hesaitech.com | AR25: 公司财报/国信证券研报 | AS25: 上游-核心零部件（激光雷达） | AT25: 激光雷达（LiDAR） | AU25: 已上市 | AV25: 华东 | AW25: 上海市嘉定区/长宁区
A26: 25 | B26: O06012 | C26: 5960 | D26: Figure AI | E26: Figure AI | F26: Helix AI Engineer, Reinforcement Learning | G26: Helix AI Engineer, Reinforcement Learning | J26: 未说明 | K26: 页面未说明或按原文保留，未根据职级推断。 | L26: 未说明 | M26: 高级 | N26: 感知决策与控制算法 | O26: SLAM与控制 | P26: 中游 | Q26: 全尺寸通用人形机器人 | R26: C轮 | S26: 海外 | T26: 美国 加利福尼亚州 圣何塞 | U26: Python; PyTorch; 强化学习; 模仿学习; 深度学习; 机器学习; 仿真; Agent | V26: 页面职责段落显示：Responsibilities Design and implement reinforcement learning algorithms for embodied agents operating in real-world and simulated environments Train policies that learn from interaction, feedback, and large-scale experience across diverse tasks Develop reward modeling, credit assignment, and exploration strategies for complex, long-horizon behaviors Improve policy robustness to real-world challenges such as noise, partial observability, and environment variability Work across online and offline RL settings, including learning from large-scale logged robot data Collaborate closely with pretraining, video, generative, agent, and robot learning teams to integrate RL into the full autonomy stack Build scalable training systems for RL, including distributed rollouts, simulation infrastructure, and experiment management Design evaluation frameworks to measure policy performance, stability, and generalization 【任职要求】 页面任职要求段落显示：Requirements Experience developing and applying reinforcement learning algorithms in complex environments Strong understanding of RL fundamentals (e.g., policy optimization, value methods, model-based RL) Experience training policies in simulation and/or real-world systems Proficiency in Python and deep learning frameworks such as PyTorch Experience with large-scale experimentation and distributed training systems Strong experimental rigor and ability to diagnose and improve learning systems Solid software engineering skills and ability to build scalable, reliable systems Ability to operate independently and drive ambiguous, high-impact technical problems Bonus Qualifications Experience applying RL to robotics, control systems, or embodied AI Experience with large-scale RL infrastructure (distributed rollouts, simulation at scale) Background in offline RL, imitation learning, or hybrid learning approaches Experience with reward modeling or human-in-the-loop learning Experience at leading AI labs such as OpenAI, Google DeepMind, Anthropic, or xAI Familiarity with robotics systems, simulation environments, or real-world deployment constraints Publication record in reinforcement learning, machine learning, or robotics The pay offered for this position may vary based on several individual factors, including job-related knowledge, skills, and experience. The total compensation package may also include additional components/benefits depending on the specific role. This information will be shared if an employment offer is extended. Create a Job Alert Interested in building your career at Figure? Get future opportunities sent straight to your email. Create alert Apply for this job * indicates a required field Quick Apply with MyGreenhouse First Name* Last Name* Prefe | W26: https://job-boards.greenhouse.io/figureai/jobs/4671707006 | Z26: embodied_final | AA26: 是 | AB26: 核心基线3718 | AC26: O06012 | AD26: 感知决策与控制算法 | AE26: SLAM与控制 | AF26: 原始6方向/17种类标签 | AG26: 高 | AH26: 正式基线 | AI26: 93ff5c64e1b76138d415 | AJ26: 核心基线标签直接沿用 | AK26: Figure AI, Inc. | AL26: 企业别名精确匹配 | AM26: 高 | AN26: 已匹配 | AO26: 具身智能本体 | AP26: C轮>$1B（2025.9/估值$39B）；累计~$3.68B；微软/NVIDIA/OpenAI/英特尔/高通/LG等投资 | AQ26: https://www.figure.ai | AR26: 公司官网/Axios/Intel Capital/PitchBook | AS26: 中游-整机（人形机器人） | AT26: 全尺寸通用人形机器人 | AU26: C轮 | AV26: 海外 | AW26: 美国加利福尼亚州圣何塞(San Jose, CA)
A27: 26 | B27: O06009 | C27: 5961 | D27: Figure AI | E27: Figure AI | F27: Helix AI Engineer, Modeling | G27: Helix AI Engineer, Modeling | J27: 未说明 | K27: 页面未说明或按原文保留，未根据职级推断。 | L27: 未说明 | M27: 中级 | N27: 基础理论与前沿研究 | O27: 基础与前沿研究 | P27: 中游 | Q27: 全尺寸通用人形机器人 | R27: C轮 | S27: 海外 | T27: 美国 加利福尼亚州 圣何塞 | U27: Python; PyTorch; 强化学习; 深度学习; 机器学习; 计算机视觉; 自然语言处理; 多模态; 动力学 | V27: 页面职责段落显示：Responsibilities Design and develop model architectures for perception, reasoning, and action across multimodal inputs (e.g., vision, language, proprioception) Build models that learn structured representations of the world, including objects, dynamics, and interactions Advance multimodal learning approaches, including fusion, alignment, and cross-modal reasoning Improve model capabilities in areas such as generalization, robustness, and long-horizon reasoning Work across the model lifecycle, from initial research and prototyping to training and deployment Collaborate closely with pretraining, video, generative, RL, and robot learning teams to integrate modeling advances into the full autonomy stack Design experiments and evaluation frameworks to understand model behavior and guide iteration Contribute to the development of new modeling paradigms for embodied AI systems 【任职要求】 页面任职要求段落显示：Requirements Experience designing and training deep learning models for vision, language, or multimodal systems Strong understanding of modern model architectures (e.g., transformers and related approaches) Experience improving model performance through architectural innovation and experimentation Proficiency in Python and deep learning frameworks such as PyTorch Strong experimental rigor and ability to iterate on model design and performance Solid software engineering skills and ability to build reliable, maintainable systems Ability to operate independently and drive ambiguous, high-impact technical problems Bonus Qualifications Experience with multimodal models (vision-language or vision-language-action systems) Background in representation learning, world models, or structured prediction Experience working on frontier models at companies such as OpenAI, Google DeepMind, Anthropic, Meta, or xAI Familiarity with embodied AI, robotics, or real-world ML systems Experience with large-scale training or distributed systems Publication record in machine learning, computer vision, NLP, or multimodal AI The pay offered for this position may vary based on several individual factors, including job-related knowledge, skills, and experience. The total compensation package may also include additional components/benefits depending on the specific role. This information will be shared if an employment offer is extended. Create a Job Alert Interested in building your career at Figure? Get future opportunities sent straight to your email. Create alert Apply for this job * indicates a required field Quick Apply with MyGreenhouse First Name* Last Name* Preferred First Name Email* Phone Country Phone Resume/CV Attach Attach Dropbox Google Drive Enter manually Enter manually Ac | W27: https://job-boards.greenhouse.io/figureai/jobs/4671712006 | Z27: embodied_final | AA27: 是 | AB27: 核心基线3718 | AC27: O06009 | AD27: 基础理论与前沿研究 | AE27: 基础与前沿研究 | AF27: 原始6方向/17种类标签 | AG27: 高 | AH27: 正式基线 | AI27: 47478abc93534a94de40 | AJ27: 核心基线标签直接沿用 | AK27: Figure AI, Inc. | AL27: 企业别名精确匹配 | AM27: 高 | AN27: 已匹配 | AO27: 具身智能本体 | AP27: C轮>$1B（2025.9/估值$39B）；累计~$3.68B；微软/NVIDIA/OpenAI/英特尔/高通/LG等投资 | AQ27: https://www.figure.ai | AR27: 公司官网/Axios/Intel Capital/PitchBook | AS27: 中游-整机（人形机器人） | AT27: 全尺寸通用人形机器人 | AU27: C轮 | AV27: 海外 | AW27: 美国加利福尼亚州圣何塞(San Jose, CA)
A28: 27 | B28: O06008 | C28: 5957 | D28: Figure AI | E28: Figure AI | F28: Helix AI Engineer, Generative AI | G28: Helix AI Engineer, Generative AI | J28: 未说明 | K28: 页面未说明或按原文保留，未根据职级推断。 | L28: 未说明 | M28: 中级 | N28: 感知决策与控制算法 | O28: 视觉与多模态 | P28: 中游 | Q28: 全尺寸通用人形机器人 | R28: C轮 | S28: 海外 | T28: 美国 加利福尼亚州 圣何塞 | U28: Python; PyTorch; 深度学习; 机器学习; 计算机视觉; Diffusion; 多模态; 仿真; 传感器; Agent | V28: 页面职责段落显示：Responsibilities Design, train, and deploy large-scale generative models, with a focus on diffusion-based approaches for vision, video, and multimodal data Develop models that improve robot perception, world modeling, and prediction from raw sensory inputs Build generative systems for synthetic data creation, augmentation, and dataset scaling for robot learning Explore and implement state-of-the-art techniques in diffusion, generative modeling, and multimodal foundation models Optimize training pipelines for large-scale generative models across distributed systems Work closely with data, training infrastructure, and agent teams to integrate generative models into the full autonomy stack Evaluate model quality, robustness, and generalization across real-world scenarios Contribute to the design of scalable experimentation frameworks for generative model development 【任职要求】 页面任职要求段落显示：Requirements Experience training and deploying generative models (diffusion, autoregressive, or related approaches) at scale Strong understanding of modern deep learning techniques for vision and/or multimodal systems Proficiency in Python and deep learning frameworks such as PyTorch Experience working with large-scale datasets and distributed training systems Strong experimental rigor and ability to iterate quickly on model performance Solid software engineering skills and ability to build reliable, maintainable systems Ability to operate independently and own ambiguous, high-impact technical problems Bonus Qualifications Experience with diffusion models for image or video generation Experience with multimodal foundation models (vision-language or vision-language-action) Background in synthetic data generation or simulation for robotics or embodied AI Experience optimizing large-scale training (multi-node, GPU clusters, etc.) Familiarity with 3D, video prediction, or world models Prior work in robotics, embodied AI, or real-world ML systems Publication record in machine learning, computer vision, or generative modeling The pay offered for this position may vary based on several individual factors, including job-related knowledge, skills, and experience. The total compensation package may also include additional components/benefits depending on the specific role. This information will be shared if an employment offer is extended. Create a Job Alert Interested in building your career at Figure? Get future opportunities sent straight to your email. Create alert Apply for this job * indicates a required field Quick Apply with MyGreenhouse First Name* Last Name* Preferred First Name Email* Phone Country Phone Resume/CV Attach Attach Dropbox Google Drive Enter man | W28: https://job-boards.greenhouse.io/figureai/jobs/4671699006 | Z28: embodied_final | AA28: 是 | AB28: 核心基线3718 | AC28: O06008 | AD28: 感知决策与控制算法 | AE28: 视觉与多模态 | AF28: 原始6方向/17种类标签 | AG28: 高 | AH28: 正式基线 | AI28: 1b86461b30440b79a6fe | AJ28: 核心基线标签直接沿用 | AK28: Figure AI, Inc. | AL28: 企业别名精确匹配 | AM28: 高 | AN28: 已匹配 | AO28: 具身智能本体 | AP28: C轮>$1B（2025.9/估值$39B）；累计~$3.68B；微软/NVIDIA/OpenAI/英特尔/高通/LG等投资 | AQ28: https://www.figure.ai | AR28: 公司官网/Axios/Intel Capital/PitchBook | AS28: 中游-整机（人形机器人） | AT28: 全尺寸通用人形机器人 | AU28: C轮 | AV28: 海外 | AW28: 美国加利福尼亚州圣何塞(San Jose, CA)
A29: 28 | B29: O06050 | C29: 5993 | D29: Figure AI | E29: Figure AI | F29: Helix Data Creator (Day Shift) | G29: San Jose, CA | J29: 未说明 | K29: 页面未说明或按原文保留，未根据职级推断。 | L29: 未说明 | M29: 高级 | N29: 软件硬件与系统架构 | O29: 软件与系统 | P29: 中游 | Q29: 全尺寸通用人形机器人 | R29: C轮 | S29: 海外 | T29: 美国 加利福尼亚州 圣何塞 | U29: 传感器; Prompt Engineering; 数据采集 | V29: 页面职责段落显示：Responsibilities: Data collection: Wear sensor suits to perform repetitive, precise physical movements (walking, lifting, reaching) that guide the robot and generate training data, for up to 8 hours per shift. SOP adherence: Follow detailed "Ground Truth" movement protocols exactly, with zero deviation, to keep data consistent and high quality. Equipment care: Help with donning and doffing sensor suits, follow proper setup and shutdown procedures, and promptly report any hardware issues to your Inventory Team Lead. Feedback & quality: Flag bugs or issues during collection, share daily feedback to improve the process, and work comfortably toward daily data-collection targets. Safety: Keep a clean, organized workspace and follow ergonomic guidelines to stay safe during repetitive tasks. We want you to speak up early about anything that doesn't feel right. 【任职要求】 页面任职要求段落显示：Requirements: Able to perform repetitive standing, walking, lifting, reaching, and full-range limb motions required for motion-capture across an 8+ hour shift Excellent physical coordination, spatial awareness, and sustained focus Quick to master new physical tasks and find the most efficient way to perform them Open to constructive feedback and motivated to keep improving Strong attendance and punctuality; reliable, accountable, and able to work both independently and within a small team Reliable transportation, and able to travel to different work sites around the Bay Area (locations change regularly) Comfortable in a fast-paced startup environment with shifting priorities Legally authorized to work in the US Bonus Qualifications: Technical or hands-on background (electronics, mechanical, IT, fabrication, etc.) Hardware/software troubleshooting experience VR headset experience and/or extensive video-game experience (great proxies for spatial tracking and hand-eye coordination) Prior robotics or motion-capture exposure Military background A genuine passion for robotics and helping scale the deployment of humanoid robots This role begins as a 6 month fixed-term agreement, with potential for longer-term opportunities depending on your contributions and interests. We’re looking for motivated people who want to support real-world robot development and grow with us. The US base salary range for this full-time position starts at $30/hr. The pay offered for this position may vary based on several individual factors, including job-related knowledge, skills, and experience. The total compensation package may also include additional components/benefits depending on the specific role. This information will be shared if an employment offer is extended. Create a Job Aler | W29: https://job-boards.greenhouse.io/figureai/jobs/4693410006 | Z29: embodied_final | AA29: 是 | AB29: 核心基线3718 | AC29: O06050 | AD29: 软件硬件与系统架构 | AE29: 软件与系统 | AF29: 原始6方向/17种类标签 | AG29: 高 | AH29: 正式基线 | AI29: 613a5efefb3fc77203f3 | AJ29: 核心基线标签直接沿用 | AK29: Figure AI, Inc. | AL29: 企业别名精确匹配 | AM29: 高 | AN29: 已匹配 | AO29: 具身智能本体 | AP29: C轮>$1B（2025.9/估值$39B）；累计~$3.68B；微软/NVIDIA/OpenAI/英特尔/高通/LG等投资 | AQ29: https://www.figure.ai | AR29: 公司官网/Axios/Intel Capital/PitchBook | AS29: 中游-整机（人形机器人） | AT29: 全尺寸通用人形机器人 | AU29: C轮 | AV29: 海外 | AW29: 美国加利福尼亚州圣何塞(San Jose, CA)
A30: 29 | B30: O06011 | C30: 5959 | D30: Figure AI | E30: Figure AI | F30: Helix AI Engineer, Pretraining | G30: Helix AI Engineer, Pretraining | J30: 未说明 | K30: 页面未说明或按原文保留，未根据职级推断。 | L30: 未说明 | M30: 中级 | N30: 基础理论与前沿研究 | O30: 基础与前沿研究 | P30: 中游 | Q30: 全尺寸通用人形机器人 | R30: C轮 | S30: 海外 | T30: 美国 加利福尼亚州 圣何塞 | U30: Python; PyTorch; 深度学习; 机器学习; 计算机视觉; 自然语言处理; Transformer; 多模态; 动力学; Agent | V30: 页面职责段落显示：Responsibilities Design and train large-scale foundation models across multimodal data (e.g., text, vision, and robot data) Develop pretraining strategies that improve generalization, reasoning, and transfer to downstream embodied tasks Explore and implement architectures including transformer-based and emerging foundation model paradigms Work on scaling laws, dataset mixture design, and training dynamics for frontier models Build and optimize large-scale distributed training pipelines across multi-node GPU clusters Collaborate closely with video, generative, agent, and robot learning teams to integrate pretrained models into the autonomy stack Design evaluation frameworks to measure reasoning ability, robustness, and cross-domain generalization Contribute to post-training approaches including fine-tuning, alignment, and model adaptation 【任职要求】 页面任职要求段落显示：Requirements Experience training large-scale foundation models or working on pretraining for LLMs or multimodal systems Strong understanding of modern deep learning architectures, especially transformers Experience with large-scale distributed training and optimization Proficiency in Python and deep learning frameworks such as PyTorch Strong experimental rigor and ability to iterate on model design and training strategies Solid software engineering skills and ability to build scalable, reliable systems Ability to operate independently and drive ambiguous, high-impact technical problems Bonus Qualifications Experience working on frontier foundation models at companies such as Anthropic, OpenAI, Google DeepMind, or xAI Experience with multimodal pretraining (vision-language or vision-language-action models) Background in scaling laws, dataset curation, and large-scale data mixture optimization Experience with post-training techniques such as RLHF, reward modeling, or alignment methods Familiarity with embodied AI, robotics, or real-world deployment constraints Publication record in machine learning, NLP, or multimodal AI The pay offered for this position may vary based on several individual factors, including job-related knowledge, skills, and experience. The total compensation package may also include additional components/benefits depending on the specific role. This information will be shared if an employment offer is extended. Create a Job Alert Interested in building your career at Figure? Get future opportunities sent straight to your email. Create alert Apply for this job * indicates a required field Quick Apply with MyGreenhouse First Name* Last Name* Preferred First Name Email* Phone Country Phone Resume/CV Attach Attach Dropbox Google Drive Enter manu | W30: https://job-boards.greenhouse.io/figureai/jobs/4671704006 | Z30: embodied_final | AA30: 是 | AB30: 核心基线3718 | AC30: O06011 | AD30: 基础理论与前沿研究 | AE30: 基础与前沿研究 | AF30: 原始6方向/17种类标签 | AG30: 高 | AH30: 正式基线 | AI30: 8f5041293373f4e1939a | AJ30: 核心基线标签直接沿用 | AK30: Figure AI, Inc. | AL30: 企业别名精确匹配 | AM30: 高 | AN30: 已匹配 | AO30: 具身智能本体 | AP30: C轮>$1B（2025.9/估值$39B）；累计~$3.68B；微软/NVIDIA/OpenAI/英特尔/高通/LG等投资 | AQ30: https://www.figure.ai | AR30: 公司官网/Axios/Intel Capital/PitchBook | AS30: 中游-整机（人形机器人） | AT30: 全尺寸通用人形机器人 | AU30: C轮 | AV30: 海外 | AW30: 美国加利福尼亚州圣何塞(San Jose, CA)
A31: 30 | B31: O03717 | C31: 6085 | D31: 酷哇科技 | E31: 酷哇科技 | F31: 世界模型方向实习研究员（World Model / World Action Model ） | J31: 未说明 | L31: 未说明 | M31: 中级 | N31: 基础理论与前沿研究 | O31: 基础与前沿研究 | P31: 中游 | Q31: 城市具身智能/世界动作模型/市政环卫/共享出行/工业制造/物业服务 | R31: 已上市 | S31: 华东 | T31: 安徽省芜湖市 | U31: C | V31: 职位描述岗位职责：密切跟踪学术界（ICLR、NeurIPS、CVPR 等）在 Embodied AI、World Models、生成式序列预测等领域的最新工作。 对现有的研发成果进行总结和沉淀，鼓励并支持在国际顶级学术会议上撰写、发表高水平学术论文或 | W31: Moka | Z31: all_jobs_jd | AA31: 是 | AB31: 核心基线3718 | AC31: O03717 | AD31: 基础理论与前沿研究 | AE31: 基础与前沿研究 | AF31: 原始6方向/17种类标签 | AG31: 高 | AH31: 正式基线 | AI31: 690dfcdbee4fd5f97598 | AJ31: 核心基线标签直接沿用；技能标签由技能词典从岗位名称/JD补全 | AK31: 酷哇科技有限公司 | AL31: 企业别名精确匹配 | AM31: 高 | AN31: 已匹配 | AO31: 具身智能本体 | AP31: 已上市；拟赴港IPO(华泰+德银联席保荐);估值超30亿美元(约234亿港元);软银中国/亚投资本/软银集团等投资;隐秘完成超6亿美元新融资 | AQ31: 未公开(拟IPO阶段) | AR31: 36氪/东方财富/科创板日报/经济观察报/智通财经/证券日报 | AS31: 中游-整机+算法(世界模型) | AT31: 城市具身智能/世界动作模型/市政环卫/共享出行/工业制造/物业服务 | AU31: 已上市 | AV31: 华东 | AW31: 安徽省芜湖市; 上海市
A32: 31 | B32: O06020 | C32: 5910 | D32: Figure AI | E32: Figure AI | F32: Manufacturing Test Engineer, PCBA | G32: Manufacturing Test Engineer, PCBA | J32: 未说明 | K32: 页面未说明或按原文保留，未根据职级推断。 | L32: 未说明 | M32: 高级 | N32: 感知决策与控制算法 | O32: 视觉与多模态 | P32: 中游 | Q32: 全尺寸通用人形机器人 | R32: C轮 | S32: 海外 | T32: 美国 加利福尼亚州 圣何塞 | U32: Python; 计算机视觉; 嵌入式开发; SolidWorks; Catia; NX; UG; 数据采集 | V32: 页面职责段落显示：Responsibilities: Own test coverage strategy for all custom PCBAs across the product Design, validate, and deploy bed-of-nails ICT and FCT test fixtures, working directly with overseas test vendors and fixture houses Collaborate with electrical and firmware teams to define test hooks, firmware test modes, and diagnostics coverage Specify and validate test software, including automated test sequencing, result logging, and failure triage Serve as the test lead on-site at CMs during NPI builds to bring up, debug, and improve test coverage and throughput Monitor test yield data, drive root cause analysis for failures, and recommend corrective actions Act as the first line of defense when boards or testers start failing Ensure test processes scale from EVT through MP, with clear handoff documentation and ongoing vendor support 【任职要求】 页面任职要求段落显示：Requirements: 5+ years of experience in PCBA manufacturing test, ideally with high-complexity boards and tight timelines Hands-on experience with ICT and FCT system design, bed-of-nails fixture development, and board-level debug Strong understanding of DFT (Design for Testability) and how to collaborate with EE/FW teams early in the design cycle Experience working directly with overseas CMs and test vendors Familiarity with test automation frameworks, data collection, and reporting tools Able to read schematics, probe/debug hardware, and communicate clearly across disciplines Strong proficiency in writing Python for interfacing with real hardware Willingness to travel overseas 40% of the time Bonus Qualifications: Bachelor or graduate degree in Electrical Engineering or related field. Experience with Altium. CAD experience (EPLAN, Solidworks Electrical, CATIA, etc) Embedded programming of DSPs, microcontrollers, and FPGAs. Robotics or other high tech industry experience. The US base salary range for this full-time position is between $160,000 and $250,000 annually. The pay offered for this position may vary based on several individual factors, including job-related knowledge, skills, and experience. The total compensation package may also include additional components/benefits depending on the specific role. This information will be shared if an employment offer is extended. Create a Job Alert Interested in building your career at Figure? Get future opportunities sent straight to your email. Create alert Apply for this job * indicates a required field Quick Apply with MyGreenhouse First Name* Last Name* Email* Phone Country Phone Resume/CV Attach Attach Dropbox Google Drive Enter manually Enter manually Accepted file types: pdf, doc, docx, txt, rtf LinkedIn P | W32: https://job-boards.greenhouse.io/figureai/jobs/4574399006 | Z32: embodied_final | AA32: 是 | AB32: 核心基线3718 | AC32: O06020 | AD32: 感知决策与控制算法 | AE32: 视觉与多模态 | AF32: 原始6方向/17种类标签 | AG32: 高 | AH32: 正式基线 | AI32: 3c3a7defadcc12536734 | AJ32: 核心基线标签直接沿用 | AK32: Figure AI, Inc. | AL32: 企业别名精确匹配 | AM32: 高 | AN32: 已匹配 | AO32: 具身智能本体 | AP32: C轮>$1B（2025.9/估值$39B）；累计~$3.68B；微软/NVIDIA/OpenAI/英特尔/高通/LG等投资 | AQ32: https://www.figure.ai | AR32: 公司官网/Axios/Intel Capital/PitchBook | AS32: 中游-整机（人形机器人） | AT32: 全尺寸通用人形机器人 | AU32: C轮 | AV32: 海外 | AW32: 美国加利福尼亚州圣何塞(San Jose, CA)
A33: 32 | B33: O06027 | C33: 5940 | D33: Figure AI | E33: Figure AI | F33: Commercial Launch Technician | G33: San Jose, CA | J33: 未说明 | K33: 页面未说明或按原文保留，未根据职级推断。 | L33: 未说明 | M33: 中级 | N33: 感知决策与控制算法 | O33: 视觉与多模态 | P33: 中游 | Q33: 全尺寸通用人形机器人 | R33: C轮 | S33: 海外 | T33: 美国 加利福尼亚州 圣何塞 | U33: 计算机视觉; 电机驱动; 传感器; PCB设计; Prompt Engineering; Catia | V33: 页面职责段落显示：Responsibilities: Responsible for the physical setup of humanoid robots and necessary site infrastructure at new commercial or residential locations. Perform routine maintenance and inspections of the humanoid robot fleet Proficient in troubleshooting mechanical, electrical and software-based issues Work closely with engineering, build, validation and fabrication teams to resolve issues quickly Verify use-case stability on-site and provide direct, actionable feedback to the Development teams to drive product improvements. Maintain detailed and accurate records of all maintenance and repairs Develop tools and document diagnostic procedures for process improvement Heavy travel to customer or development partner sites, up to 75% Ability to follow assembly documentation Ability to work under short timelines when needed 【任职要求】 页面任职要求段落显示：Requirements: 3+ years experience working with complex systems Familiarity with computer based tools such as but not limited to CMD prompt, Google Suite, in house development GUI’s Familiarity with electrical hardware based diagnostic tools such as but not limited to Scope, Digital MultiMeter, Current Probes Familiarity with torque tools and mechanical assembly Ability to read PCB and Harness schematics Full system architecture diagnostic experience and organized diagnostic processes Ability to remove and replace mechanical components up to 50lbs Great attitude and excited to face challenges Valid Driver's License and clean driving record Bonus Qualifications: Catia or CAD based program experience Fabrication experience PCB Rework experience DAQ system implementation experience Small brushless motor experience Harmonic drive, clutches, torque/force sensor knowledge Robotics experience Experience using Jira, Confluence, Slack IPC 610, 620 or J-Std-001 The US base salary range for this full-time position is between $35 - $65/hr. The pay offered for this position may vary based on several individual factors, including job-related knowledge, skills, and experience. The total compensation package may also include additional components/benefits depending on the specific role. This information will be shared if an employment offer is extended. Create a Job Alert Interested in building your career at Figure? Get future opportunities sent straight to your email. Create alert Apply for this job * indicates a required field Quick Apply with MyGreenhouse First Name* Last Name* Email* Phone Country Phone Resume/CV Attach Attach Dropbox Google Drive Enter manually Enter manually Accepted file types: pdf, doc, docx, txt, rtf LinkedIn Profile Website Submit application Power | W33: https://job-boards.greenhouse.io/figureai/jobs/4651747006 | Z33: embodied_final | AA33: 是 | AB33: 核心基线3718 | AC33: O06027 | AD33: 感知决策与控制算法 | AE33: 视觉与多模态 | AF33: 原始6方向/17种类标签 | AG33: 高 | AH33: 正式基线 | AI33: f86c1adc9f0f87a87d4b | AJ33: 核心基线标签直接沿用 | AK33: Figure AI, Inc. | AL33: 企业别名精确匹配 | AM33: 高 | AN33: 已匹配 | AO33: 具身智能本体 | AP33: C轮>$1B（2025.9/估值$39B）；累计~$3.68B；微软/NVIDIA/OpenAI/英特尔/高通/LG等投资 | AQ33: https://www.figure.ai | AR33: 公司官网/Axios/Intel Capital/PitchBook | AS33: 中游-整机（人形机器人） | AT33: 全尺寸通用人形机器人 | AU33: C轮 | AV33: 海外 | AW33: 美国加利福尼亚州圣何塞(San Jose, CA)
A34: 33 | B34: O06031 | C34: 5980 | D34: Figure AI | E34: Figure AI | F34: Field Service Technician - Commercial Site Team | G34: Los Angeles, CA | J34: 未说明 | K34: 页面未说明或按原文保留，未根据职级推断。 | L34: 未说明 | M34: 中级 | N34: 感知决策与控制算法 | O34: 视觉与多模态 | P34: 中游 | Q34: 全尺寸通用人形机器人 | R34: C轮 | S34: 海外 | T34: 美国 加利福尼亚州 圣何塞 | U34: 计算机视觉; 电机驱动; 传感器; PCB设计; Prompt Engineering; Catia | V34: 页面职责段落显示：Responsibilities: Responsible for the maintenance of humanoid robots and necessary site infrastructure at commercial or residential locations. Perform routine maintenance and inspections of the humanoid robot fleet Proficient in troubleshooting mechanical, electrical and software-based issues Work closely with engineering, build, validation and fabrication teams to resolve issues quickly Verify use-case stability on-site and provide direct, actionable feedback to the Development teams to drive product improvements. Maintain detailed and accurate records of all maintenance and repairs Develop tools and document diagnostic procedures for process improvement Ability to follow assembly documentation Ability to work under short timelines when needed Experience in customer-facing positions 【任职要求】 页面任职要求段落显示：Requirements: 3+ years experience working with complex systems Familiarity with computer based tools such as but not limited to CMD prompt, Google Suite, in house development GUI’s Familiarity with electrical hardware based diagnostic tools such as but not limited to Scope, Digital MultiMeter, Current Probes Familiarity with torque tools and mechanical assembly Ability to read PCB and Harness schematics Full system architecture diagnostic experience and organized diagnostic processes Ability to remove and replace mechanical components up to 50lbs Great attitude and excited to face challenges Valid drivers license and clean driving record Bonus Qualifications: Catia or CAD based program experience Fabrication experience PCB Rework experience DAQ system implementation experience Small brushless motor experience Harmonic drive, clutches, torque/force sensor knowledge Robotics experience Experience using Jira, Confluence, Slack IPC 610, 620 or J-Std-001 The US base salary range for this full-time position is between $35 - $50/hr. The pay offered for this position may vary based on several individual factors, including job-related knowledge, skills, and experience. The total compensation package may also include additional components/benefits depending on the specific role. This information will be shared if an employment offer is extended. Create a Job Alert Interested in building your career at Figure? Get future opportunities sent straight to your email. Create alert Apply for this job * indicates a required field Quick Apply with MyGreenhouse First Name* Last Name* Email* Phone Country Phone Resume/CV Attach Attach Dropbox Google Drive Enter manually Enter manually Accepted file types: pdf, doc, docx, txt, rtf LinkedIn Profile Website Submit application Powere | W34: https://job-boards.greenhouse.io/figureai/jobs/4683847006 | Z34: embodied_final | AA34: 是 | AB34: 核心基线3718 | AC34: O06031 | AD34: 感知决策与控制算法 | AE34: 视觉与多模态 | AF34: 原始6方向/17种类标签 | AG34: 高 | AH34: 正式基线 | AI34: 8f642a2e94b63f42b2a1 | AJ34: 核心基线标签直接沿用 | AK34: Figure AI, Inc. | AL34: 企业别名精确匹配 | AM34: 高 | AN34: 已匹配 | AO34: 具身智能本体 | AP34: C轮>$1B（2025.9/估值$39B）；累计~$3.68B；微软/NVIDIA/OpenAI/英特尔/高通/LG等投资 | AQ34: https://www.figure.ai | AR34: 公司官网/Axios/Intel Capital/PitchBook | AS34: 中游-整机（人形机器人） | AT34: 全尺寸通用人形机器人 | AU34: C轮 | AV34: 海外 | AW34: 美国加利福尼亚州圣何塞(San Jose, CA)
A35: 34 | B35: O06045 | C35: 5969 | D35: Figure AI | E35: Figure AI | F35: Data Quality Partner Lead | G35: San Jose, CA | J35: 未说明 | K35: 页面未说明或按原文保留，未根据职级推断。 | L35: 未说明 | M35: 中级 | N35: 软件硬件与系统架构 | O35: 软件与系统 | P35: 中游 | Q35: 全尺寸通用人形机器人 | R35: C轮 | S35: 海外 | T35: 美国 加利福尼亚州 圣何塞 | U35: 端到端学习; CAN; 数据标注 | V35: 页面职责段落显示：Responsibilities: Own Figure’s external annotation and review vendor strategy end to end, from sourcing through onboarding through ongoing performance management Build the vendor pipeline from zero by identifying and engaging BPOs, specialized labeling firms, crowdsourcing platforms, and emerging providers in the AI data ecosystem Run structured evaluations of prospective vendors, including pilots, quality benchmarking, and capacity testing, and make clear recommendations on who to scale with Translate the Data Quality team’s standards and methodologies into vendor specs, making sure the bar we set internally is the bar our partners deliver against Stand up the operating model for managing partners at scale, including scorecards, escalation paths, and the tooling 【任职要求】 页面任职要求段落显示：Requirements: 5+ years in vendor management, BPO/outsourcing partnerships, strategic sourcing, or operations roles with significant external partner ownership Track record of building or scaling a vendor function from an early stage, ideally in a domain where quality was the primary lever Comfortable rapidly building and deploying apps/agents using AI coding tools to build internal tools, dashboards, and trackers (zero technical academic background necessary) Excellent written and verbal communication skills, especially when setting expectations with external partners Comfortable operating with ambiguity and managing multiple concurrent partner relationships Low ego, team player with can-do attitude Bonus Qualifications: Direct experience managing data annotation, labeling, or content review vendors Background at a frontier AI lab, autonomous vehicle company, or other organization where data quality at scale was a core problem A passion for helping scale the deployment of learning humanoid robots The pay offered for this position may vary based on several individual factors, including job-related knowledge, skills, and experience. The total compensation package may also include additional components/benefits depending on the specific role. This information will be shared if an employment offer is extended. The US base salary range for this full-time position is between $120,000 – $180,000 annually. The pay offered for this position may vary based on several individual factors, including job-related knowledge, skills, and experience. The total compensation package may also include additional components/benefits depending on the specific role. This information will be shared if an employment offer is extended. Create a Job Alert Interested in building your care | W35: https://job-boards.greenhouse.io/figureai/jobs/4679201006 | Z35: embodied_final | AA35: 是 | AB35: 核心基线3718 | AC35: O06045 | AD35: 软件硬件与系统架构 | AE35: 软件与系统 | AF35: 原始6方向/17种类标签 | AG35: 高 | AH35: 正式基线 | AI35: cc468b03a0ed9f106353 | AJ35: 核心基线标签直接沿用 | AK35: Figure AI, Inc. | AL35: 企业别名精确匹配 | AM35: 高 | AN35: 已匹配 | AO35: 具身智能本体 | AP35: C轮>$1B（2025.9/估值$39B）；累计~$3.68B；微软/NVIDIA/OpenAI/英特尔/高通/LG等投资 | AQ35: https://www.figure.ai | AR35: 公司官网/Axios/Intel Capital/PitchBook | AS35: 中游-整机（人形机器人） | AT35: 全尺寸通用人形机器人 | AU35: C轮 | AV35: 海外 | AW35: 美国加利福尼亚州圣何塞(San Jose, CA)
A36: 35 | B36: O06034 | C36: 5973 | D36: Figure AI | E36: Figure AI | F36: Service Technician - Commercial Site Team | G36: Reno, NV | J36: 未说明 | K36: 页面未说明或按原文保留，未根据职级推断。 | L36: 未说明 | M36: 中级 | N36: 感知决策与控制算法 | O36: 视觉与多模态 | P36: 中游 | Q36: 全尺寸通用人形机器人 | R36: C轮 | S36: 海外 | T36: 美国 加利福尼亚州 圣何塞 | U36: 计算机视觉; 电机驱动; 传感器; PCB设计; Prompt Engineering; Catia | V36: 页面职责段落显示：Responsibilities: Responsible for the maintenance of humanoid robots and necessary site infrastructure at commercial or residential locations. Perform routine maintenance and inspections of the humanoid robot fleet Proficient in troubleshooting mechanical, electrical and software-based issues Work closely with engineering, build, validation and fabrication teams to resolve issues quickly Verify use-case stability on-site and provide direct, actionable feedback to the Development teams to drive product improvements. Maintain detailed and accurate records of all maintenance and repairs Develop tools and document diagnostic procedures for process improvement Ability to follow assembly documentation Ability to work under short timelines when needed Experience in customer-facing positions 【任职要求】 页面任职要求段落显示：Requirements: 3+ years experience working with complex systems Familiarity with computer based tools such as but not limited to CMD prompt, Google Suite, in house development GUI’s Familiarity with electrical hardware based diagnostic tools such as but not limited to Scope, Digital MultiMeter, Current Probes Familiarity with torque tools and mechanical assembly Ability to read PCB and Harness schematics Full system architecture diagnostic experience and organized diagnostic processes Ability to remove and replace mechanical components up to 50lbs Great attitude and excited to face challenges Valid drivers license and clean driving record Bonus Qualifications: Catia or CAD based program experience Fabrication experience PCB Rework experience DAQ system implementation experience Small brushless motor experience Harmonic drive, clutches, torque/force sensor knowledge Robotics experience Experience using Jira, Confluence, Slack IPC 610, 620 or J-Std-001 The pay offered for this position may vary based on several individual factors, including job-related knowledge, skills, and experience. The total compensation package may also include additional components/benefits depending on the specific role. This information will be shared if an employment offer is extended. Create a Job Alert Interested in building your career at Figure? Get future opportunities sent straight to your email. Create alert Apply for this job * indicates a required field Quick Apply with MyGreenhouse First Name* Last Name* Email* Phone Country Phone Resume/CV Attach Attach Dropbox Google Drive Enter manually Enter manually Accepted file types: pdf, doc, docx, txt, rtf LinkedIn Profile Website Submit application | W36: https://job-boards.greenhouse.io/figureai/jobs/4681835006 | Z36: embodied_final | AA36: 是 | AB36: 核心基线3718 | AC36: O06034 | AD36: 感知决策与控制算法 | AE36: 视觉与多模态 | AF36: 原始6方向/17种类标签 | AG36: 高 | AH36: 正式基线 | AI36: 1bdc8c2f9ac51341758e | AJ36: 核心基线标签直接沿用 | AK36: Figure AI, Inc. | AL36: 企业别名精确匹配 | AM36: 高 | AN36: 已匹配 | AO36: 具身智能本体 | AP36: C轮>$1B（2025.9/估值$39B）；累计~$3.68B；微软/NVIDIA/OpenAI/英特尔/高通/LG等投资 | AQ36: https://www.figure.ai | AR36: 公司官网/Axios/Intel Capital/PitchBook | AS36: 中游-整机（人形机器人） | AT36: 全尺寸通用人形机器人 | AU36: C轮 | AV36: 海外 | AW36: 美国加利福尼亚州圣何塞(San Jose, CA)
A37: 36 | B37: O06030 | C37: 5953 | D37: Figure AI | E37: Figure AI | F37: Deployment Logistics Coordinator | G37: San Jose, CA | J37: 未说明 | K37: 页面未说明或按原文保留，未根据职级推断。 | L37: 未说明 | M37: 初级 | N37: 感知决策与控制算法 | O37: 视觉与多模态 | P37: 中游 | Q37: 全尺寸通用人形机器人 | R37: C轮 | S37: 海外 | T37: 美国 加利福尼亚州 圣何塞 | U37: 计算机视觉; 数据采集 | V37: 页面职责段落显示：Responsibilities: Schedule, track, and manage deployment and return of robots and equipment between HQ, customer pilot sites, and field data collection locations. Coordinate domestic and international shipments, including freight carriers, customs documentation, and delivery timelines. Maintain accurate, real-time records of robot and equipment inventory in the field with locations, status, and availability. Own the process for preparing, inspecting, and documenting equipment before deployment and upon return. Serve as the primary logistics point of contact across Commercial Operations, ensuring clear communication on availability, schedules, and any delays or issues. Maintain detailed logs of equipment usage, shipping costs, and deployment history. When needed, travel to customer sites or events to support equipment setup, handoff, or retrieval. 【任职要求】 页面任职要求段落显示：Requirements: 2+ years experience in logistics, shipping, asset management, or field operations coordination Strong organizational skills and meticulous attention to detail Excellent communication skills - comfortable coordinating across multiple teams and external partners Proficiency with tracking systems, spreadsheets, and project management tools (e.g., Google Sheets, Jira, Confluence) Valid driver's license; willingness to travel up to 25% of the time Thrives in a fast-paced, rapidly changing environment Bonus Qualifications: Experience in robotics, autonomous vehicles, or hardware company logistics Familiarity with international shipping, customs, and import/export documentation Experience supporting trade shows, demos, or customer events Exposure to inventory management systems or ERP tools The US base salary range for this full-time position is between $50 - $60 / hour. The pay offered for this position may vary based on several individual factors, including job-related knowledge, skills, and experience. The total compensation package may also include additional components/benefits depending on the specific role. This information will be shared if an employment offer is extended. Create a Job Alert Interested in building your career at Figure? Get future opportunities sent straight to your email. Create alert Apply for this job * indicates a required field Quick Apply with MyGreenhouse First Name* Last Name* Email* Phone Country Phone Resume/CV Attach Attach Dropbox Google Drive Enter manually Enter manually Accepted file types: pdf, doc, docx, txt, rtf LinkedIn Profile Website Submit application | W37: https://job-boards.greenhouse.io/figureai/jobs/4666290006 | Z37: embodied_final | AA37: 是 | AB37: 核心基线3718 | AC37: O06030 | AD37: 感知决策与控制算法 | AE37: 视觉与多模态 | AF37: 原始6方向/17种类标签 | AG37: 高 | AH37: 正式基线 | AI37: 2de6c54b310f2ab2d753 | AJ37: 核心基线标签直接沿用 | AK37: Figure AI, Inc. | AL37: 企业别名精确匹配 | AM37: 高 | AN37: 已匹配 | AO37: 具身智能本体 | AP37: C轮>$1B（2025.9/估值$39B）；累计~$3.68B；微软/NVIDIA/OpenAI/英特尔/高通/LG等投资 | AQ37: https://www.figure.ai | AR37: 公司官网/Axios/Intel Capital/PitchBook | AS37: 中游-整机（人形机器人） | AT37: 全尺寸通用人形机器人 | AU37: C轮 | AV37: 海外 | AW37: 美国加利福尼亚州圣何塞(San Jose, CA)
A38: 37 | B38: O06022 | C38: 5927 | D38: Figure AI | E38: Figure AI | F38: Quality Engineer, Metrology | G38: Quality Engineer, Metrology | J38: 未说明 | K38: 页面未说明或按原文保留，未根据职级推断。 | L38: 未说明 | M38: 中级 | N38: 感知决策与控制算法 | O38: 视觉与多模态 | P38: 中游 | Q38: 全尺寸通用人形机器人 | R38: C轮 | S38: 海外 | T38: 美国 加利福尼亚州 圣何塞 | U38: 计算机视觉 | V38: 页面职责段落显示：Responsibilities: Manage Incoming Quality Lab, manage QC workload, priority and make sure all equipments are in good operation oder Develop Quality Control Plan and Quality Work Instructions Lead and supervise QC inspectors to perform dimensional, visual and functional verifications Lead MRB meetings, manage MRB processes, collaborate with associated parties to resolve issues related Perform dimensional, visual, functional verification and other inspections per QC plan or Work Instructions Review and Approve First Article Inspection Report Initiate Non-conformance Report and Oversee Open Quality Tracker Keep the QC area in clean and organized conditions Support other QC related activities 【任职要求】 页面任职要求段落显示：Requirements: 5+ years of similar experiences in a manufacturing environment Able to read and interpret engineering drawings and CAD models Expert on GD&T ASME Y14.5-2009 or ASME Y14.5-2018 Expert on Sampling Plan C=0, and ASQ Z1.4/MIL-STD-105 Proficiency with common inspection tools, including Digital Height Gage, caliper, micrometer, thread gages, etc. Attention to detail: capable of maintaining precision in a fast-paced environment Strong communication skills: good verbal and written communications skills with analytics and numeracy Bonus Qualifications: Proficiency with CMM, OMM Certifications such as ASQ CQE, CQM, CRE, CQA. Robotics or other high tech industry experience Understanding of manufacturing processes, quality systems, and industrial engineering principles The US base salary range for this full-time position is between $150,000 – $225,000 base salary annually. The pay offered for this position may vary based on several individual factors, including job-related knowledge, skills, and experience. The total compensation package may also include additional components/benefits depending on the specific role. This information will be shared if an employment offer is extended. Create a Job Alert Interested in building your career at Figure? Get future opportunities sent straight to your email. Create alert Apply for this job * indicates a required field Quick Apply with MyGreenhouse First Name* Last Name* Preferred First Name Email* Phone Country Phone Resume/CV Attach Attach Dropbox Google Drive Enter manually Enter manually Accepted file types: pdf, doc, docx, txt, rtf Cover Letter Attach Attach Dropbox Google Drive Enter manually Enter manually Accepted file types: pdf, doc, docx, txt, rtf LinkedIn Profile Website Submit application | W38: https://job-boards.greenhouse.io/figureai/jobs/4626806006 | Z38: embodied_final | AA38: 是 | AB38: 核心基线3718 | AC38: O06022 | AD38: 感知决策与控制算法 | AE38: 视觉与多模态 | AF38: 原始6方向/17种类标签 | AG38: 高 | AH38: 正式基线 | AI38: e2a6b8fd0738e5f247fe | AJ38: 核心基线标签直接沿用 | AK38: Figure AI, Inc. | AL38: 企业别名精确匹配 | AM38: 高 | AN38: 已匹配 | AO38: 具身智能本体 | AP38: C轮>$1B（2025.9/估值$39B）；累计~$3.68B；微软/NVIDIA/OpenAI/英特尔/高通/LG等投资 | AQ38: https://www.figure.ai | AR38: 公司官网/Axios/Intel Capital/PitchBook | AS38: 中游-整机（人形机器人） | AT38: 全尺寸通用人形机器人 | AU38: C轮 | AV38: 海外 | AW38: 美国加利福尼亚州圣何塞(San Jose, CA)
A39: 38 | B39: O06025 | C39: 5928 | D39: Figure AI | E39: Figure AI | F39: Supplier Quality Engineer (Asia) | G39: 未说明 | J39: 未说明 | K39: 页面未说明或按原文保留，未根据职级推断。 | L39: 未说明 | M39: 中级 | N39: 感知决策与控制算法 | O39: 视觉与多模态 | P39: 中游 | Q39: 全尺寸通用人形机器人 | R39: C轮 | S39: 海外 | T39: 美国 加利福尼亚州 圣何塞 | U39: 计算机视觉 | V39: 页面职责段落显示：Responsibilities: Evaluate and qualify new suppliers, develop and implement quality plans for suppliers Monitor supplier performance metrics and drive improvement initiatives to meet or exceed quality targets. Review and verify quality inspection reports, including FAI report, outgoing QC report, in process quality, etc. Perform in person quality audit Review and feedback on vendor DFM and inspection plans Work with suppliers to resolve quality issues, perform root cause analysis, and implement corrective actions. Monitor supplier performance metrics and drive improvement Work with HQ to effectively and accurately communicate quality issues between Figure and the suppliers 【任职要求】 页面任职要求段落显示：Requirements: 5+ years of similar experiences in a manufacturing environment Being able to speak and write English fluently Being able to speak and write Mandarin Chinese fluently Able to read and interpret engineering drawings and CAD models Expert on GD&T ASME Y14.5-2009 or ASME Y14.5-2018 Expert on Sampling Plan C=0, and ASQ Z1.4/MIL-STD-105 Proficiency with common inspection tools, including Digital Height Gage, caliper, micrometer, thread gages, etc. Attention to detail: capable of maintaining precision in a fast-paced environment Knowledge with parts including injection molding, die casting, stamping Strong communication skills: good verbal and written communications skills with analytics and numeracy Ability to travel up to 50% of the time Being able to speak and write Mandarin Chinese fluently Bonus Qualifications: Certifications such as ASQ CQE, CQM, CRE, CQA. Robotics or other high tech industry experience Understanding of manufacturing processes, quality systems, and industrial engineering principles Knowledge with parts including PCBA, cables, wire harness assemblies, textiles The pay offered for this position may vary based on several individual factors, including job-related knowledge, skills, and experience. The total compensation package may also include additional components/benefits depending on the specific role. This information will be shared if an employment offer is extended. Create a Job Alert Interested in building your career at Figure? Get future opportunities sent straight to your email. Create alert Apply for this job * indicates a required field Quick Apply with MyGreenhouse First Name* Last Name* Preferred First Name Email* Phone Country Phone Resume/CV Attach Attach Dropbox Google Drive Enter manually Enter manually Accepted fi | W39: https://job-boards.greenhouse.io/figureai/jobs/4626809006 | Z39: embodied_final | AA39: 是 | AB39: 核心基线3718 | AC39: O06025 | AD39: 感知决策与控制算法 | AE39: 视觉与多模态 | AF39: 原始6方向/17种类标签 | AG39: 高 | AH39: 正式基线 | AI39: d248e8fb5c7b944eb36a | AJ39: 核心基线标签直接沿用 | AK39: Figure AI, Inc. | AL39: 企业别名精确匹配 | AM39: 高 | AN39: 已匹配 | AO39: 具身智能本体 | AP39: C轮>$1B（2025.9/估值$39B）；累计~$3.68B；微软/NVIDIA/OpenAI/英特尔/高通/LG等投资 | AQ39: https://www.figure.ai | AR39: 公司官网/Axios/Intel Capital/PitchBook | AS39: 中游-整机（人形机器人） | AT39: 全尺寸通用人形机器人 | AU39: C轮 | AV39: 海外 | AW39: 美国加利福尼亚州圣何塞(San Jose, CA)
A40: 39 | B40: O06039 | C40: 5965 | D40: Figure AI | E40: Figure AI | F40: AI Training Infrastructure Engineer – Humanoid Whole Body Control | G40: San Jose, CA | J40: 未说明 | K40: 页面未说明或按原文保留，未根据职级推断。 | L40: 未说明 | M40: 中级 | N40: 感知决策与控制算法 | O40: 视觉与多模态 | P40: 中游 | Q40: 全尺寸通用人形机器人 | R40: C轮 | S40: 海外 | T40: 美国 加利福尼亚州 圣何塞 | U40: Python; PyTorch; MuJoCo; 强化学习; 模仿学习; 计算机视觉; 动力学; 仿真 | V40: 页面职责段落显示：Responsibilities: Own and scale the infrastructure used to train whole-body control policies (simulation, data pipelines, orchestration, visualizations) Design systems that are fast, reliable, and highly configurable for our controls engineers Ensure high cluster utilization and minimal downtime—unblocking the team and accelerating iteration cycles Evaluate and integrate physics engines, simulation environments, and parameterizations to balance realism and training speed Optimize hyperparameters and infrastructure to maximize training speed and efficiency and final model performance Build robust tooling to take policies from training → validation → deployment on hardware 【任职要求】 页面任职要求段落显示：Requirements: Strong software engineering fundamentals with production experience in Python and PyTorch Experience building or scaling training infrastructure for robotics, control systems, or large-scale ML workloads Familiarity with physics simulation tools such as NVIDIA PhysX, MuJoCo, Warp, or PyBullet Working knowledge of dynamics, controls, and robotics systems Experience with reinforcement learning, imitation learning, or policy distillation Strong ownership mindset—you own systems that your teammates rely on every day Experience modeling contact interactions and photorealistic simulation environments for complex manipulation tasks Bonus Qualifications: Experience with humanoid or legged robot control Background in distributed systems, job schedulers, or cluster management Experience deploying ML models or control policies to real-world systems The US base salary range for this full-time position is between $200,000 and $350,000 annually. The pay offered for this position may vary based on several individual factors, including job-related knowledge, skills, and experience. The total compensation package may also include additional components/benefits depending on the specific role. This information will be shared if an employment offer is extended. Create a Job Alert Interested in building your career at Figure? Get future opportunities sent straight to your email. Create alert Apply for this job * indicates a required field Quick Apply with MyGreenhouse First Name* Last Name* Preferred First Name Email* Phone Country Phone Resume/CV* Attach Attach Dropbox Google Drive Enter manually Enter manually Accepted file types: pdf, doc, docx, txt, rtf Cover Letter Attach Attach Dropbox Google Drive Enter manually Enter manually Accepted file types: pdf, doc, d | W40: https://job-boards.greenhouse.io/figureai/jobs/4674754006 | Z40: embodied_final | AA40: 是 | AB40: 核心基线3718 | AC40: O06039 | AD40: 感知决策与控制算法 | AE40: 视觉与多模态 | AF40: 原始6方向/17种类标签 | AG40: 高 | AH40: 正式基线 | AI40: c3d7141f6844ca3045f6 | AJ40: 核心基线标签直接沿用 | AK40: Figure AI, Inc. | AL40: 企业别名精确匹配 | AM40: 高 | AN40: 已匹配 | AO40: 具身智能本体 | AP40: C轮>$1B（2025.9/估值$39B）；累计~$3.68B；微软/NVIDIA/OpenAI/英特尔/高通/LG等投资 | AQ40: https://www.figure.ai | AR40: 公司官网/Axios/Intel Capital/PitchBook | AS40: 中游-整机（人形机器人） | AT40: 全尺寸通用人形机器人 | AU40: C轮 | AV40: 海外 | AW40: 美国加利福尼亚州圣何塞(San Jose, CA)
A41: 40 | B41: O07662 | C41: 6009 | D41: Apptronik | E41: Apptronik | F41: Robot Platform Software Engineer | G41: Austin, TX | J41: 未说明 | K41: 页面未说明或按原文保留，未根据职级推断。 | L41: 未说明 | M41: 中级 | N41: 软件硬件与系统架构 | O41: 软件与系统 | P41: 中游 | Q41: 人形机器人/工业机器人/模块化机器人 | R41: B轮 | S41: 海外 | T41: 美国 得克萨斯州 奥斯汀 | U41: C++; 嵌入式开发; CAN; EtherCAT; 传感器; Linux; Docker; Kubernetes | V41: 页面职责段落显示：ESSENTIAL DUTIES AND RESPONSIBILITIES or KEY ACCOUNTABILITIES Platform Evolution: Contribute to the development and implementation of scalable software solutions that evolve existing architectures to support next-generation robotic systems. Architecture: Participate in architectural discussions and provide technical input to help define the roadmap for platform software, focusing on modularity and performance. Hardware-Software Integration: Work closely with hardware teams to execute de-risking tasks and validate new components, ensuring reliable communication and integration across the robotic stack. Resource Profiling: Assist in evaluating compute resource 【任职要求】 页面任职要求段落显示：requirements by profiling complex software stacks and identifying opportunities for optimization in constrained environments. System Adaptation: Support the porting and optimization of established software frameworks to new hardware platforms, maintaining high standards for system stability and reliability. Performance Benchmarking: Conduct profiling and benchmarking tests to identify system bottlenecks, helping to ensure the platform scales effectively across diverse hardware. Engineering Standards: Adhere to and promote software engineering best practices, including participating in code reviews, maintaining clear documentation, and contributing to continuous integration efforts. SKILLS AND REQUIREMENTS Strong C++ Command: Proficiency in C++ within a Linux environment, with experience in system-level programming and an understanding of performance-sensitive code. Architectural Awareness: Solid understanding of complex, multi-component system architectures and the ability to contribute meaningful design ideas for safety and scalability. Hardware Interaction: Experience with hardware integration and testing, including familiarity with low-level drivers, communication protocols (e.g., CAN, EtherCAT), or sensor data handling. Analytical Profiling: Ability to perform resource usage analysis (CPU, memory, latency) to help inform system specifications and hardware selection. Adaptability with Existing Code: Proven ability to work within and improve established codebases, balancing the need for modernization with a respect for proven architectural foundations. Distributed Systems: Familiarity with API design, and containerization tools like Docker or Kubernetes in a robotics or embedded context. Collaborative Mindset: Strong communication skills and the ability to | W41: https://job-boards.greenhouse.io/apptronik/jobs/5813642004 | Z41: embodied_final | AA41: 是 | AB41: 核心基线3718 | AC41: O07662 | AD41: 软件硬件与系统架构 | AE41: 软件与系统 | AF41: 原始6方向/17种类标签 | AG41: 高 | AH41: 正式基线 | AI41: f1f952c32c4a7e1729cc | AJ41: 核心基线标签直接沿用 | AK41: Apptronik, Inc. | AL41: 企业别名精确匹配 | AM41: 高 | AN41: 已匹配 | AO41: 具身智能本体 | AP41: B轮（2026年2月完成5.2亿美元融资），累计融资超10亿美元，投后估值约50亿美元 | AQ41: https://apptronik.com | AR41: 公司官网、36氪、搜狐网、新浪财经、抖音百科 | AS41: 中游-整机制造+上游-核心技术 | AT41: 人形机器人/工业机器人/模块化机器人 | AU41: B轮 | AV41: 海外 | AW41: 美国得克萨斯州奥斯汀(Austin, TX)
A42: 41 | B42: O01793 | C42: 5114 | D42: 智元机器人 | E42: 智元机器人 | F42: 上海 Sales Manager | H42: 50-80k·16薪 | I42: 本科 | J42: 本科 | L42: 未说明 | M42: 中级 | N42: 软件硬件与系统架构 | O42: 软件与系统 | P42: 中游 | Q42: 通用人形机器人; 具身智能全栈 | R42: C轮 | S42: 华东 | T42: 上海市临港新片区 | U42: 动力学 | V42: Are you ready to lead the commercial rollout of a company that is redefining the physical capabilities of AI? Job Title: Sales Manager Location: U.S. Based (Remote) About this role We are looking for a professional to lead our market expansion in America. This role is responsible for identifying business opportunities, managing the enterprise sales cycle, and establishing a local partner ecosystem to support our business objectives. Key Responsibilities - Market Analysis: Track North American industry trends and competitor dynamics to identify actionable market opportunities. - Enterprise Sales: Manage the full sales life cycle for major corporate clients, including prospecting, business negotiations, and contract execution. - Account Management: Oversee the delivery of service to key accounts to ensure customer satisfaction and drive recurring or large-scale procurement. - Partner Development: Build a local partner network and represent the company at industry events and trade organizations to integrate into the local industrial ecosystem. Cross-Departmental Collaboration: Coordinate with internal teams to align market strategies and ensure smooth implementation. -Product Feedback Loop: Provide timely, data-backed feedback on local client needs to help refine product offerings and sales models for the North American market. -Performance Tracking: Analyze sales data, track key metrics, and report on performance against business targets. Job Requirements - Bachelor’s degree or higher in a relevant field. - 5+ years of experience in business development or sales in the North American market. Prior experience in robotics, industrial automation, or complex B2B solutions is required. - Proven ability to handle cross-border communication and collaboration between China and North America. - Demonstrated ability in large-scale account management, complex negotiations, and managing client relationships at the corporate level. - Capable of independent project management, cross-departmental resource coordination, and achieving sales KPIs in a fast-paced, results-oriented environment. - Adaptable to startup culture, with a focus on practical problem-solving and meeting business deadlines. About AGIBOT Founded in 2023, AGIBOT is a global leader in Embodied AI and humanoid robotics. We pioneer the mass production of general-purpose intelligent machines that are actively deployed across real-world industrial and commercial sectors worldwide. | W42: https://www.liepin.com/job/1983674077.shtml | Z42: all_jobs_jd | AA42: 是 | AB42: 核心基线3718 | AC42: O01793 | AD42: 软件硬件与系统架构 | AE42: 软件与系统 | AF42: 原始6方向/17种类标签 | AG42: 高 | AH42: 正式基线 | AI42: e507bcb38f960be66337 | AJ42: 核心基线标签直接沿用 | AK42: 智元创新（上海）科技股份有限公司 | AL42: 企业别名精确匹配 | AM42: 高 | AN42: 已匹配 | AO42: 具身智能本体 | AP42: C轮；成立3年融资12轮; 最新估值约150亿元人民币; 投资方含红杉中国、高瓴创投、蓝驰创投、中金资本等顶级机构; 2025年营收突破10亿元 | AQ42: https://zhiyuan-robot.com | AR42: zhiyuan-robot.com官方网站; 36氪; 经济观察报; 长江日报; 南方日报; 投资界; 猎云网; 腾讯新闻; store.agibot.com; 界面新闻; 新华网 | AS42: 中游-整机+算法（软硬全栈） | AT42: 全尺寸人形机器人/四足机器人/具身智能操作系统 | AU42: 已上市 | AV42: 华东 | AW42: 上海市浦东新区临港新片区
A43: 42 | B43: O06014 | C43: 5903 | D43: Figure AI | E43: Figure AI | F43: Helix AI Engineer, Training Infrastructure | G43: Helix AI Engineer, Training Infrastructure | J43: 未说明 | K43: 页面未说明或按原文保留，未根据职级推断。 | L43: 未说明 | M43: 中级 | N43: 感知决策与控制算法 | O43: 视觉与多模态 | P43: 中游 | Q43: 全尺寸通用人形机器人 | R43: C轮 | S43: 海外 | T43: 美国 加利福尼亚州 圣何塞 | U43: Python; PyTorch; CUDA; 深度学习; 计算机视觉; Kubernetes | V43: 页面职责段落显示：Responsibilities Design, deploy, and maintain Figure's training clusters Architect, optimize, and maintain scalable deep learning frameworks for training on massive robot datasets Work together with AI researchers to implement training of new model architectures at a large scale Implement distributed training, advanced parallelization strategies, and high-performance data loaders to reduce model development cycles Profile, identify, and eliminate training bottlenecks at the hardware and software levels to maximize Model FLOPs Utilization (MFU) Implement tooling for data processing, model experimentation, and continuous integration 【任职要求】 页面任职要求段落显示：Requirements Strong software engineering fundamentals Bachelor's or Master's degree in Computer Science, Robotics, Engineering, or a related field Extensive professional experience with Python and PyTorch Proven track record of scaling and running large-scale training experiments personally on 800+ GPUs Experience managing HPC clusters for deep neural network training Minimum of 4 years of professional, full-time experience building reliable backend systems and infrastructure Bonus Qualifications Experience contributing to or maintaining open-source distributed training frameworks (Megatron-LM, DeepSpeed, TorchTitan) Experience managing cloud infrastructure (AWS, Azure, GCP) Experience with job scheduling / orchestration tools (SLURM, Kubernetes, LSF, etc.) Experience with configuration management tools (Ansible, Terraform, Puppet, Chef, etc.) Deep understanding of CUDA and hands-on experience writing custom GPU kernels to optimize training The US base salary range for this full-time position is between $150,000 - $350,000 annually. The pay offered for this position may vary based on several individual factors, including job-related knowledge, skills, and experience. The total compensation package may also include additional components/benefits depending on the specific role. This information will be shared if an employment offer is extended. Create a Job Alert Interested in building your career at Figure? Get future opportunities sent straight to your email. Create alert Apply for this job * indicates a required field Quick Apply with MyGreenhouse First Name* Last Name* Email* Phone Country Phone Resume/CV Attach Attach Dropbox Google Drive Enter manually Enter manually Accepted file types: pdf, doc, docx, txt, rtf LinkedIn Profile Website Submit application | W43: https://job-boards.greenhouse.io/figureai/jobs/4431092006 | Z43: embodied_final | AA43: 是 | AB43: 核心基线3718 | AC43: O06014 | AD43: 感知决策与控制算法 | AE43: 视觉与多模态 | AF43: 原始6方向/17种类标签 | AG43: 高 | AH43: 正式基线 | AI43: a24858a8a280d19fcf06 | AJ43: 核心基线标签直接沿用 | AK43: Figure AI, Inc. | AL43: 企业别名精确匹配 | AM43: 高 | AN43: 已匹配 | AO43: 具身智能本体 | AP43: C轮>$1B（2025.9/估值$39B）；累计~$3.68B；微软/NVIDIA/OpenAI/英特尔/高通/LG等投资 | AQ43: https://www.figure.ai | AR43: 公司官网/Axios/Intel Capital/PitchBook | AS43: 中游-整机（人形机器人） | AT43: 全尺寸通用人形机器人 | AU43: C轮 | AV43: 海外 | AW43: 美国加利福尼亚州圣何塞(San Jose, CA)
A44: 43 | B44: O06047 | C44: 5954 | D44: Figure AI | E44: Figure AI | F44: Hardware Technician (TeleOperations) | G44: San Jose, CA | J44: 未说明 | K44: 页面未说明或按原文保留，未根据职级推断。 | L44: 未说明 | M44: 中级 | N44: 感知决策与控制算法 | O44: 视觉与多模态 | P44: 中游 | Q44: 全尺寸通用人形机器人 | R44: C轮 | S44: 海外 | T44: 美国 加利福尼亚州 圣何塞 | U44: Python; ROS; ROS2; 计算机视觉; 标定 | V44: 页面职责段落显示：Responsibilities: Set up, configure, and maintain VR/AR headsets and teleoperation equipment Install, image, and configure laptops and workstations for the Pilot team Troubleshoot hardware and network connectivity, performance, and calibration issues Perform routine maintenance and calibration on teleoperation systems Configure and manage network infrastructure, including switches, access points, and routers Diagnose and resolve network issues including packet loss, bandwidth degradation, and intermittent drops that affect teleoperation sessions Create and maintain documentation, setup guides, and troubleshooting procedures 【任职要求】 页面任职要求段落显示：Requirements: 2+ years of experience in hardware support, IT technician, or similar technical role Hands-on experience with VR/AR headset setup and maintenance Strong troubleshooting skills for hardware, connectivity, and system configuration issues Experience with laptop/PC imaging, configuration, and deployment Familiarity with basic electronics, cable management, and equipment calibration Basic networking knowledge and setup experience (Wi-Fi configuration, IP addressing, router provisioning, troubleshooting connectivity issues) Excellent documentation and communication skills Ability to lift equipment up to 30 lbs and work in a lab environment Detail-oriented with strong organizational skills Bonus Qualifications: Experience in robotics, manufacturing, or automation environments Familiarity with ROS (Robot Operating System) or robotics platforms Background in motion capture or VR/AR gaming systems Basic scripting skills (Python, Bash) Associate degree or certification in electronics, IT, or related field The US base salary range for this full-time position is between $85,000 - $110,000 annually. The pay offered for this position may vary based on several individual factors, including job-related knowledge, skills, and experience. The total compensation package may also include additional components/benefits depending on the specific role. This information will be shared if an employment offer is extended. Create a Job Alert Interested in building your career at Figure? Get future opportunities sent straight to your email. Create alert Apply for this job * indicates a required field Quick Apply with MyGreenhouse First Name* Last Name* Email* Phone Country Phone Resume/CV Attach Attach Dropbox Google Drive Enter manually Enter manually Accepted file types: | W44: https://job-boards.greenhouse.io/figureai/jobs/4666292006 | Z44: embodied_final | AA44: 是 | AB44: 核心基线3718 | AC44: O06047 | AD44: 感知决策与控制算法 | AE44: 视觉与多模态 | AF44: 原始6方向/17种类标签 | AG44: 高 | AH44: 正式基线 | AI44: 5c2175c5ee263a7ce460 | AJ44: 核心基线标签直接沿用 | AK44: Figure AI, Inc. | AL44: 企业别名精确匹配 | AM44: 高 | AN44: 已匹配 | AO44: 具身智能本体 | AP44: C轮>$1B（2025.9/估值$39B）；累计~$3.68B；微软/NVIDIA/OpenAI/英特尔/高通/LG等投资 | AQ44: https://www.figure.ai | AR44: 公司官网/Axios/Intel Capital/PitchBook | AS44: 中游-整机（人形机器人） | AT44: 全尺寸通用人形机器人 | AU44: C轮 | AV44: 海外 | AW44: 美国加利福尼亚州圣何塞(San Jose, CA)
A45: 44 | B45: O07687 | C45: 5650 | D45: 吉翼具身智能 | E45: 吉翼具身智能 | F45: 硬件资深工程师（座舱/智驾/机器人大小脑） | G45: 北京 | J45: 未说明 | K45: 页面未说明或按原文保留，未根据职级推断。 | L45: 未说明 | M45: 高级 | N45: 基础理论与前沿研究 | O45: 基础与前沿研究 | P45: 中游 | Q45: 工业机器人、商业服务机器人、具身智能大模型、工业质检、智能装备 | R45: 天使轮/种子轮 | S45: 东北 | T45: 吉林省长春市北湖科技开发区 | U45: C++; 多模态; 仿真; 嵌入式开发; MCU; 电机驱动; 传感器; PCB设计 | V45: 页面职责段落显示：岗位职责: 1、 硬件需求分析： 参与具身智能机器人电气硬件系统需求分析,拆分硬件平台设计要求； 2、电路原理图设计： 负责机器人整机或核心部件（如大小脑、运控、关节等）的原理图设计、PCB布局，以及低压电源分配设计，确保设计满足信号完整性、电源完整性、EMC/EMI等要求； 3、硬件调试与测试： 对设计的硬件电路进行初步调试，使用示波器、万用表、逻辑分析仪等工具排查硬件问题。编写和执行硬件测试方案，验证设计的功能、性能和可靠性，确保硬件满足开发和生产需求； 4、物料管理与供应链协作： 协助建立和管理物料清单（BOM），跟踪物料采购进度。与采购、生产、质量等部门协作，解决物料和生产过程中的电气硬件问题； 5、技术文档撰写： 编写硬件设计说明、HSI、DFMEA、WCCA、FMEDA、测试报告等相关技术文档，并对设计方案进行评审和汇报； 6、技术预研与创新： 关注机器人领域前沿电气硬件技术，参与新技术的预研和方案验证，不断优化硬件设计，提升机器人性能； 7、成本优化：对具身智能机器人系统各组件成本保持敏感，从硬件设计视角提出成本优化方案和实现路径。 【任职要求】 页面任职要求段落显示：任职要求: 1、学历背景： 电子工程、自动化、通信工程、微电子等相关专业本科及以上学历； 2、专业知识： (1)扎实的模拟电路、数字电路、电源电路、高频电路设计理论和实践经验。 (2)熟悉常用微控制器（MCU）、嵌入式处理器SOC、FPGA等的工作原理和应用。 (3)熟悉各类传感器（编码器、IMU、力觉传感器、视觉传感器等）的接口原理和驱动。 (4)熟悉电机驱动器、功率器件、通信协议（如CAN, SPI, I2C, Ethernet等）的设计和应用。 (5)掌握高速/低速信号设计,精通高速/低速通信物理层原理。 (6)熟悉EMC/EMI设计与整改，了解相关标准。 3、工作经验： 具备机器人、无人机、消费电子、工业自动化等领域电气硬件设计经验者优先。有具身智能机器人相关项目经验者更佳； 4、技能掌握： 熟练使用至少一种主流EDA工具进行电路设计，具备一定的电路板（PCB）设计经验。 熟练使用示波器、逻辑分析仪、信号发生器等硬件调试和测试仪器。 具备一定的嵌入式软件开发基础（如C/C++）者优先； 5、能力素质： 具备良好的分析问题、解决问题的能力，较强的学习能力和创新精神；良好的沟通协调能力和团队合作意识；责任心强，工作主动性高。 备注： 汽车座舱或者智驾，机器人大小脑优先。 其他信息 行业要求：全部行业 公司简介 吉林省吉翼具身智能机器人有限公司（简称“吉翼智能”）成立于2025年8月，由捷翼科技领衔，省市区三级产业基金及科研团队等实力机构联合组建，形成涵盖机器人"小脑"仿真引擎与"智慧大脑"算法的技术体系和“产学研用”深度融合的创新平台。吉翼具身智能主营业务涵盖制造、智能算法开发、人工智能硬件销售及机器人操作系统研发，并通过整合多模态大模型、运动规划等技术，布局工业制造、智能物流及智慧医疗领域。吉翼具身智能致力于成为全球优秀的以真实场景为牵引的具身智能机器人平台型公司，打造从工业场景到家庭康养场景的全栈智能化产品矩阵。 公司立足发展和培育智慧大脑，在长春、北京、上海、深圳一线城市CBD区域，广招行业专家和工程师们加入，已经引入各领域首席科学家、架构师、专家等一系列资深行业从业者加入，进行原型机的研发工作。 以热爱为锚点，我们期待具身智能各个领域的行业专家和资深从业者加入！ 查看全部 猎聘温馨提示： 1. 如您发现平台内招聘方存在以下违规行为的，请立即 | W45: https://www.liepin.com/job/1984018863.shtml?pgRef=c_pc_company_home_page%3Ac_pc_company_home_job_listcard%402_84018863%3A1%3Agw.2a797a33-596594383 | Z45: all_jobs_jd;embodied_final | AA45: 是 | AB45: 核心基线3718 | AC45: O07687 | AD45: 基础理论与前沿研究 | AE45: 基础与前沿研究 | AF45: 原始6方向/17种类标签 | AG45: 高 | AH45: 正式基线 | AI45: a7c84ca35c1f4854d619 | AJ45: 核心基线标签直接沿用 | AK45: 吉林省吉翼具身智能机器人有限公司 | AL45: 企业别名精确匹配 | AM45: 高 | AN45: 已匹配 | AO45: 具身智能本体 | AP45: 已完成天使轮融资，由捷翼科技、吉林省/市/区三级产业基金共同投资，注册资本16.33亿元，后续持续获得产业资本加持 | AQ45: 未公开 | AR45: 吉林省人民政府官网、企查查、深信服官网、今日头条、BOSS直聘 | AS45: 中游-整机制造+核心算法+上游-核心零部件 | AT45: 工业机器人、商业服务机器人、具身智能大模型、工业质检、智能装备 | AU45: 天使轮/种子轮 | AV45: 东北 | AW45: 吉林省长春市北湖科技开发区长新创谷
